Workbook

Sheet feature_catalog
A1: source_column | B1: feature_name | C1: type | D1: description | E1: exemple | F1: relevant_roles | G1: inverted | H1: feat_col | I1: z_col
A2: goals | B2: goals_p90 | C2: vol | D2: But marqué — ballon franchissant entièrement la ligne de but, attribué au dernier joueur ayant touché le ballon intentionnellement | E2: Haaland reprend un centre de Bernardo Silva du pied droit — but | F2: CF|W|AM|SS | G2: False | H2: feat_goals_p90 | I2: z_goals_p90
A3: expectedGoals | B3: xg_p90 | C3: vol | D3: Probabilité qu'un tir donné se transforme en but, calculée sur la base de situations similaires dans la base historique Opta (~1 million de tirs). Facteurs : position, partie du corps, type de situation (ouvert/corner/coup franc), pression défensive. Échelle 0-1. | E3: Tir du pied droit à 12m face au but, sans gardien sorti : xG=0.38. Même tir de l'extérieur de la surface : xG=0.05 | F3: CF|W|AM|SS|CM | G3: False | H3: feat_xg_p90 | I3: z_xg_p90
A4: np_xg | B4: npxg_p90 | C4: vol | D4: xG total du joueur sur la saison, pénaltys exclus. Les pénaltys étant des tirs à xG fixe ~0.76 quelle que soit la qualité du tireur, ils sont retirés pour mesurer la vraie qualité des occasions en jeu ouvert. | E4: Joueur avec 18 xG dont 4 sur pénaltys → npxG = 14 | F4: CF|W|AM|SS|CM | G4: False | H4: feat_npxg_p90 | I4: z_npxg_p90
A5: xGChain_us | B5: xgchain_p90 | C5: vol | D5: Somme des xG de toutes les occasions auxquelles le joueur a participé dans la séquence de jeu, qu'il ait tiré, passé, ou simplement touché le ballon à n'importe quel moment de l'action. Très inclusif. | E5: Modric touche le ballon 3 passes avant le tir de Benzema (xG=0.25) → Modric reçoit 0.25 dans son xGChain | F5: CF|W|AM|CM|DM|FB | G5: False | H5: feat_xgchain_p90 | I5: z_xgchain_p90
A6: xGBuildup_us | B6: xgbuildup_p90 | C6: vol | D6: xGChain moins la contribution directe du tireur (xG) et du passeur décisif (xA). Mesure exclusivement les touches 'invisibles' en amont de la phase finale — la contribution à la construction profonde. | E6: Cancelo → De Bruyne → Haaland (but, xG=0.45). Cancelo : xGBuildup=0.45. De Bruyne : xGBuildup=0 (passeur déc. exclu). Haaland : xGBuildup=0 (tireur exclu) | F6: CM|DM|CB|FB|AM | G6: False | H6: feat_xgbuildup_p90 | I6: z_xgbuildup_p90
A7: totalShots | B7: shots_p90 | C7: vol | D7: Toute tentative délibérée de marquer, qu'elle soit cadrée, non-cadrée, bloquée ou sur le poteau. Exclut : les centres rentrants comptés comme but, les dégagements comptés comme tir. | E7: Frappe de 25m qui finit en tribunes = 1 tir. Tir bloqué par un défenseur = 1 tir (mais pas cadré) | F7: CF|W|AM | G7: False | H7: feat_shots_p90 | I7: z_shots_p90
A8: shotsFromInsideTheBox | B8: shots_inside_p90 | C8: vol | D8: Tirs tentés depuis l'intérieur de la surface de réparation (18 yards). Sous-ensemble de totalShots mesurant la présence offensive dans la zone de vérité, indépendamment de la précision. | E8: Haaland contrôle dans la surface à 7m et frappe au but = 1 tir depuis l'intérieur de la surface | F8: CF|W|AM | G8: False | H8: feat_shots_inside_p90 | I8: z_shots_inside_p90
A9: headedGoals | B9: headed_goals_p90 | C9: vol | D9: Buts marqués de la tête — sous-ensemble de goals attribués à une touche de tête intentionnelle. Indicateur de domination aérienne offensive. | E9: Giroud détourne un corner de la tête en haut du filet = 1 headed goal | F9: CF|CD | G9: False | H9: feat_headed_goals_p90 | I9: z_headed_goals_p90
A10: _npxg_proxy_p90 | B10: npxg_proxy_p90 | C10: vol | D10: Proxy npxG calculé depuis les données Opta : xG total (expectedGoals) moins la contribution estimée des pénaltys (penaltiesTaken × 0.76). Clip à 0 pour éviter les valeurs négatives. | E10: Joueur avec expectedGoals=12.5 et penaltiesTaken=3 → npxg_proxy = 12.5 − 3×0.76 = 10.22 | F10: CF|W|AM|SS|CM | G10: False | H10: feat_npxg_proxy_p90 | I10: z_npxg_proxy_p90
A11: shotsOnTarget | B11: shots_ot_p90 | C11: vol | D11: Tir cadré = tir qui serait rentré sans intervention du gardien ou du dernier défenseur. Inclut les buts. Exclut les tirs bloqués par un défenseur ordinaire (non dernier défenseur) et les tirs sur le poteau. | E11: Tir stoppé par le gardien = cadré. Tir bloqué par un défenseur en dehors de la ligne = non cadré. Tir sur le poteau = non cadré | F11: CF|W|AM | G11: False | H11: feat_shots_ot_p90 | I11: z_shots_ot_p90
A12: goalConversionPercentage | B12: goal_conv_pct | C12: pct | D12: Buts divisés par tirs totaux tentés, exprimé en pourcentage. Mesure l'efficacité brute de finition. Ne tient pas compte de la qualité des occasions (contrairement à xG). | E12: 10 buts sur 50 tirs = 20%. Valeur moyenne PL ≈ 10-12% | F12: CF|W|AM | G12: False | H12: feat_goal_conv_pct | I12: z_goal_conv_pct
... A96: market_value | B96: market_value | C96: raw | D96: Estimation de la valeur marchande actuelle du joueur par la communauté Transfermarkt, mise à jour périodiquement. Basée sur l'âge, les performances, le contrat restant, l'inflation du marché. N'est pas une valeur contractuelle — c'est une estimation de ce qu'un club paierait. | E96: Bellingham évalué 200M€ = estimation TM communauté, pas valeur contractuelle. Kane à 30 ans : 80M€ vs 150M€ à 27 ans (décote âge) | F96: ALL | G96: False | H96: feat_market_value | I96: z_market_value
A97: derived | B97: np_goals_minus_npxg | C97: derived | D97: Différentiel de finition : buts hors-pénalty par 90 min moins npxG par 90 min (source Understat). Valeur positive = surperforme ses xG (bon finisseur). Valeur négative = sous-performe. Calculé comme npGoals_p90 - npxg_p90, où npGoals = goals - penalty_goals. | E97: Haaland npGoals_p90=0.85, npxg_p90=0.62 → différentiel=+0.23 (excellent finisseur). Joueur moyen ≈ 0. Buteur chanceux ≈ -0.10 | F97: CF|W|AM|SS | G97: FALSE | H97: feat_np_goals_minus_npxg | I97: z_np_goals_minus_npxg
A98: progressiveCarries | B98: prog_carries_p90 | C98: vol | D98: Conduites progressives par 90 min — conduites de balle avançant d'au moins 10 yards vers le but adverse (ou entrant dans la surface de réparation). Mesure la capacité à porter le ballon dans le dos de la défense et créer des situations dangeureuses par la percussion balle au pied. | E98: Mbappé part côté gauche, conduit 15m vers l'intérieur et arrive à l'entrée de la surface = 1 progressive carry. Vinicius : 6-8 progressive carries/match = profil percuteur élite | F98: W|CF|AM|CM|FB | G98: FALSE | H98: feat_prog_carries_p90 | I98: z_prog_carries_p90
A99: touchesInBox | B99: touches_box_p90 | C99: vol | D99: Touches de balle dans la surface de réparation adverse (18 yards) par 90 min. Mesure la présence physique dans la zone de vérité — combinaison de courses, de remises, de fixations et de tirs depuis la surface. Indicateur clé pour les avant-centres et ailiers qui finissent. | E99: Giroud reçoit un centre dans la surface, remet de la tête = 1 touch in box. Haaland contrôle et frappe = 1 touch in box. Valeur top CF PL ≈ 6-10/match | F99: CF|W|AM|SS | G99: FALSE | H99: feat_touches_box_p90 | I99: z_touches_box_p90

Sheet gardien_classique
A1: source_column | B1: feature_name | C1: type | D1: description | E1: exemple | F1: relevant_roles | G1: inverted | H1: feat_col | I1: z_col | J1: source_column | K1: Pondération
A2: accuratePasses | B2: acc_passes_p90 | C2: vol | D2: Nombre absolu de passes réussies sur la saison — passe qu'un coéquipier contrôle. Converti en per-90 pour la comparaison inter-joueurs. Exclut les corners, remises en jeu et dégagements gardien. | E2: Kroos : 85 passes réussies en 90min = 85 acc_passes pour ce match. Moyenne DM = 60-80 per-90 | F2: CM|DM|CB|AM | G2: FALSE | H2: feat_acc_passes_p90 | I2: z_acc_passes_p90 | J2: accuratePasses | K2: 1 | L2: =IFERROR(_xlfn.XLOOKUP(J2,feature_catalog!A:A,feature_catalog!A:A),"") -> accuratePasses
A3: accuratePassesPercentage | B3: pass_acc_pct | C3: pct | D3: Passes réussies divisées par passes tentées. Une passe est réussie si un coéquipier la contrôle. Exclut les corners, remises en jeu, dégagements du gardien et centres (comptés séparément). | E3: Kroos : 85 passes réussies / 90 tentées = 94.4%. Moyenne DM Premier League ≈ 82% | F3: CM|DM|CB|FB|AM|GK | G3: FALSE | H3: feat_pass_acc_pct | I3: z_pass_acc_pct | J3: accuratePassesPercentage | L3: =IFERROR(_xlfn.XLOOKUP(J3,feature_catalog!A:A,feature_catalog!A:A),"") -> accuratePassesPercentage
A4: accurateLongBalls | B4: long_balls_p90 | C4: vol | D4: Passes longues réussies — ballon joué en hauteur sur une distance significative (généralement >32m) récupéré par un coéquipier. Comptées en absolu per-90. | E4: Rúben Dias joue 8 longues passes dont 6 arrivent à un coéquipier = 6 long balls réussies | F4: CB|DM|GK|CM | G4: FALSE | H4: feat_long_balls_p90 | I4: z_long_balls_p90 | J4: accurateLongBalls | L4: =IFERROR(_xlfn.XLOOKUP(J4,feature_catalog!A:A,feature_catalog!A:A),"") -> accurateLongBalls
A5: accurateLongBallsPercentage | B5: long_balls_pct | C5: pct | D5: Passes longues réussies sur passes longues tentées. Une passe longue est définie par Opta comme un ballon joué en hauteur sur une distance significative (généralement >32m). Indicateur clé des CBs relanceurs et gardiens modernes. | E5: Rúben Dias joue 8 longues passes, 6 arrivent à un coéquipier = 75% long balls | F5: CB|DM|GK|CM | G5: FALSE | H5: feat_long_balls_pct | I5: z_long_balls_pct | J5: accurateLongBallsPercentage | K5: 1 | L5: =IFERROR(_xlfn.XLOOKUP(J5,feature_catalog!A:A,feature_catalog!A:A),"") -> accurateLongBallsPercentage
A6: errorLeadToGoal | B6: errors_goal_p90 | C6: vol | D6: Erreur individuelle d'un joueur menant DIRECTEMENT à un but encaissé. L'erreur doit être la cause directe sans phase de jeu intermédiaire. Très rare — 0 à 2 occurrences par saison pour la plupart des joueurs. | E6: Maguire perd le ballon dans sa propre surface, l'adversaire marque immédiatement = 1 errorLeadToGoal. Feature à inverser | F6: CD|GK|FB | G6: TRUE | H6: feat_errors_goal_p90 | I6: z_errors_goal_p90 | J6: errorLeadToGoal | L6: =IFERROR(_xlfn.XLOOKUP(J6,feature_catalog!A:A,feature_catalog!A:A),"") -> errorLeadToGoal
A7: errorLeadToShot | B7: errors_shot_p90 | C7: vol | D7: Erreur menant DIRECTEMENT à un tir adverse, but ou non. Sur-ensemble de errorLeadToGoal — chaque errorLeadToGoal est aussi un errorLeadToShot mais pas l'inverse. Légèrement plus fréquent (2-6/saison). | E7: Stones glisse et offre le ballon à Salah qui tire (gardien arrête) = 1 errorLeadToShot mais pas errorLeadToGoal | F7: CD|GK|FB | G7: TRUE | H7: feat_errors_shot_p90 | I7: z_errors_shot_p90 | J7: errorLeadToShot | K7: 3 | L7: =IFERROR(_xlfn.XLOOKUP(J7,feature_catalog!A:A,feature_catalog!A:A),"") -> errorLeadToShot
A8: headedClearances | B8: headed_clear_p90 | C8: vol | D8: Sous-ensemble des clearances : dégagements effectués de la tête uniquement. Indicateur de domination aérienne défensive dans la surface propre. | E8: Dias dégage un corner adverse de la tête = 1 headed clearance | F8: CB|GK | G8: FALSE | H8: feat_headed_clear_p90 | I8: z_headed_clear_p90 | J8: headedClearances | L8: =IFERROR(_xlfn.XLOOKUP(J8,feature_catalog!A:A,feature_catalog!A:A),"")
A9: saves | B9: saves_p90 | C9: vol | D9: Arrêts réalisés — tirs cadrés adverses stoppés par le gardien. Comptés uniquement sur les tirs qui auraient constitué un but sans l'intervention. Corrélé au volume de tirs adverses reçus. | E9: Alisson arrête un tir de Salah au premier poteau = 1 save. Alisson dévie un tir qui allait à côté = 0 save (pas cadré) | F9: GK | G9: FALSE | H9: feat_saves_p90 | I9: z_saves_p90 | J9: saves | L9: =IFERROR(_xlfn.XLOOKUP(J9,feature_catalog!A:A,feature_catalog!A:A),"") -> saves
A10: cleanSheet | B10: clean_sheets_p90 | C10: vol | D10: Match sans but encaissé — gardien ayant tenu sa cage à zéro pour la totalité du match joué. Per-90 utilisé comme proportion de matchs à zéro. Corrélé à la qualité défensive collective. | E10: Ederson joue 90min sans encaisser = 1 cleanSheet. Ederson sort à la 80e (0-0), remplaçant encaisse = pas de cleanSheet | F10: GK | G10: FALSE | H10: feat_clean_sheets_p90 | I10: z_clean_sheets_p90 | J10: cleanSheet | L10: =IFERROR(_xlfn.XLOOKUP(J10,feature_catalog!A:A,feature_catalog!A:A),"") -> cleanSheet
A11: savedShotsFromInsideTheBox | B11: saves_inside_p90 | C11: vol | D11: Arrêts sur tirs depuis l'intérieur de la surface de réparation — sous-ensemble des saves sur les tirs les plus dangereux (zone de vérité). Indicateur du niveau de difficulté des arrêts réalisés. | E11: Alisson arrête une frappe à bout portant de Haaland à 6m = 1 savedShotFromInsideTheBox | F11: GK | G11: FALSE | H11: feat_saves_inside_p90 | I11: z_saves_inside_p90 | J11: savedShotsFromInsideTheBox | L11: =IFERROR(_xlfn.XLOOKUP(J11,feature_catalog!A:A,feature_catalog!A:A),"") -> savedShotsFromInsideTheBox
A12: savedShotsFromOutsideTheBox | B12: saves_outside_p90 | C12: vol | D12: Arrêts sur tirs depuis l'extérieur de la surface — saves sur frappes lointaines. Généralement plus prévisibles mais peuvent être déviées. Indicateur du volume de tirs lointains arrêtés. | E12: Alisson arrête une frappe de 25m de Salah qui allait dans le coin = 1 savedShotFromOutsideTheBox | F12: GK | G12: FALSE | H12: feat_saves_outside_p90 | I12: z_saves_outside_p90 | J12: savedShotsFromOutsideTheBox | L12: =IFERROR(_xlfn.XLOOKUP(J12,feature_catalog!A:A,feature_catalog!A:A),"") -> savedShotsFromOutsideTheBox
A13: crossesNotClaimed | B13: crosses_not_claimed_p90 | C13: vol | D13: Centres non interceptés par le gardien — ballon joué depuis les côtés vers la surface que le gardien n'a pas capté ni dégagé. Feature à inverser : plus ce nombre est élevé, moins le gardien contrôle sa surface. | E13: Un corner arrive dans la surface, Courtois ne sort pas et le ballon traîne = 1 crossNotClaimed | F13: GK | G13: TRUE | H13: feat_crosses_not_claimed_p90 | I13: z_crosses_not_claimed_p90 | J13: crossesNotClaimed | L13: =IFERROR(_xlfn.XLOOKUP(J13,feature_catalog!A:A,feature_catalog!A:A),"") -> crossesNotClaimed
A14: _penalty_save_pct | B14: penalty_save_pct | C14: pct | D14: % pénaltys arrêtés = penaltySave / penaltyFaced × 100. Mesure la performance du gardien sur penalty. Calculé uniquement pour les gardiens ayant fait face à au moins 1 pénalty saison. | E14: Alisson face à 5 pénaltys, en arrête 2 = 40% penalty_save_pct. Moyenne PL gardien ≈ 20-30% | F14: GK | G14: FALSE | H14: feat_penalty_save_pct | I14: z_penalty_save_pct | J14: _penalty_save_pct | K14: 2 | L14: =IFERROR(_xlfn.XLOOKUP(J14,feature_catalog!A:A,feature_catalog!A:A),"") -> _penalty_save_pct
A15: rating | B15: ss_rating | C15: raw | D15: Note SofaScore calculée algorithmiquement à partir de l'ensemble des actions de jeu pondérées par poste. Échelle 1-10, mise à jour après chaque match. Utilisée comme benchmark de validation des scores du modèle. | E15: De Bruyne : moyenne 7.3 sur la saison = excellent. Moyenne joueur ≈ 6.8. Gardien bonne saison ≈ 7.0-7.2 | F15: ALL | G15: FALSE | H15: feat_ss_rating | I15: z_ss_rating | J15: rating | L15: =IFERROR(_xlfn.XLOOKUP(J15,feature_catalog!A:A,feature_catalog!A:A),"") -> rating
A16: _save_pct | B16: save_pct | C16: pct | D16: Arrêts réalisés divisés par tirs cadrés adverses reçus. Ne tient pas compte de la difficulté des tirs (contrairement à PSxG). Un gardien face à une équipe qui tire beaucoup de loin aura mécaniquement un bon % même s'il n'est pas excellent. | E16: Alisson : 112 arrêts / 140 tirs cadrés = 80%. Valeur top gardien PL ≈ 72-78% | F16: GK | G16: FALSE | H16: feat_save_pct | I16: z_save_pct | J16: _save_pct | L16: =IFERROR(_xlfn.XLOOKUP(J16,feature_catalog!A:A,feature_catalog!A:A),"") -> _save_pct
A17: goalsConceded | B17: goals_conc_p90 | C17: vol | D17: Buts encaissés sur la saison. Feature à inverser : moins le gardien encaisse, mieux c'est. Corrélé à la qualité défensive collective — un gardien de grande équipe encaissera naturellement moins. | E17: Courtois encaisse 1 but par match en moyenne = 1 goal_conc_p90. Top gardien PL ≈ 0.8-1.0 | F17: GK | G17: TRUE | H17: feat_goals_conc_p90 | I17: z_goals_conc_p90 | J17: goalsConceded | L17: =IFERROR(_xlfn.XLOOKUP(J17,feature_catalog!A:A,feature_catalog!A:A),"") -> goalsConceded
A18: xGoalsConceded | B18: xg_conc_p90 | C18: vol | D18: xGoals concédés — somme des probabilités de but des tirs adverses reçus. Mesure la difficulté des arrêts du gardien indépendamment des résultats. Base du calcul de goalsPrevented. | E18: Ederson reçoit 5 tirs/match avec xGC cumulé = 1.2/match → équipe concède moins que prévu si réels buts < 1.2 | F18: GK | G18: TRUE | H18: feat_xg_conc_p90 | I18: z_xg_conc_p90 | J18: xGoalsConceded | L18: =IFERROR(_xlfn.XLOOKUP(J18,feature_catalog!A:A,feature_catalog!A:A),"")
A19: goalsPrevented | B19: goals_prevented_p90 | C19: vol | D19: Buts évités = arrêts réalisés moins xGoals concédés attendus. Mesure la surperformance du gardien par rapport aux attentes. Équivalent SofaScore du PSxG+/- de FBref. Positif = meilleur que prévu, négatif = moins bon. | E19: Ederson reçoit 45 tirs cadrés avec xGC=38.5, encaisse 34 buts → goalsPrevented = 38.5-34 = +4.5 (surperformance) | F19: GK | G19: FALSE | H19: feat_goals_prevented_p90 | I19: z_goals_prevented_p90 | J19: goalsPrevented | K19: 4 | L19: =IFERROR(_xlfn.XLOOKUP(J19,feature_catalog!A:A,feature_catalog!A:A),"") -> goalsPrevented
A20: penaltiesSaved | B20: pk_saved_p90 | C20: vol | D20: Pénaltys arrêtés en absolu (nb de penalties stoppés sur la saison). Comptabilise uniquement les arrêts directs, pas les tirs repoussés puis marqués sur le rebond. | E20: Alisson arrête 2 pénaltys sur la saison = 2 penaltiesSaved. Stat très rare — la plupart des gardiens → 0-1/saison | F20: GK | G20: FALSE | H20: feat_pk_saved_p90 | I20: z_pk_saved_p90 | J20: penaltiesSaved | L20: =IFERROR(_xlfn.XLOOKUP(J20,feature_catalog!A:A,feature_catalog!A:A),"")
A21: highClaims | B21: high_claims_p90 | C21: vol | D21: Captages hauts réussis — le gardien sort aériennement pour attraper ou dégager un centre ou corner en hauteur, en challengeant avec des attaquants adverses. Réussi = le gardien capture ou dégage proprement sans laisser la balle traîner. | E21: Alisson sort sur un corner, capte le ballon devant Lukaku qui challengeait = 1 high claim réussi. Alisson sort, perd le duel et le ballon traîne = 0 high claim réussi | F21: GK | G21: FALSE | H21: feat_high_claims_p90 | I21: z_high_claims_p90 | J21: highClaims | L21: =IFERROR(_xlfn.XLOOKUP(J21,feature_catalog!A:A,feature_catalog!A:A),"") -> highClaims
A22: runsOut | B22: runs_out_p90 | C22: vol | D22: Sorties physiques du gardien HORS de sa surface de réparation pour intervenir sur le ballon — couper une passe longue, contrer un dribbleur en un-contre-un, dégager un ballon avant l'attaquant. Le gardien doit franchir la ligne des 18m. | E22: Neuer sort à 30m de son but pour couper un ballon dans le dos de Boateng = 1 runOut. Neuer sort à la limite de sa surface = 0 runOut | F22: GK | G22: FALSE | H22: feat_runs_out_p90 | I22: z_runs_out_p90 | J22: runsOut | L22: =IFERROR(_xlfn.XLOOKUP(J22,feature_catalog!A:A,feature_catalog!A:A),"") -> runsOut
A23: successfulRunsOut | B23: runs_out_suc_p90 | C23: vol | D23: Sous-ensemble des sorties (runsOut) réussies — le gardien récupère proprement le ballon ou le dégage sans laisser de rebond dangereux. Indicateur de précision dans les sorties hors surface. | E23: Neuer sort à 25m et capte le ballon proprement = 1 successful runOut. Neuer sort, rate le ballon, attaquant passe à côté = runOut non réussi | F23: GK | G23: FALSE | H23: feat_runs_out_suc_p90 | I23: z_runs_out_suc_p90 | J23: successfulRunsOut | L23: =IFERROR(_xlfn.XLOOKUP(J23,feature_catalog!A:A,feature_catalog!A:A),"") -> successfulRunsOut
A24: punches | B24: punches_p90 | C24: vol | D24: Dégagements au poing — action du gardien qui repousse le ballon du poing plutôt que de le capter. Souvent utilisé sur les centres difficiles à contrôler en conditions de pression. | E24: Lloris ne peut pas capter un corner tendu et repousse du poing = 1 punch | F24: GK | G24: FALSE | H24: feat_punches_p90 | I24: z_punches_p90 | J24: punches | L24: =IFERROR(_xlfn.XLOOKUP(J24,feature_catalog!A:A,feature_catalog!A:A),"") -> punches
A25: totalKeeperSweeper | B25: gk_sweeper_p90 | C25: vol | D25: Actions sweeper du gardien = toutes les interventions où le gardien agit en dernier défenseur sur un ballon dangereux arrivant derrière sa défense. Plus large que runsOut — inclut les sorties DANS la surface sur ballons filtrés. runsOut ⊂ keeperSweeper. | E25: Ederson sort à 30m = runOut ET keeperSweeper. Ederson sort à 15m (dans sa surface) pour couper un ballon filtré = keeperSweeper mais PAS runOut | F25: GK | G25: FALSE | H25: feat_gk_sweeper_p90 | I25: z_gk_sweeper_p90 | J25: totalKeeperSweeper | L25: =IFERROR(_xlfn.XLOOKUP(J25,feature_catalog!A:A,feature_catalog!A:A),"")
A26: accurateKeeperSweeper | B26: gk_sweeper_acc_p90 | C26: vol | D26: Actions sweeper réussies — sous-ensemble des keeperSweeper où le gardien récupère ou dégage proprement le ballon arrivant derrière la défense. Indicateur de précision du jeu en sweeper keeper. | E26: Ederson sort en sweeper et capte proprement le ballon filtré = 1 accurate keeperSweeper. Ederson sort, manque le ballon = keeperSweeper non réussi | F26: GK | G26: FALSE | H26: feat_gk_sweeper_acc_p90 | I26: z_gk_sweeper_acc_p90 | J26: accurateKeeperSweeper | L26: =IFERROR(_xlfn.XLOOKUP(J26,feature_catalog!A:A,feature_catalog!A:A),"")
A27: accurateLongBallsPercentage | B27: gk_long_balls_pct | C27: pct | D27: % longues passes réussies du gardien — passes longues réussies / tentées. Indicateur clé du gardien relanceur ou sweeper keeper qui participe à la construction. | E27: Ederson joue 8 longues passes, 6 arrivent à un coéquipier = 75% gk_long_balls_pct | F27: GK | G27: FALSE | H27: feat_gk_long_balls_pct | I27: z_gk_long_balls_pct | J27: accurateLongBallsPercentage | L27: =IFERROR(_xlfn.XLOOKUP(J27,feature_catalog!A:A,feature_catalog!A:A),"") -> accurateLongBallsPercentage
A28: averageX | B28: avg_x | C28: raw | D28: Position X moyenne du joueur sur le terrain au moment de ses touches de balle, agrégée sur la saison via l'endpoint heatmap/overall SofaScore. X=0 = ligne de but propre, X=100 = ligne de but adverse. Calculé comme moyenne des coordonnées X de toutes les touches de la heatmap saison. | E28: Benzema saison faux-9 : avgX≈62 (milieu-haut). Haaland : avgX≈80 (très haut). Casemiro sentinelle : avgX≈35 (bas) | F28: ALL | G28: FALSE | H28: feat_avg_x | I28: z_avg_x | J28: averageX | L28: =IFERROR(_xlfn.XLOOKUP(J28,feature_catalog!A:A,feature_catalog!A:A),"") -> averageX
A29: averageY | B29: avg_y | C29: raw | D29: Position Y moyenne du joueur (axe latéral), agrégée sur la saison. Y=0 = ligne de touche gauche, Y=100 = ligne de touche droite, Y=50 = axe central. Utilisé pour distinguer ailier excentré (Y≈10 ou 90) d'un intérieur (Y≈30 ou 70). | E29: Trent Alexander-Arnold : avgY≈80 (côté droit collé). Modric : avgY≈50 (axe central). Salah ailier droit rentrant : avgY≈65 | F29: ALL | G29: FALSE | H29: feat_avg_y | I29: z_avg_y | J29: averageY | L29: =IFERROR(_xlfn.XLOOKUP(J29,feature_catalog!A:A,feature_catalog!A:A),"") -> averageY
A30: height | B30: height_cm | C30: raw | D30: Taille en cm déclarée sur le profil officiel Transfermarkt du joueur. Donnée statique, issue des fiches officielles clubs / fédérations. | E30: Virgil van Dijk : 193cm. Thibaut Courtois : 199cm. Seuil 'tour de contrôle' CB : ≥188cm | F30: CB|CF|GK | G30: FALSE | H30: feat_height_cm | I30: z_height_cm | J30: height | L30: =IFERROR(_xlfn.XLOOKUP(J30,feature_catalog!A:A,feature_catalog!A:A),"") -> height
A31: runs_out_pct | B31: runs_out_pct | C31: pct | D31: Sorties hors surface réussies / sorties tentées. runsOut = gardien franchit la ligne des 18m pour intervenir sur le ballon. successfulRunsOut = parmi ces sorties, celles où il obtient le ballon. | E31: Neuer : 18 runsOut, 16 successfulRunsOut → runs_out_pct = 88.9% | F31: GK | G31: False | H31: feat_runs_out_pct | I31: z_runs_out_pct
A32: high_claims_pct | B32: high_claims_pct | C32: pct | D32: Passes aériennes captées / (captées + ratées). highClaims = gardien sort et capte le ballon aérien. crossesNotClaimed = gardien sort pour capter un cross mais rate le ballon. Ratio de réussite sur les sorties aériennes tentées. | E32: Alisson : 28 highClaims, 3 crossesNotClaimed → high_claims_pct = 28/31 = 90.3% | F32: GK | G32: False | H32: feat_high_claims_pct | I32: z_high_claims_pct | K32: 2

Sheet gardien_libero
A1: source_column | B1: feature_name | C1: type | D1: description | E1: exemple | F1: relevant_roles | G1: inverted | H1: feat_col | I1: z_col | J1: source_column | K1: Pondération
A2: xGBuildup_us | B2: xgbuildup_p90 | C2: vol | D2: xGChain moins la contribution directe du tireur (xG) et du passeur décisif (xA). Mesure exclusivement les touches 'invisibles' en amont de la phase finale — la contribution à la construction profonde. | E2: Cancelo → De Bruyne → Haaland (but, xG=0.45). Cancelo : xGBuildup=0.45. De Bruyne : xGBuildup=0 (passeur déc. exclu). Haaland : xGBuildup=0 (tireur exclu) | F2: CM|DM|CB|FB|AM | G2: FALSE | H2: feat_xgbuildup_p90 | I2: z_xgbuildup_p90 | J2: xGBuildup_us | L2: =IFERROR(_xlfn.XLOOKUP(J2,feature_catalog!A:A,feature_catalog!A:A),"") -> xGBuildup_us
A3: accuratePasses | B3: acc_passes_p90 | C3: vol | D3: Nombre absolu de passes réussies sur la saison — passe qu'un coéquipier contrôle. Converti en per-90 pour la comparaison inter-joueurs. Exclut les corners, remises en jeu et dégagements gardien. | E3: Kroos : 85 passes réussies en 90min = 85 acc_passes pour ce match. Moyenne DM = 60-80 per-90 | F3: CM|DM|CB|AM | G3: FALSE | H3: feat_acc_passes_p90 | I3: z_acc_passes_p90 | J3: accuratePasses | L3: =IFERROR(_xlfn.XLOOKUP(J3,feature_catalog!A:A,feature_catalog!A:A),"") -> accuratePasses
A4: accuratePassesPercentage | B4: pass_acc_pct | C4: pct | D4: Passes réussies divisées par passes tentées. Une passe est réussie si un coéquipier la contrôle. Exclut les corners, remises en jeu, dégagements du gardien et centres (comptés séparément). | E4: Kroos : 85 passes réussies / 90 tentées = 94.4%. Moyenne DM Premier League ≈ 82% | F4: CM|DM|CB|FB|AM|GK | G4: FALSE | H4: feat_pass_acc_pct | I4: z_pass_acc_pct | J4: accuratePassesPercentage | K4: 1 | L4: =IFERROR(_xlfn.XLOOKUP(J4,feature_catalog!A:A,feature_catalog!A:A),"") -> accuratePassesPercentage
A5: accurateLongBalls | B5: long_balls_p90 | C5: vol | D5: Passes longues réussies — ballon joué en hauteur sur une distance significative (généralement >32m) récupéré par un coéquipier. Comptées en absolu per-90. | E5: Rúben Dias joue 8 longues passes dont 6 arrivent à un coéquipier = 6 long balls réussies | F5: CB|DM|GK|CM | G5: FALSE | H5: feat_long_balls_p90 | I5: z_long_balls_p90 | J5: accurateLongBalls | L5: =IFERROR(_xlfn.XLOOKUP(J5,feature_catalog!A:A,feature_catalog!A:A),"") -> accurateLongBalls
A6: accurateLongBallsPercentage | B6: long_balls_pct | C6: pct | D6: Passes longues réussies sur passes longues tentées. Une passe longue est définie par Opta comme un ballon joué en hauteur sur une distance significative (généralement >32m). Indicateur clé des CBs relanceurs et gardiens modernes. | E6: Rúben Dias joue 8 longues passes, 6 arrivent à un coéquipier = 75% long balls | F6: CB|DM|GK|CM | G6: FALSE | H6: feat_long_balls_pct | I6: z_long_balls_pct | J6: accurateLongBallsPercentage | K6: 1 | L6: =IFERROR(_xlfn.XLOOKUP(J6,feature_catalog!A:A,feature_catalog!A:A),"") -> accurateLongBallsPercentage
A7: touches | B7: touches_p90 | C7: vol | D7: Somme de tous les événements où le joueur touche le ballon — passe, tir, contrôle, dégagement, etc. Si un joueur contrôle puis passe, c'est 1 touche (l'action complète), pas 2. | E7: Iniesta reçoit, contrôle et passe en une action fluide = 1 touch. Un défenseur qui dévie involontairement un tir = 1 touch | F7: CF|CM|DM|AM|W | G7: FALSE | H7: feat_touches_p90 | I7: z_touches_p90 | J7: touches | L7: =IFERROR(_xlfn.XLOOKUP(J7,feature_catalog!A:A,feature_catalog!A:A),"") -> touches
A8: errorLeadToGoal | B8: errors_goal_p90 | C8: vol | D8: Erreur individuelle d'un joueur menant DIRECTEMENT à un but encaissé. L'erreur doit être la cause directe sans phase de jeu intermédiaire. Très rare — 0 à 2 occurrences par saison pour la plupart des joueurs. | E8: Maguire perd le ballon dans sa propre surface, l'adversaire marque immédiatement = 1 errorLeadToGoal. Feature à inverser | F8: CD|GK|FB | G8: TRUE | H8: feat_errors_goal_p90 | I8: z_errors_goal_p90 | J8: errorLeadToGoal | L8: =IFERROR(_xlfn.XLOOKUP(J8,feature_catalog!A:A,feature_catalog!A:A),"") -> errorLeadToGoal
A9: errorLeadToShot | B9: errors_shot_p90 | C9: vol | D9: Erreur menant DIRECTEMENT à un tir adverse, but ou non. Sur-ensemble de errorLeadToGoal — chaque errorLeadToGoal est aussi un errorLeadToShot mais pas l'inverse. Légèrement plus fréquent (2-6/saison). | E9: Stones glisse et offre le ballon à Salah qui tire (gardien arrête) = 1 errorLeadToShot mais pas errorLeadToGoal | F9: CD|GK|FB | G9: TRUE | H9: feat_errors_shot_p90 | I9: z_errors_shot_p90 | J9: errorLeadToShot | K9: 3 | L9: =IFERROR(_xlfn.XLOOKUP(J9,feature_catalog!A:A,feature_catalog!A:A),"") -> errorLeadToShot
A10: headedClearances | B10: headed_clear_p90 | C10: vol | D10: Sous-ensemble des clearances : dégagements effectués de la tête uniquement. Indicateur de domination aérienne défensive dans la surface propre. | E10: Dias dégage un corner adverse de la tête = 1 headed clearance | F10: CB|GK | G10: FALSE | H10: feat_headed_clear_p90 | I10: z_headed_clear_p90 | J10: headedClearances | L10: =IFERROR(_xlfn.XLOOKUP(J10,feature_catalog!A:A,feature_catalog!A:A),"")
A11: saves | B11: saves_p90 | C11: vol | D11: Arrêts réalisés — tirs cadrés adverses stoppés par le gardien. Comptés uniquement sur les tirs qui auraient constitué un but sans l'intervention. Corrélé au volume de tirs adverses reçus. | E11: Alisson arrête un tir de Salah au premier poteau = 1 save. Alisson dévie un tir qui allait à côté = 0 save (pas cadré) | F11: GK | G11: FALSE | H11: feat_saves_p90 | I11: z_saves_p90 | J11: saves | L11: =IFERROR(_xlfn.XLOOKUP(J11,feature_catalog!A:A,feature_catalog!A:A),"") -> saves
A12: cleanSheet | B12: clean_sheets_p90 | C12: vol | D12: Match sans but encaissé — gardien ayant tenu sa cage à zéro pour la totalité du match joué. Per-90 utilisé comme proportion de matchs à zéro. Corrélé à la qualité défensive collective. | E12: Ederson joue 90min sans encaisser = 1 cleanSheet. Ederson sort à la 80e (0-0), remplaçant encaisse = pas de cleanSheet | F12: GK | G12: FALSE | H12: feat_clean_sheets_p90 | I12: z_clean_sheets_p90 | J12: cleanSheet | L12: =IFERROR(_xlfn.XLOOKUP(J12,feature_catalog!A:A,feature_catalog!A:A),"") -> cleanSheet
A13: savedShotsFromInsideTheBox | B13: saves_inside_p90 | C13: vol | D13: Arrêts sur tirs depuis l'intérieur de la surface de réparation — sous-ensemble des saves sur les tirs les plus dangereux (zone de vérité). Indicateur du niveau de difficulté des arrêts réalisés. | E13: Alisson arrête une frappe à bout portant de Haaland à 6m = 1 savedShotFromInsideTheBox | F13: GK | G13: FALSE | H13: feat_saves_inside_p90 | I13: z_saves_inside_p90 | J13: savedShotsFromInsideTheBox | L13: =IFERROR(_xlfn.XLOOKUP(J13,feature_catalog!A:A,feature_catalog!A:A),"") -> savedShotsFromInsideTheBox
A14: savedShotsFromOutsideTheBox | B14: saves_outside_p90 | C14: vol | D14: Arrêts sur tirs depuis l'extérieur de la surface — saves sur frappes lointaines. Généralement plus prévisibles mais peuvent être déviées. Indicateur du volume de tirs lointains arrêtés. | E14: Alisson arrête une frappe de 25m de Salah qui allait dans le coin = 1 savedShotFromOutsideTheBox | F14: GK | G14: FALSE | H14: feat_saves_outside_p90 | I14: z_saves_outside_p90 | J14: savedShotsFromOutsideTheBox | L14: =IFERROR(_xlfn.XLOOKUP(J14,feature_catalog!A:A,feature_catalog!A:A),"") -> savedShotsFromOutsideTheBox
A15: crossesNotClaimed | B15: crosses_not_claimed_p90 | C15: vol | D15: Centres non interceptés par le gardien — ballon joué depuis les côtés vers la surface que le gardien n'a pas capté ni dégagé. Feature à inverser : plus ce nombre est élevé, moins le gardien contrôle sa surface. | E15: Un corner arrive dans la surface, Courtois ne sort pas et le ballon traîne = 1 crossNotClaimed | F15: GK | G15: TRUE | H15: feat_crosses_not_claimed_p90 | I15: z_crosses_not_claimed_p90 | J15: crossesNotClaimed | L15: =IFERROR(_xlfn.XLOOKUP(J15,feature_catalog!A:A,feature_catalog!A:A),"") -> crossesNotClaimed
A16: _penalty_save_pct | B16: penalty_save_pct | C16: pct | D16: % pénaltys arrêtés = penaltySave / penaltyFaced × 100. Mesure la performance du gardien sur penalty. Calculé uniquement pour les gardiens ayant fait face à au moins 1 pénalty saison. | E16: Alisson face à 5 pénaltys, en arrête 2 = 40% penalty_save_pct. Moyenne PL gardien ≈ 20-30% | F16: GK | G16: FALSE | H16: feat_penalty_save_pct | I16: z_penalty_save_pct | J16: _penalty_save_pct | K16: 1.5 | L16: =IFERROR(_xlfn.XLOOKUP(J16,feature_catalog!A:A,feature_catalog!A:A),"") -> _penalty_save_pct
A17: rating | B17: ss_rating | C17: raw | D17: Note SofaScore calculée algorithmiquement à partir de l'ensemble des actions de jeu pondérées par poste. Échelle 1-10, mise à jour après chaque match. Utilisée comme benchmark de validation des scores du modèle. | E17: De Bruyne : moyenne 7.3 sur la saison = excellent. Moyenne joueur ≈ 6.8. Gardien bonne saison ≈ 7.0-7.2 | F17: ALL | G17: FALSE | H17: feat_ss_rating | I17: z_ss_rating | J17: rating | L17: =IFERROR(_xlfn.XLOOKUP(J17,feature_catalog!A:A,feature_catalog!A:A),"") -> rating
A18: _save_pct | B18: save_pct | C18: pct | D18: Arrêts réalisés divisés par tirs cadrés adverses reçus. Ne tient pas compte de la difficulté des tirs (contrairement à PSxG). Un gardien face à une équipe qui tire beaucoup de loin aura mécaniquement un bon % même s'il n'est pas excellent. | E18: Alisson : 112 arrêts / 140 tirs cadrés = 80%. Valeur top gardien PL ≈ 72-78% | F18: GK | G18: FALSE | H18: feat_save_pct | I18: z_save_pct | J18: _save_pct | L18: =IFERROR(_xlfn.XLOOKUP(J18,feature_catalog!A:A,feature_catalog!A:A),"") -> _save_pct
A19: goalsConceded | B19: goals_conc_p90 | C19: vol | D19: Buts encaissés sur la saison. Feature à inverser : moins le gardien encaisse, mieux c'est. Corrélé à la qualité défensive collective — un gardien de grande équipe encaissera naturellement moins. | E19: Courtois encaisse 1 but par match en moyenne = 1 goal_conc_p90. Top gardien PL ≈ 0.8-1.0 | F19: GK | G19: TRUE | H19: feat_goals_conc_p90 | I19: z_goals_conc_p90 | J19: goalsConceded | L19: =IFERROR(_xlfn.XLOOKUP(J19,feature_catalog!A:A,feature_catalog!A:A),"") -> goalsConceded
A20: xGoalsConceded | B20: xg_conc_p90 | C20: vol | D20: xGoals concédés — somme des probabilités de but des tirs adverses reçus. Mesure la difficulté des arrêts du gardien indépendamment des résultats. Base du calcul de goalsPrevented. | E20: Ederson reçoit 5 tirs/match avec xGC cumulé = 1.2/match → équipe concède moins que prévu si réels buts < 1.2 | F20: GK | G20: TRUE | H20: feat_xg_conc_p90 | I20: z_xg_conc_p90 | J20: xGoalsConceded | L20: =IFERROR(_xlfn.XLOOKUP(J20,feature_catalog!A:A,feature_catalog!A:A),"")
A21: goalsPrevented | B21: goals_prevented_p90 | C21: vol | D21: Buts évités = arrêts réalisés moins xGoals concédés attendus. Mesure la surperformance du gardien par rapport aux attentes. Équivalent SofaScore du PSxG+/- de FBref. Positif = meilleur que prévu, négatif = moins bon. | E21: Ederson reçoit 45 tirs cadrés avec xGC=38.5, encaisse 34 buts → goalsPrevented = 38.5-34 = +4.5 (surperformance) | F21: GK | G21: FALSE | H21: feat_goals_prevented_p90 | I21: z_goals_prevented_p90 | J21: goalsPrevented | K21: 4 | L21: =IFERROR(_xlfn.XLOOKUP(J21,feature_catalog!A:A,feature_catalog!A:A),"") -> goalsPrevented
A22: penaltiesSaved | B22: pk_saved_p90 | C22: vol | D22: Pénaltys arrêtés en absolu (nb de penalties stoppés sur la saison). Comptabilise uniquement les arrêts directs, pas les tirs repoussés puis marqués sur le rebond. | E22: Alisson arrête 2 pénaltys sur la saison = 2 penaltiesSaved. Stat très rare — la plupart des gardiens → 0-1/saison | F22: GK | G22: FALSE | H22: feat_pk_saved_p90 | I22: z_pk_saved_p90 | J22: penaltiesSaved | L22: =IFERROR(_xlfn.XLOOKUP(J22,feature_catalog!A:A,feature_catalog!A:A),"")
A23: highClaims | B23: high_claims_p90 | C23: vol | D23: Captages hauts réussis — le gardien sort aériennement pour attraper ou dégager un centre ou corner en hauteur, en challengeant avec des attaquants adverses. Réussi = le gardien capture ou dégage proprement sans laisser la balle traîner. | E23: Alisson sort sur un corner, capte le ballon devant Lukaku qui challengeait = 1 high claim réussi. Alisson sort, perd le duel et le ballon traîne = 0 high claim réussi | F23: GK | G23: FALSE | H23: feat_high_claims_p90 | I23: z_high_claims_p90 | J23: highClaims | L23: =IFERROR(_xlfn.XLOOKUP(J23,feature_catalog!A:A,feature_catalog!A:A),"") -> highClaims
A24: runsOut | B24: runs_out_p90 | C24: vol | D24: Sorties physiques du gardien HORS de sa surface de réparation pour intervenir sur le ballon — couper une passe longue, contrer un dribbleur en un-contre-un, dégager un ballon avant l'attaquant. Le gardien doit franchir la ligne des 18m. | E24: Neuer sort à 30m de son but pour couper un ballon dans le dos de Boateng = 1 runOut. Neuer sort à la limite de sa surface = 0 runOut | F24: GK | G24: FALSE | H24: feat_runs_out_p90 | I24: z_runs_out_p90 | J24: runsOut | K24: 1 | L24: =IFERROR(_xlfn.XLOOKUP(J24,feature_catalog!A:A,feature_catalog!A:A),"") -> runsOut
A25: successfulRunsOut | B25: runs_out_suc_p90 | C25: vol | D25: Sous-ensemble des sorties (runsOut) réussies — le gardien récupère proprement le ballon ou le dégage sans laisser de rebond dangereux. Indicateur de précision dans les sorties hors surface. | E25: Neuer sort à 25m et capte le ballon proprement = 1 successful runOut. Neuer sort, rate le ballon, attaquant passe à côté = runOut non réussi | F25: GK | G25: FALSE | H25: feat_runs_out_suc_p90 | I25: z_runs_out_suc_p90 | J25: successfulRunsOut | L25: =IFERROR(_xlfn.XLOOKUP(J25,feature_catalog!A:A,feature_catalog!A:A),"") -> successfulRunsOut
A26: totalKeeperSweeper | B26: gk_sweeper_p90 | C26: vol | D26: Actions sweeper du gardien = toutes les interventions où le gardien agit en dernier défenseur sur un ballon dangereux arrivant derrière sa défense. Plus large que runsOut — inclut les sorties DANS la surface sur ballons filtrés. runsOut ⊂ keeperSweeper. | E26: Ederson sort à 30m = runOut ET keeperSweeper. Ederson sort à 15m (dans sa surface) pour couper un ballon filtré = keeperSweeper mais PAS runOut | F26: GK | G26: FALSE | H26: feat_gk_sweeper_p90 | I26: z_gk_sweeper_p90 | J26: totalKeeperSweeper | L26: =IFERROR(_xlfn.XLOOKUP(J26,feature_catalog!A:A,feature_catalog!A:A),"")
A27: accurateKeeperSweeper | B27: gk_sweeper_acc_p90 | C27: vol | D27: Actions sweeper réussies — sous-ensemble des keeperSweeper où le gardien récupère ou dégage proprement le ballon arrivant derrière la défense. Indicateur de précision du jeu en sweeper keeper. | E27: Ederson sort en sweeper et capte proprement le ballon filtré = 1 accurate keeperSweeper. Ederson sort, manque le ballon = keeperSweeper non réussi | F27: GK | G27: FALSE | H27: feat_gk_sweeper_acc_p90 | I27: z_gk_sweeper_acc_p90 | J27: accurateKeeperSweeper | L27: =IFERROR(_xlfn.XLOOKUP(J27,feature_catalog!A:A,feature_catalog!A:A),"")
A28: accurateLongBallsPercentage | B28: gk_long_balls_pct | C28: pct | D28: % longues passes réussies du gardien — passes longues réussies / tentées. Indicateur clé du gardien relanceur ou sweeper keeper qui participe à la construction. | E28: Ederson joue 8 longues passes, 6 arrivent à un coéquipier = 75% gk_long_balls_pct | F28: GK | G28: FALSE | H28: feat_gk_long_balls_pct | I28: z_gk_long_balls_pct | J28: accurateLongBallsPercentage | L28: =IFERROR(_xlfn.XLOOKUP(J28,feature_catalog!A:A,feature_catalog!A:A),"") -> accurateLongBallsPercentage
A29: averageX | B29: avg_x | C29: raw | D29: Position X moyenne du joueur sur le terrain au moment de ses touches de balle, agrégée sur la saison via l'endpoint heatmap/overall SofaScore. X=0 = ligne de but propre, X=100 = ligne de but adverse. Calculé comme moyenne des coordonnées X de toutes les touches de la heatmap saison. | E29: Benzema saison faux-9 : avgX≈62 (milieu-haut). Haaland : avgX≈80 (très haut). Casemiro sentinelle : avgX≈35 (bas) | F29: ALL | G29: FALSE | H29: feat_avg_x | I29: z_avg_x | J29: averageX | L29: =IFERROR(_xlfn.XLOOKUP(J29,feature_catalog!A:A,feature_catalog!A:A),"") -> averageX
A30: averageY | B30: avg_y | C30: raw | D30: Position Y moyenne du joueur (axe latéral), agrégée sur la saison. Y=0 = ligne de touche gauche, Y=100 = ligne de touche droite, Y=50 = axe central. Utilisé pour distinguer ailier excentré (Y≈10 ou 90) d'un intérieur (Y≈30 ou 70). | E30: Trent Alexander-Arnold : avgY≈80 (côté droit collé). Modric : avgY≈50 (axe central). Salah ailier droit rentrant : avgY≈65 | F30: ALL | G30: FALSE | H30: feat_avg_y | I30: z_avg_y | J30: averageY | L30: =IFERROR(_xlfn.XLOOKUP(J30,feature_catalog!A:A,feature_catalog!A:A),"") -> averageY
A31: height | B31: height_cm | C31: raw | D31: Taille en cm déclarée sur le profil officiel Transfermarkt du joueur. Donnée statique, issue des fiches officielles clubs / fédérations. | E31: Virgil van Dijk : 193cm. Thibaut Courtois : 199cm. Seuil 'tour de contrôle' CB : ≥188cm | F31: CB|CF|GK | G31: FALSE | H31: feat_height_cm | I31: z_height_cm | J31: height | L31: =IFERROR(_xlfn.XLOOKUP(J31,feature_catalog!A:A,feature_catalog!A:A),"") -> height
A32: runs_out_pct | B32: runs_out_pct | C32: pct | D32: Sorties hors surface réussies / sorties tentées. runsOut = gardien franchit la ligne des 18m pour intervenir sur le ballon. successfulRunsOut = parmi ces sorties, celles où il obtient le ballon. | E32: Neuer : 18 runsOut, 16 successfulRunsOut → runs_out_pct = 88.9% | F32: GK | G32: False | H32: feat_runs_out_pct | I32: z_runs_out_pct | J32: runs_out_pct | K32: 2 | L32: =IFERROR(_xlfn.XLOOKUP(J32,feature_catalog!A:A,feature_catalog!A:A),"") -> runs_out_pct
A33: high_claims_pct | B33: high_claims_pct | C33: pct | D33: Passes aériennes captées / (captées + ratées). highClaims = gardien sort et capte le ballon aérien. crossesNotClaimed = gardien sort pour capter un cross mais rate le ballon. Ratio de réussite sur les sorties aériennes tentées. | E33: Alisson : 28 highClaims, 3 crossesNotClaimed → high_claims_pct = 28/31 = 90.3% | F33: GK | G33: False | H33: feat_high_claims_pct | I33: z_high_claims_pct | J33: high_claims_pct | K33: 1.5 | L33: =IFERROR(_xlfn.XLOOKUP(J33,feature_catalog!A:A,feature_catalog!A:A),"") -> high_claims_pct

Sheet gardien_relanceur
A1: source_column | B1: feature_name | C1: type | D1: description | E1: exemple | F1: relevant_roles | G1: inverted | H1: feat_col | I1: z_col | J1: source_column | K1: Pondération
A2: xGChain_us | B2: xgchain_p90 | C2: vol | D2: Somme des xG de toutes les occasions auxquelles le joueur a participé dans la séquence de jeu, qu'il ait tiré, passé, ou simplement touché le ballon à n'importe quel moment de l'action. Très inclusif. | E2: Modric touche le ballon 3 passes avant le tir de Benzema (xG=0.25) → Modric reçoit 0.25 dans son xGChain | F2: CF|W|AM|CM|DM|FB | G2: False | H2: feat_xgchain_p90 | I2: z_xgchain_p90 | J2: xGChain_us | K2: 2 | L2: =IFERROR(_xlfn.XLOOKUP(J2,feature_catalog!A:A,feature_catalog!A:A),"") -> xGChain_us
A3: expectedAssists | B3: xa_p90 | C3: vol | D3: xG de l'occasion créée par la passe, calculé au moment où le receveur tire. Mesure la qualité des passes menant à un tir, quel que soit le résultat du tir. Une passe vers un xG=0.5 vaut xA=0.5 même si le tir est raté. | E3: Passe dans la surface pour tir à bout portant (xG=0.45) = xA=0.45 pour le passeur. Passe vers une frappe lointaine (xG=0.03) = xA=0.03 | F3: W|AM|CM|CF|FB | G3: FALSE | H3: feat_xa_p90 | I3: z_xa_p90 | J3: expectedAssists | L3: =IFERROR(_xlfn.XLOOKUP(J3,feature_catalog!A:A,feature_catalog!A:A),"") -> expectedAssists
A4: keyPasses | B4: key_passes_p90 | C4: vol | D4: Passe menant directement à une tentative de but de l'équipe, sans être une passe décisive officielle (le tir ne se transforme pas en but). Critère : la passe doit être la dernière avant le tir. | E4: Ødegaard joue une passe à Saka qui tire, gardien arrête = 1 key pass pour Ødegaard. Si Saka marque = assist, pas key pass | F4: AM|CM|W|CF|FB | G4: FALSE | H4: feat_key_passes_p90 | I4: z_key_passes_p90 | J4: keyPasses | L4: =IFERROR(_xlfn.XLOOKUP(J4,feature_catalog!A:A,feature_catalog!A:A),"") -> keyPasses
A5: accuratePasses | B5: acc_passes_p90 | C5: vol | D5: Nombre absolu de passes réussies sur la saison — passe qu'un coéquipier contrôle. Converti en per-90 pour la comparaison inter-joueurs. Exclut les corners, remises en jeu et dégagements gardien. | E5: Kroos : 85 passes réussies en 90min = 85 acc_passes pour ce match. Moyenne DM = 60-80 per-90 | F5: CM|DM|CB|AM | G5: FALSE | H5: feat_acc_passes_p90 | I5: z_acc_passes_p90 | J5: accuratePasses | L5: =IFERROR(_xlfn.XLOOKUP(J5,feature_catalog!A:A,feature_catalog!A:A),"") -> accuratePasses
A6: accuratePassesPercentage | B6: pass_acc_pct | C6: pct | D6: Passes réussies divisées par passes tentées. Une passe est réussie si un coéquipier la contrôle. Exclut les corners, remises en jeu, dégagements du gardien et centres (comptés séparément). | E6: Kroos : 85 passes réussies / 90 tentées = 94.4%. Moyenne DM Premier League ≈ 82% | F6: CM|DM|CB|FB|AM|GK | G6: FALSE | H6: feat_pass_acc_pct | I6: z_pass_acc_pct | J6: accuratePassesPercentage | K6: 2 | L6: =IFERROR(_xlfn.XLOOKUP(J6,feature_catalog!A:A,feature_catalog!A:A),"") -> accuratePassesPercentage
A7: accurateLongBalls | B7: long_balls_p90 | C7: vol | D7: Passes longues réussies — ballon joué en hauteur sur une distance significative (généralement >32m) récupéré par un coéquipier. Comptées en absolu per-90. | E7: Rúben Dias joue 8 longues passes dont 6 arrivent à un coéquipier = 6 long balls réussies | F7: CB|DM|GK|CM | G7: FALSE | H7: feat_long_balls_p90 | I7: z_long_balls_p90 | J7: accurateLongBalls | L7: =IFERROR(_xlfn.XLOOKUP(J7,feature_catalog!A:A,feature_catalog!A:A),"") -> accurateLongBalls
A8: accurateLongBallsPercentage | B8: long_balls_pct | C8: pct | D8: Passes longues réussies sur passes longues tentées. Une passe longue est définie par Opta comme un ballon joué en hauteur sur une distance significative (généralement >32m). Indicateur clé des CBs relanceurs et gardiens modernes. | E8: Rúben Dias joue 8 longues passes, 6 arrivent à un coéquipier = 75% long balls | F8: CB|DM|GK|CM | G8: FALSE | H8: feat_long_balls_pct | I8: z_long_balls_pct | J8: accurateLongBallsPercentage | K8: 2 | L8: =IFERROR(_xlfn.XLOOKUP(J8,feature_catalog!A:A,feature_catalog!A:A),"") -> accurateLongBallsPercentage
A9: possessionLost | B9: poss_lost_p90 | C9: vol | D9: Nombre de fois où le joueur perd la possession — tacle adverse réussi sur lui, mauvais contrôle, passe ratée dans les pieds adverses, interception subie. Comptabilisé uniquement quand la possession change d'équipe suite à l'action du joueur. | E9: Griezmann reçoit, adverse le tacklé et récupère le ballon = 1 possession lost pour Griezmann | F9: CF|W|CM|DM|CB | G9: TRUE | H9: feat_poss_lost_p90 | I9: z_poss_lost_p90 | J9: possessionLost | K9: 2 | L9: =IFERROR(_xlfn.XLOOKUP(J9,feature_catalog!A:A,feature_catalog!A:A),"") -> possessionLost
A10: errorLeadToGoal | B10: errors_goal_p90 | C10: vol | D10: Erreur individuelle d'un joueur menant DIRECTEMENT à un but encaissé. L'erreur doit être la cause directe sans phase de jeu intermédiaire. Très rare — 0 à 2 occurrences par saison pour la plupart des joueurs. | E10: Maguire perd le ballon dans sa propre surface, l'adversaire marque immédiatement = 1 errorLeadToGoal. Feature à inverser | F10: CD|GK|FB | G10: TRUE | H10: feat_errors_goal_p90 | I10: z_errors_goal_p90 | J10: errorLeadToGoal | L10: =IFERROR(_xlfn.XLOOKUP(J10,feature_catalog!A:A,feature_catalog!A:A),"") -> errorLeadToGoal
A11: errorLeadToShot | B11: errors_shot_p90 | C11: vol | D11: Erreur menant DIRECTEMENT à un tir adverse, but ou non. Sur-ensemble de errorLeadToGoal — chaque errorLeadToGoal est aussi un errorLeadToShot mais pas l'inverse. Légèrement plus fréquent (2-6/saison). | E11: Stones glisse et offre le ballon à Salah qui tire (gardien arrête) = 1 errorLeadToShot mais pas errorLeadToGoal | F11: CD|GK|FB | G11: TRUE | H11: feat_errors_shot_p90 | I11: z_errors_shot_p90 | J11: errorLeadToShot | K11: 1 | L11: =IFERROR(_xlfn.XLOOKUP(J11,feature_catalog!A:A,feature_catalog!A:A),"") -> errorLeadToShot
A12: headedClearances | B12: headed_clear_p90 | C12: vol | D12: Sous-ensemble des clearances : dégagements effectués de la tête uniquement. Indicateur de domination aérienne défensive dans la surface propre. | E12: Dias dégage un corner adverse de la tête = 1 headed clearance | F12: CB|GK | G12: FALSE | H12: feat_headed_clear_p90 | I12: z_headed_clear_p90 | J12: headedClearances | L12: =IFERROR(_xlfn.XLOOKUP(J12,feature_catalog!A:A,feature_catalog!A:A),"")
A13: saves | B13: saves_p90 | C13: vol | D13: Arrêts réalisés — tirs cadrés adverses stoppés par le gardien. Comptés uniquement sur les tirs qui auraient constitué un but sans l'intervention. Corrélé au volume de tirs adverses reçus. | E13: Alisson arrête un tir de Salah au premier poteau = 1 save. Alisson dévie un tir qui allait à côté = 0 save (pas cadré) | F13: GK | G13: FALSE | H13: feat_saves_p90 | I13: z_saves_p90 | J13: saves | L13: =IFERROR(_xlfn.XLOOKUP(J13,feature_catalog!A:A,feature_catalog!A:A),"") -> saves
A14: cleanSheet | B14: clean_sheets_p90 | C14: vol | D14: Match sans but encaissé — gardien ayant tenu sa cage à zéro pour la totalité du match joué. Per-90 utilisé comme proportion de matchs à zéro. Corrélé à la qualité défensive collective. | E14: Ederson joue 90min sans encaisser = 1 cleanSheet. Ederson sort à la 80e (0-0), remplaçant encaisse = pas de cleanSheet | F14: GK | G14: FALSE | H14: feat_clean_sheets_p90 | I14: z_clean_sheets_p90 | J14: cleanSheet | L14: =IFERROR(_xlfn.XLOOKUP(J14,feature_catalog!A:A,feature_catalog!A:A),"") -> cleanSheet
A15: savedShotsFromInsideTheBox | B15: saves_inside_p90 | C15: vol | D15: Arrêts sur tirs depuis l'intérieur de la surface de réparation — sous-ensemble des saves sur les tirs les plus dangereux (zone de vérité). Indicateur du niveau de difficulté des arrêts réalisés. | E15: Alisson arrête une frappe à bout portant de Haaland à 6m = 1 savedShotFromInsideTheBox | F15: GK | G15: FALSE | H15: feat_saves_inside_p90 | I15: z_saves_inside_p90 | J15: savedShotsFromInsideTheBox | L15: =IFERROR(_xlfn.XLOOKUP(J15,feature_catalog!A:A,feature_catalog!A:A),"") -> savedShotsFromInsideTheBox
A16: savedShotsFromOutsideTheBox | B16: saves_outside_p90 | C16: vol | D16: Arrêts sur tirs depuis l'extérieur de la surface — saves sur frappes lointaines. Généralement plus prévisibles mais peuvent être déviées. Indicateur du volume de tirs lointains arrêtés. | E16: Alisson arrête une frappe de 25m de Salah qui allait dans le coin = 1 savedShotFromOutsideTheBox | F16: GK | G16: FALSE | H16: feat_saves_outside_p90 | I16: z_saves_outside_p90 | J16: savedShotsFromOutsideTheBox | L16: =IFERROR(_xlfn.XLOOKUP(J16,feature_catalog!A:A,feature_catalog!A:A),"") -> savedShotsFromOutsideTheBox
A17: crossesNotClaimed | B17: crosses_not_claimed_p90 | C17: vol | D17: Centres non interceptés par le gardien — ballon joué depuis les côtés vers la surface que le gardien n'a pas capté ni dégagé. Feature à inverser : plus ce nombre est élevé, moins le gardien contrôle sa surface. | E17: Un corner arrive dans la surface, Courtois ne sort pas et le ballon traîne = 1 crossNotClaimed | F17: GK | G17: TRUE | H17: feat_crosses_not_claimed_p90 | I17: z_crosses_not_claimed_p90 | J17: crossesNotClaimed | L17: =IFERROR(_xlfn.XLOOKUP(J17,feature_catalog!A:A,feature_catalog!A:A),"") -> crossesNotClaimed
A18: _penalty_save_pct | B18: penalty_save_pct | C18: pct | D18: % pénaltys arrêtés = penaltySave / penaltyFaced × 100. Mesure la performance du gardien sur penalty. Calculé uniquement pour les gardiens ayant fait face à au moins 1 pénalty saison. | E18: Alisson face à 5 pénaltys, en arrête 2 = 40% penalty_save_pct. Moyenne PL gardien ≈ 20-30% | F18: GK | G18: FALSE | H18: feat_penalty_save_pct | I18: z_penalty_save_pct | J18: _penalty_save_pct | K18: 1.5 | L18: =IFERROR(_xlfn.XLOOKUP(J18,feature_catalog!A:A,feature_catalog!A:A),"") -> _penalty_save_pct
A19: rating | B19: ss_rating | C19: raw | D19: Note SofaScore calculée algorithmiquement à partir de l'ensemble des actions de jeu pondérées par poste. Échelle 1-10, mise à jour après chaque match. Utilisée comme benchmark de validation des scores du modèle. | E19: De Bruyne : moyenne 7.3 sur la saison = excellent. Moyenne joueur ≈ 6.8. Gardien bonne saison ≈ 7.0-7.2 | F19: ALL | G19: FALSE | H19: feat_ss_rating | I19: z_ss_rating | J19: rating | L19: =IFERROR(_xlfn.XLOOKUP(J19,feature_catalog!A:A,feature_catalog!A:A),"") -> rating
A20: _save_pct | B20: save_pct | C20: pct | D20: Arrêts réalisés divisés par tirs cadrés adverses reçus. Ne tient pas compte de la difficulté des tirs (contrairement à PSxG). Un gardien face à une équipe qui tire beaucoup de loin aura mécaniquement un bon % même s'il n'est pas excellent. | E20: Alisson : 112 arrêts / 140 tirs cadrés = 80%. Valeur top gardien PL ≈ 72-78% | F20: GK | G20: FALSE | H20: feat_save_pct | I20: z_save_pct | J20: _save_pct | L20: =IFERROR(_xlfn.XLOOKUP(J20,feature_catalog!A:A,feature_catalog!A:A),"") -> _save_pct
A21: goalsConceded | B21: goals_conc_p90 | C21: vol | D21: Buts encaissés sur la saison. Feature à inverser : moins le gardien encaisse, mieux c'est. Corrélé à la qualité défensive collective — un gardien de grande équipe encaissera naturellement moins. | E21: Courtois encaisse 1 but par match en moyenne = 1 goal_conc_p90. Top gardien PL ≈ 0.8-1.0 | F21: GK | G21: TRUE | H21: feat_goals_conc_p90 | I21: z_goals_conc_p90 | J21: goalsConceded | L21: =IFERROR(_xlfn.XLOOKUP(J21,feature_catalog!A:A,feature_catalog!A:A),"") -> goalsConceded
A22: xGoalsConceded | B22: xg_conc_p90 | C22: vol | D22: xGoals concédés — somme des probabilités de but des tirs adverses reçus. Mesure la difficulté des arrêts du gardien indépendamment des résultats. Base du calcul de goalsPrevented. | E22: Ederson reçoit 5 tirs/match avec xGC cumulé = 1.2/match → équipe concède moins que prévu si réels buts < 1.2 | F22: GK | G22: TRUE | H22: feat_xg_conc_p90 | I22: z_xg_conc_p90 | J22: xGoalsConceded | L22: =IFERROR(_xlfn.XLOOKUP(J22,feature_catalog!A:A,feature_catalog!A:A),"")
A23: goalsPrevented | B23: goals_prevented_p90 | C23: vol | D23: Buts évités = arrêts réalisés moins xGoals concédés attendus. Mesure la surperformance du gardien par rapport aux attentes. Équivalent SofaScore du PSxG+/- de FBref. Positif = meilleur que prévu, négatif = moins bon. | E23: Ederson reçoit 45 tirs cadrés avec xGC=38.5, encaisse 34 buts → goalsPrevented = 38.5-34 = +4.5 (surperformance) | F23: GK | G23: FALSE | H23: feat_goals_prevented_p90 | I23: z_goals_prevented_p90 | J23: goalsPrevented | K23: 4 | L23: =IFERROR(_xlfn.XLOOKUP(J23,feature_catalog!A:A,feature_catalog!A:A),"") -> goalsPrevented
A24: penaltiesSaved | B24: pk_saved_p90 | C24: vol | D24: Pénaltys arrêtés en absolu (nb de penalties stoppés sur la saison). Comptabilise uniquement les arrêts directs, pas les tirs repoussés puis marqués sur le rebond. | E24: Alisson arrête 2 pénaltys sur la saison = 2 penaltiesSaved. Stat très rare — la plupart des gardiens → 0-1/saison | F24: GK | G24: FALSE | H24: feat_pk_saved_p90 | I24: z_pk_saved_p90 | J24: penaltiesSaved | L24: =IFERROR(_xlfn.XLOOKUP(J24,feature_catalog!A:A,feature_catalog!A:A),"")
A25: highClaims | B25: high_claims_p90 | C25: vol | D25: Captages hauts réussis — le gardien sort aériennement pour attraper ou dégager un centre ou corner en hauteur, en challengeant avec des attaquants adverses. Réussi = le gardien capture ou dégage proprement sans laisser la balle traîner. | E25: Alisson sort sur un corner, capte le ballon devant Lukaku qui challengeait = 1 high claim réussi. Alisson sort, perd le duel et le ballon traîne = 0 high claim réussi | F25: GK | G25: FALSE | H25: feat_high_claims_p90 | I25: z_high_claims_p90 | J25: highClaims | L25: =IFERROR(_xlfn.XLOOKUP(J25,feature_catalog!A:A,feature_catalog!A:A),"") -> highClaims
A26: runsOut | B26: runs_out_p90 | C26: vol | D26: Sorties physiques du gardien HORS de sa surface de réparation pour intervenir sur le ballon — couper une passe longue, contrer un dribbleur en un-contre-un, dégager un ballon avant l'attaquant. Le gardien doit franchir la ligne des 18m. | E26: Neuer sort à 30m de son but pour couper un ballon dans le dos de Boateng = 1 runOut. Neuer sort à la limite de sa surface = 0 runOut | F26: GK | G26: FALSE | H26: feat_runs_out_p90 | I26: z_runs_out_p90 | J26: runsOut | L26: =IFERROR(_xlfn.XLOOKUP(J26,feature_catalog!A:A,feature_catalog!A:A),"") -> runsOut
A27: successfulRunsOut | B27: runs_out_suc_p90 | C27: vol | D27: Sous-ensemble des sorties (runsOut) réussies — le gardien récupère proprement le ballon ou le dégage sans laisser de rebond dangereux. Indicateur de précision dans les sorties hors surface. | E27: Neuer sort à 25m et capte le ballon proprement = 1 successful runOut. Neuer sort, rate le ballon, attaquant passe à côté = runOut non réussi | F27: GK | G27: FALSE | H27: feat_runs_out_suc_p90 | I27: z_runs_out_suc_p90 | J27: successfulRunsOut | L27: =IFERROR(_xlfn.XLOOKUP(J27,feature_catalog!A:A,feature_catalog!A:A),"") -> successfulRunsOut
A28: punches | B28: punches_p90 | C28: vol | D28: Dégagements au poing — action du gardien qui repousse le ballon du poing plutôt que de le capter. Souvent utilisé sur les centres difficiles à contrôler en conditions de pression. | E28: Lloris ne peut pas capter un corner tendu et repousse du poing = 1 punch | F28: GK | G28: FALSE | H28: feat_punches_p90 | I28: z_punches_p90 | J28: punches | L28: =IFERROR(_xlfn.XLOOKUP(J28,feature_catalog!A:A,feature_catalog!A:A),"") -> punches
A29: totalKeeperSweeper | B29: gk_sweeper_p90 | C29: vol | D29: Actions sweeper du gardien = toutes les interventions où le gardien agit en dernier défenseur sur un ballon dangereux arrivant derrière sa défense. Plus large que runsOut — inclut les sorties DANS la surface sur ballons filtrés. runsOut ⊂ keeperSweeper. | E29: Ederson sort à 30m = runOut ET keeperSweeper. Ederson sort à 15m (dans sa surface) pour couper un ballon filtré = keeperSweeper mais PAS runOut | F29: GK | G29: FALSE | H29: feat_gk_sweeper_p90 | I29: z_gk_sweeper_p90 | J29: totalKeeperSweeper | L29: =IFERROR(_xlfn.XLOOKUP(J29,feature_catalog!A:A,feature_catalog!A:A),"")
A30: accurateKeeperSweeper | B30: gk_sweeper_acc_p90 | C30: vol | D30: Actions sweeper réussies — sous-ensemble des keeperSweeper où le gardien récupère ou dégage proprement le ballon arrivant derrière la défense. Indicateur de précision du jeu en sweeper keeper. | E30: Ederson sort en sweeper et capte proprement le ballon filtré = 1 accurate keeperSweeper. Ederson sort, manque le ballon = keeperSweeper non réussi | F30: GK | G30: FALSE | H30: feat_gk_sweeper_acc_p90 | I30: z_gk_sweeper_acc_p90 | J30: accurateKeeperSweeper | L30: =IFERROR(_xlfn.XLOOKUP(J30,feature_catalog!A:A,feature_catalog!A:A),"")
A31: accurateLongBallsPercentage | B31: gk_long_balls_pct | C31: pct | D31: % longues passes réussies du gardien — passes longues réussies / tentées. Indicateur clé du gardien relanceur ou sweeper keeper qui participe à la construction. | E31: Ederson joue 8 longues passes, 6 arrivent à un coéquipier = 75% gk_long_balls_pct | F31: GK | G31: FALSE | H31: feat_gk_long_balls_pct | I31: z_gk_long_balls_pct | J31: accurateLongBallsPercentage | L31: =IFERROR(_xlfn.XLOOKUP(J31,feature_catalog!A:A,feature_catalog!A:A),"") -> accurateLongBallsPercentage
A32: averageX | B32: avg_x | C32: raw | D32: Position X moyenne du joueur sur le terrain au moment de ses touches de balle, agrégée sur la saison via l'endpoint heatmap/overall SofaScore. X=0 = ligne de but propre, X=100 = ligne de but adverse. Calculé comme moyenne des coordonnées X de toutes les touches de la heatmap saison. | E32: Benzema saison faux-9 : avgX≈62 (milieu-haut). Haaland : avgX≈80 (très haut). Casemiro sentinelle : avgX≈35 (bas) | F32: ALL | G32: FALSE | H32: feat_avg_x | I32: z_avg_x | J32: averageX | L32: =IFERROR(_xlfn.XLOOKUP(J32,feature_catalog!A:A,feature_catalog!A:A),"") -> averageX
A33: averageY | B33: avg_y | C33: raw | D33: Position Y moyenne du joueur (axe latéral), agrégée sur la saison. Y=0 = ligne de touche gauche, Y=100 = ligne de touche droite, Y=50 = axe central. Utilisé pour distinguer ailier excentré (Y≈10 ou 90) d'un intérieur (Y≈30 ou 70). | E33: Trent Alexander-Arnold : avgY≈80 (côté droit collé). Modric : avgY≈50 (axe central). Salah ailier droit rentrant : avgY≈65 | F33: ALL | G33: FALSE | H33: feat_avg_y | I33: z_avg_y | J33: averageY | L33: =IFERROR(_xlfn.XLOOKUP(J33,feature_catalog!A:A,feature_catalog!A:A),"") -> averageY
A34: height | B34: height_cm | C34: raw | D34: Taille en cm déclarée sur le profil officiel Transfermarkt du joueur. Donnée statique, issue des fiches officielles clubs / fédérations. | E34: Virgil van Dijk : 193cm. Thibaut Courtois : 199cm. Seuil 'tour de contrôle' CB : ≥188cm | F34: CB|CF|GK | G34: FALSE | H34: feat_height_cm | I34: z_height_cm | J34: height | L34: =IFERROR(_xlfn.XLOOKUP(J34,feature_catalog!A:A,feature_catalog!A:A),"") -> height
A35: runs_out_pct | B35: runs_out_pct | C35: pct | D35: Sorties hors surface réussies / sorties tentées. runsOut = gardien franchit la ligne des 18m pour intervenir sur le ballon. successfulRunsOut = parmi ces sorties, celles où il obtient le ballon. | E35: Neuer : 18 runsOut, 16 successfulRunsOut → runs_out_pct = 88.9% | F35: GK | G35: False | H35: feat_runs_out_pct | I35: z_runs_out_pct | J35: runs_out_pct | L35: =IFERROR(_xlfn.XLOOKUP(J35,feature_catalog!A:A,feature_catalog!A:A),"") -> runs_out_pct
A36: high_claims_pct | B36: high_claims_pct | C36: pct | D36: Passes aériennes captées / (captées + ratées). highClaims = gardien sort et capte le ballon aérien. crossesNotClaimed = gardien sort pour capter un cross mais rate le ballon. Ratio de réussite sur les sorties aériennes tentées. | E36: Alisson : 28 highClaims, 3 crossesNotClaimed → high_claims_pct = 28/31 = 90.3% | F36: GK | G36: False | H36: feat_high_claims_pct | I36: z_high_claims_pct | J36: high_claims_pct | K36: 1.5 | L36: =IFERROR(_xlfn.XLOOKUP(J36,feature_catalog!A:A,feature_catalog!A:A),"") -> high_claims_pct

Sheet defenseur_central
A1: source_column | B1: feature_name | C1: type | D1: description | E1: exemple | F1: relevant_roles | G1: inverted | H1: feat_col | I1: z_col | J1: source_column | K1: pondération
A2: xGBuildup_us | B2: xgbuildup_p90 | C2: vol | D2: xGChain moins la contribution directe du tireur (xG) et du passeur décisif (xA). Mesure exclusivement les touches 'invisibles' en amont de la phase finale — la contribution à la construction profonde. | E2: Cancelo → De Bruyne → Haaland (but, xG=0.45). Cancelo : xGBuildup=0.45. De Bruyne : xGBuildup=0 (passeur déc. exclu). Haaland : xGBuildup=0 (tireur exclu) | F2: CM|DM|CB|FB|AM | G2: FALSE | H2: feat_xgbuildup_p90 | I2: z_xgbuildup_p90 | J2: xGBuildup_us | L2: =IFERROR(_xlfn.XLOOKUP(A2,feature_catalog!A:A,feature_catalog!A:A),"") -> xGBuildup_us
A3: headedGoals | B3: headed_goals_p90 | C3: vol | D3: Buts marqués de la tête — sous-ensemble de goals attribués à une touche de tête intentionnelle. Indicateur de domination aérienne offensive. | E3: Giroud détourne un corner de la tête en haut du filet = 1 headed goal | F3: CF|CD | G3: FALSE | H3: feat_headed_goals_p90 | I3: z_headed_goals_p90 | J3: headedGoals | L3: =IFERROR(_xlfn.XLOOKUP(A3,feature_catalog!A:A,feature_catalog!A:A),"") -> headedGoals
A4: accurateFinalThirdPasses | B4: passes_f3_p90 | C4: vol | D4: Passes dont le point d'arrivée se situe dans le dernier tiers du terrain (33m finaux). Mesure la capacité à faire progresser le jeu vers l'avant. Ne requiert pas que la passe soit une passe clé. | E4: Busquets joue une passe depuis son propre camp vers Pedri dans le dernier tiers = 1 passToFinalThird | F4: CM|DM|CB|AM | G4: FALSE | H4: feat_passes_f3_p90 | I4: z_passes_f3_p90 | J4: accurateFinalThirdPasses | L4: =IFERROR(_xlfn.XLOOKUP(A4,feature_catalog!A:A,feature_catalog!A:A),"") -> accurateFinalThirdPasses
A5: accuratePasses | B5: acc_passes_p90 | C5: vol | D5: Nombre absolu de passes réussies sur la saison — passe qu'un coéquipier contrôle. Converti en per-90 pour la comparaison inter-joueurs. Exclut les corners, remises en jeu et dégagements gardien. | E5: Kroos : 85 passes réussies en 90min = 85 acc_passes pour ce match. Moyenne DM = 60-80 per-90 | F5: CM|DM|CB|AM | G5: FALSE | H5: feat_acc_passes_p90 | I5: z_acc_passes_p90 | J5: accuratePasses | L5: =IFERROR(_xlfn.XLOOKUP(A5,feature_catalog!A:A,feature_catalog!A:A),"") -> accuratePasses
A6: accuratePassesPercentage | B6: pass_acc_pct | C6: pct | D6: Passes réussies divisées par passes tentées. Une passe est réussie si un coéquipier la contrôle. Exclut les corners, remises en jeu, dégagements du gardien et centres (comptés séparément). | E6: Kroos : 85 passes réussies / 90 tentées = 94.4%. Moyenne DM Premier League ≈ 82% | F6: CM|DM|CB|FB|AM|GK | G6: FALSE | H6: feat_pass_acc_pct | I6: z_pass_acc_pct | J6: accuratePassesPercentage | K6: 1 | L6: =IFERROR(_xlfn.XLOOKUP(A6,feature_catalog!A:A,feature_catalog!A:A),"") -> accuratePassesPercentage
A7: accurateLongBalls | B7: long_balls_p90 | C7: vol | D7: Passes longues réussies — ballon joué en hauteur sur une distance significative (généralement >32m) récupéré par un coéquipier. Comptées en absolu per-90. | E7: Rúben Dias joue 8 longues passes dont 6 arrivent à un coéquipier = 6 long balls réussies | F7: CB|DM|GK|CM | G7: FALSE | H7: feat_long_balls_p90 | I7: z_long_balls_p90 | J7: accurateLongBalls | L7: =IFERROR(_xlfn.XLOOKUP(A7,feature_catalog!A:A,feature_catalog!A:A),"") -> accurateLongBalls
A8: accurateLongBallsPercentage | B8: long_balls_pct | C8: pct | D8: Passes longues réussies sur passes longues tentées. Une passe longue est définie par Opta comme un ballon joué en hauteur sur une distance significative (généralement >32m). Indicateur clé des CBs relanceurs et gardiens modernes. | E8: Rúben Dias joue 8 longues passes, 6 arrivent à un coéquipier = 75% long balls | F8: CB|DM|GK|CM | G8: FALSE | H8: feat_long_balls_pct | I8: z_long_balls_pct | J8: accurateLongBallsPercentage | K8: 1 | L8: =IFERROR(_xlfn.XLOOKUP(A8,feature_catalog!A:A,feature_catalog!A:A),"") -> accurateLongBallsPercentage
A9: possessionLost | B9: poss_lost_p90 | C9: vol | D9: Nombre de fois où le joueur perd la possession — tacle adverse réussi sur lui, mauvais contrôle, passe ratée dans les pieds adverses, interception subie. Comptabilisé uniquement quand la possession change d'équipe suite à l'action du joueur. | E9: Griezmann reçoit, adverse le tacklé et récupère le ballon = 1 possession lost pour Griezmann | F9: CF|W|CM|DM|CB | G9: TRUE | H9: feat_poss_lost_p90 | I9: z_poss_lost_p90 | J9: possessionLost | K9: 2 | L9: =IFERROR(_xlfn.XLOOKUP(A9,feature_catalog!A:A,feature_catalog!A:A),"") -> possessionLost
A10: ballRecovery | B10: ball_recovery_p90 | C10: vol | D10: Récupération de balle — action où le joueur obtient la possession sur un ballon libre ou dévié, sans que ce soit un tacle direct sur porteur ni une interception anticipée. Inclut les segundas pelotas. | E10: Kanté se retrouve sur un rebond d'un tir adverse et récupère le ballon = 1 ball recovery | F10: DM|CM|CD|FB | G10: FALSE | H10: feat_ball_recovery_p90 | I10: z_ball_recovery_p90 | J10: ballRecovery | L10: =IFERROR(_xlfn.XLOOKUP(A10,feature_catalog!A:A,feature_catalog!A:A),"") -> ballRecovery
A11: dribbledPast | B11: dribbled_past_p90 | C11: vol | D11: Nombre de fois où un adversaire réussit un dribble sur ce joueur. Feature défensive à inverser : moins le joueur se fait dribbler, mieux c'est. Indicateur de solidité défensive individuelle au sol. | E11: Salah élimine le latéral adverse qui ne peut que le faucher = 1 dribbled past pour le défenseur | F11: CD|FB | G11: TRUE | H11: feat_dribbled_past_p90 | I11: z_dribbled_past_p90 | J11: dribbledPast | K11: 3 | L11: =IFERROR(_xlfn.XLOOKUP(A11,feature_catalog!A:A,feature_catalog!A:A),"") -> dribbledPast
A12: fouls | B12: fouls_p90 | C12: vol | D12: Fautes commises — infractions sifflées suite à un contact irrégulier du joueur sur un adversaire. Comptée indépendamment du carton éventuel. Feature à inverser : moins = mieux. | E12: Tchouaméni tacklé irrégulièrement un adversaire, arbitre siffle = 1 foul. Valeur typique DM ≈ 2-3/match | F12: DM|CB|CM | G12: TRUE | H12: feat_fouls_p90 | I12: z_fouls_p90 | J12: fouls | K12: 1 | L12: =IFERROR(_xlfn.XLOOKUP(A12,feature_catalog!A:A,feature_catalog!A:A),"") -> fouls
A13: penaltyConceded | B13: penalty_conc_p90 | C13: vol | D13: Pénalty concédé — faute commise par ce joueur dans sa propre surface de réparation, entraînant un pénalty pour l'adversaire. Feature à inverser : moins = mieux. | E13: Pavard fauche Mbappé dans la surface = 1 penalty conceded pour Pavard | F13: CD|FB | G13: TRUE | H13: feat_penalty_conc_p90 | I13: z_penalty_conc_p90 | J13: penaltyConceded | L13: =IFERROR(_xlfn.XLOOKUP(A13,feature_catalog!A:A,feature_catalog!A:A),"") -> penaltyConceded
A14: outfielderBlocks | B14: outfielder_blocks_p90 | C14: vol | D14: Bloc ou dégagement d'urgence d'un joueur de champ — intervention défensive où le joueur se sacrifie pour couper un tir ou une passe dangereuse dans la surface. Différent de blockedShots (moins strict sur la direction). | E14: Saliba plonge devant une frappe dans la surface et la dévie en corner = 1 outfielder block | F14: CD|DM | G14: FALSE | H14: feat_outfielder_blocks_p90 | I14: z_outfielder_blocks_p90 | J14: outfielderBlocks | L14: =IFERROR(_xlfn.XLOOKUP(A14,feature_catalog!A:A,feature_catalog!A:A),"") -> outfielderBlocks
A15: errorLeadToGoal | B15: errors_goal_p90 | C15: vol | D15: Erreur individuelle d'un joueur menant DIRECTEMENT à un but encaissé. L'erreur doit être la cause directe sans phase de jeu intermédiaire. Très rare — 0 à 2 occurrences par saison pour la plupart des joueurs. | E15: Maguire perd le ballon dans sa propre surface, l'adversaire marque immédiatement = 1 errorLeadToGoal. Feature à inverser | F15: CD|GK|FB | G15: TRUE | H15: feat_errors_goal_p90 | I15: z_errors_goal_p90 | J15: errorLeadToGoal | L15: =IFERROR(_xlfn.XLOOKUP(A15,feature_catalog!A:A,feature_catalog!A:A),"") -> errorLeadToGoal
A16: errorLeadToShot | B16: errors_shot_p90 | C16: vol | D16: Erreur menant DIRECTEMENT à un tir adverse, but ou non. Sur-ensemble de errorLeadToGoal — chaque errorLeadToGoal est aussi un errorLeadToShot mais pas l'inverse. Légèrement plus fréquent (2-6/saison). | E16: Stones glisse et offre le ballon à Salah qui tire (gardien arrête) = 1 errorLeadToShot mais pas errorLeadToGoal | F16: CD|GK|FB | G16: TRUE | H16: feat_errors_shot_p90 | I16: z_errors_shot_p90 | J16: errorLeadToShot | K16: 2 | L16: =IFERROR(_xlfn.XLOOKUP(A16,feature_catalog!A:A,feature_catalog!A:A),"") -> errorLeadToShot
A17: tackles | B17: tackles_p90 | C17: vol | D17: Tacle réussi = le joueur entre en contact avec le ballon dans un duel au sol et récupère la possession ou dégage le ballon. Le joueur taclé doit clairement être en possession. Couper une passe n'est PAS un tacle (c'est une interception). | E17: Kanté glisse et rafle le ballon sous le pied de Pogba qui avait le contrôle = 1 tackle. Kanté intercepte une passe = interception, pas tackle | F17: DM|CB|CM|FB | G17: FALSE | H17: feat_tackles_p90 | I17: z_tackles_p90 | J17: tackles | L17: =IFERROR(_xlfn.XLOOKUP(A17,feature_catalog!A:A,feature_catalog!A:A),"") -> tackles
A18: tacklesWon | B18: tackles_won_p90 | C18: vol | D18: Sous-ensemble des tacles : tacles remportés où le joueur récupère proprement la possession après le tacle (pas seulement dégagé). Indicateur de qualité défensive au sol. | E18: Kanté tacklé Pogba et repart avec le ballon = 1 tackle won. Kanté dévie le ballon en touche = tacle mais pas won | F18: DM|CB|CM|FB | G18: FALSE | H18: feat_tackles_won_p90 | I18: z_tackles_won_p90 | J18: tacklesWon | L18: =IFERROR(_xlfn.XLOOKUP(A18,feature_catalog!A:A,feature_catalog!A:A),"") -> tacklesWon
A19: _tackle_success_pct | B19: tackle_success_pct | C19: pct | D19: % tacles réussis = tacklesWon / tackles × 100. Mesure l'efficacité défensive au sol. Distingue le défenseur engagé précis (haut %) du défenseur brouillon qui tacle beaucoup mais perd souvent. | E19: Fabinho : 8 tacles, 6 remportés = 75% tackle success. Valeur top DM PL ≈ 65-75% | F19: DM|CB|CM|FB | G19: FALSE | H19: feat_tackle_success_pct | I19: z_tackle_success_pct | J19: _tackle_success_pct | L19: =IFERROR(_xlfn.XLOOKUP(A19,feature_catalog!A:A,feature_catalog!A:A),"") -> _tackle_success_pct
A20: interceptions | B20: interceptions_p90 | C20: vol | D20: Le joueur lit la passe adverse et se déplace dans la trajectoire du ballon pour l'intercepter. Geste ANTICIPATIF — le joueur doit se déplacer vers la ligne de passe avant que le ballon arrive. Différent du tacle (réactif sur porteur) et de la récupération (ballon libre). | E20: Fabinho lit une passe horizontale, se décale et intercepte le ballon dans sa course = 1 interception. Fabinho récupère un rebond qui traîne = ball recovery, pas interception | F20: DM|CB|CM|FB | G20: FALSE | H20: feat_interceptions_p90 | I20: z_interceptions_p90 | J20: interceptions | K20: 3 | L20: =IFERROR(_xlfn.XLOOKUP(A20,feature_catalog!A:A,feature_catalog!A:A),"") -> interceptions
A21: clearances | B21: clearances_p90 | C21: vol | D21: Dégagement = action d'un joueur qui éloigne le ballon d'une zone dangereuse SANS cible précise — il n'essaie pas de passer à un coéquipier, juste de dégager le danger. Si une cible est identifiée, c'est une passe. | E21: Stones dégage un centre tendu de la tête dans les tribunes = 1 clearance. Stones contrôle le même centre et passe à Ederson = passe, pas clearance | F21: CB|FB|DM | G21: FALSE | H21: feat_clearances_p90 | I21: z_clearances_p90 | J21: clearances | L21: =IFERROR(_xlfn.XLOOKUP(A21,feature_catalog!A:A,feature_catalog!A:A),"") -> clearances
A22: headedClearances | B22: headed_clear_p90 | C22: vol | D22: Sous-ensemble des clearances : dégagements effectués de la tête uniquement. Indicateur de domination aérienne défensive dans la surface propre. | E22: Dias dégage un corner adverse de la tête = 1 headed clearance | F22: CB|GK | G22: FALSE | H22: feat_headed_clear_p90 | I22: z_headed_clear_p90 | J22: headedClearances | L22: =IFERROR(_xlfn.XLOOKUP(A22,feature_catalog!A:A,feature_catalog!A:A),"")
A23: blockedShots | B23: blocked_shots_p90 | C23: vol | D23: Joueur de champ qui bloque une tentative de but adverse. Condition stricte Opta : le tir doit être dirigé vers le but (aurait été cadré ou but sans le bloc). Si le tir allait de toute façon à côté, aucun bloc n'est comptabilisé. | E23: Van Dijk se jette devant la frappe de Salah adverse qui allait en haut du poteau = 1 blocked shot. Van Dijk dévie un tir qui allait largement à côté = 0 blocked shot | F23: CB|DM|CM | G23: FALSE | H23: feat_blocked_shots_p90 | I23: z_blocked_shots_p90 | J23: blockedShots | L23: =IFERROR(_xlfn.XLOOKUP(A23,feature_catalog!A:A,feature_catalog!A:A),"") -> blockedShots
A24: _duels_won_p90 | B24: duels_won_p90 | C24: vol | D24: Duels gagnés par 90min — somme des duels au sol et aériens gagnés (groundDuelsWon + aerialDuelsWon), converti en per-90. Indicateur global de présence physique dans les duels. | E24: Tchouaméni : 4 duels sol gagnés + 2 duels aériens gagnés = 6 duels_won pour ce match | F24: CB|DM|CM|CF | G24: FALSE | H24: feat_duels_won_p90 | I24: z_duels_won_p90 | J24: _duels_won_p90 | L24: =IFERROR(_xlfn.XLOOKUP(A24,feature_catalog!A:A,feature_catalog!A:A),"") -> _duels_won_p90
A25: _duels_won_pct | B25: duels_won_pct | C25: pct | D25: % duels gagnés (tous types) — proxy calculé comme (groundDuelsWonPercentage + aerialDuelsWonPercentage) / 2. Indicateur global d'efficacité dans les duels 1v1. | E25: Tchouaméni : 67% duels sol + 58% duels aériens = 62.5% duels_won_pct | F25: CB|DM|CM|CF|FB | G25: FALSE | H25: feat_duels_won_pct | I25: z_duels_won_pct | J25: _duels_won_pct | L25: =IFERROR(_xlfn.XLOOKUP(A25,feature_catalog!A:A,feature_catalog!A:A),"") -> _duels_won_pct
A26: groundDuelsWon | B26: ground_duels_p90 | C26: vol | D26: Duels au sol gagnés — contests 50/50 sur le sol où le joueur récupère la possession. Comptés séparément des duels aériens. Indicateur de solidité physique au sol. | E26: Tchouaméni glisse dans un tacle et récupère le ballon face à De Bruyne = 1 ground duel won | F26: DM|CM|CB|CF | G26: FALSE | H26: feat_ground_duels_p90 | I26: z_ground_duels_p90 | J26: groundDuelsWon | L26: =IFERROR(_xlfn.XLOOKUP(A26,feature_catalog!A:A,feature_catalog!A:A),"") -> groundDuelsWon
A27: groundDuelsWonPercentage | B27: ground_duels_pct | C27: pct | D27: % duels au sol gagnés sur duels au sol disputés. Un duel est défini comme un contest 50/50 entre deux joueurs adverses. Indicateur de solidité au sol dans les duels 1v1. | E27: Tchouaméni : 6 duels sol gagnés / 9 disputés = 67%. Moyenne milieu défensif PL ≈ 55-60% | F27: DM|CM|CB|CF | G27: FALSE | H27: feat_ground_duels_pct | I27: z_ground_duels_pct | J27: groundDuelsWonPercentage | K27: 2.5 | L27: =IFERROR(_xlfn.XLOOKUP(A27,feature_catalog!A:A,feature_catalog!A:A),"") -> groundDuelsWonPercentage
A28: aerialDuelsWon | B28: aerial_duels_p90 | C28: vol | D28: Duels aériens gagnés — challenges en l'air pour des centres, dégagements ou balles longues. Indicateur de domination physique aérienne. Comptés séparément des duels au sol. | E28: Giroud saute plus haut que le défenseur et capte un corner de la tête = 1 aerial duel won | F28: CB|CF|DM | G28: FALSE | H28: feat_aerial_duels_p90 | I28: z_aerial_duels_p90 | J28: aerialDuelsWon | L28: =IFERROR(_xlfn.XLOOKUP(A28,feature_catalog!A:A,feature_catalog!A:A),"") -> aerialDuelsWon
A29: aerialDuelsWonPercentage | B29: aerial_duels_pct | C29: pct | D29: Duels aériens gagnés sur duels aériens disputés. Un duel aérien nécessite 2+ joueurs qui challengent pour le même ballon en l'air. Gagné = le joueur obtient le premier contact contrôlé. Si fauté pendant le duel aérien, le joueur fauté gagne le duel. | E29: Giroud vs un défenseur sur corner : tous deux sautent, Giroud capte le ballon de la tête = Giroud gagne le duel aérien. Si le défenseur le fauche en sautant = Giroud gagne le duel (fauté) | F29: CB|CF|DM|FB | G29: FALSE | H29: feat_aerial_duels_pct | I29: z_aerial_duels_pct | J29: aerialDuelsWonPercentage | K29: 2 | L29: =IFERROR(_xlfn.XLOOKUP(A29,feature_catalog!A:A,feature_catalog!A:A),"") -> aerialDuelsWonPercentage

Sheet relanceur
A1: source_column | B1: feature_name | C1: type | D1: description | E1: exemple | F1: relevant_roles | G1: inverted | H1: feat_col | I1: z_col | J1: source_column | K1: pondération
A2: aerialDuelsWonPercentage | B2: aerial_duels_pct | C2: pct | D2: Duels aériens gagnés sur duels aériens disputés. Un duel aérien nécessite 2+ joueurs qui challengent pour le même ballon en l'air. Gagné = le joueur obtient le premier contact contrôlé. Si fauté pendant le duel aérien, le joueur fauté gagne le duel. | E2: Giroud vs un défenseur sur corner : tous deux sautent, Giroud capte le ballon de la tête = Giroud gagne le duel aérien. Si le défenseur le fauche en sautant = Giroud gagne le duel (fauté) | F2: CB|CF|DM|FB | G2: FALSE | H2: feat_aerial_duels_pct | I2: z_aerial_duels_pct | J2: aerialDuelsWonPercentage | K2: 1.5 | L2: =IFERROR(_xlfn.XLOOKUP(A2,feature_catalog!A:A,feature_catalog!A:A),"") -> aerialDuelsWonPercentage
A3: aerialDuelsWon | B3: aerial_duels_p90 | C3: vol | D3: Duels aériens gagnés — challenges en l'air pour des centres, dégagements ou balles longues. Indicateur de domination physique aérienne. Comptés séparément des duels au sol. | E3: Giroud saute plus haut que le défenseur et capte un corner de la tête = 1 aerial duel won | F3: CB|CF|DM | G3: FALSE | H3: feat_aerial_duels_p90 | I3: z_aerial_duels_p90 | J3: aerialDuelsWon | L3: =IFERROR(_xlfn.XLOOKUP(A3,feature_catalog!A:A,feature_catalog!A:A),"") -> aerialDuelsWon
A4: groundDuelsWonPercentage | B4: ground_duels_pct | C4: pct | D4: % duels au sol gagnés sur duels au sol disputés. Un duel est défini comme un contest 50/50 entre deux joueurs adverses. Indicateur de solidité au sol dans les duels 1v1. | E4: Tchouaméni : 6 duels sol gagnés / 9 disputés = 67%. Moyenne milieu défensif PL ≈ 55-60% | F4: DM|CM|CB|CF | G4: FALSE | H4: feat_ground_duels_pct | I4: z_ground_duels_pct | J4: groundDuelsWonPercentage | K4: 2 | L4: =IFERROR(_xlfn.XLOOKUP(A4,feature_catalog!A:A,feature_catalog!A:A),"") -> groundDuelsWonPercentage
A5: groundDuelsWon | B5: ground_duels_p90 | C5: vol | D5: Duels au sol gagnés — contests 50/50 sur le sol où le joueur récupère la possession. Comptés séparément des duels aériens. Indicateur de solidité physique au sol. | E5: Tchouaméni glisse dans un tacle et récupère le ballon face à De Bruyne = 1 ground duel won | F5: DM|CM|CB|CF | G5: FALSE | H5: feat_ground_duels_p90 | I5: z_ground_duels_p90 | J5: groundDuelsWon | L5: =IFERROR(_xlfn.XLOOKUP(A5,feature_catalog!A:A,feature_catalog!A:A),"") -> groundDuelsWon
A6: _duels_won_pct | B6: duels_won_pct | C6: pct | D6: % duels gagnés (tous types) — proxy calculé comme (groundDuelsWonPercentage + aerialDuelsWonPercentage) / 2. Indicateur global d'efficacité dans les duels 1v1. | E6: Tchouaméni : 67% duels sol + 58% duels aériens = 62.5% duels_won_pct | F6: CB|DM|CM|CF|FB | G6: FALSE | H6: feat_duels_won_pct | I6: z_duels_won_pct | J6: _duels_won_pct | L6: =IFERROR(_xlfn.XLOOKUP(A6,feature_catalog!A:A,feature_catalog!A:A),"") -> _duels_won_pct
A7: _duels_won_p90 | B7: duels_won_p90 | C7: vol | D7: Duels gagnés par 90min — somme des duels au sol et aériens gagnés (groundDuelsWon + aerialDuelsWon), converti en per-90. Indicateur global de présence physique dans les duels. | E7: Tchouaméni : 4 duels sol gagnés + 2 duels aériens gagnés = 6 duels_won pour ce match | F7: CB|DM|CM|CF | G7: FALSE | H7: feat_duels_won_p90 | I7: z_duels_won_p90 | J7: _duels_won_p90 | L7: =IFERROR(_xlfn.XLOOKUP(A7,feature_catalog!A:A,feature_catalog!A:A),"") -> _duels_won_p90
A8: _tackle_success_pct | B8: tackle_success_pct | C8: pct | D8: % tacles réussis = tacklesWon / tackles × 100. Mesure l'efficacité défensive au sol. Distingue le défenseur engagé précis (haut %) du défenseur brouillon qui tacle beaucoup mais perd souvent. | E8: Fabinho : 8 tacles, 6 remportés = 75% tackle success. Valeur top DM PL ≈ 65-75% | F8: DM|CB|CM|FB | G8: FALSE | H8: feat_tackle_success_pct | I8: z_tackle_success_pct | J8: _tackle_success_pct | L8: =IFERROR(_xlfn.XLOOKUP(A8,feature_catalog!A:A,feature_catalog!A:A),"") -> _tackle_success_pct
A9: tackles | B9: tackles_p90 | C9: vol | D9: Tacle réussi = le joueur entre en contact avec le ballon dans un duel au sol et récupère la possession ou dégage le ballon. Le joueur taclé doit clairement être en possession. Couper une passe n'est PAS un tacle (c'est une interception). | E9: Kanté glisse et rafle le ballon sous le pied de Pogba qui avait le contrôle = 1 tackle. Kanté intercepte une passe = interception, pas tackle | F9: DM|CB|CM|FB | G9: FALSE | H9: feat_tackles_p90 | I9: z_tackles_p90 | J9: tackles | L9: =IFERROR(_xlfn.XLOOKUP(A9,feature_catalog!A:A,feature_catalog!A:A),"") -> tackles
A10: tacklesWon | B10: tackles_won_p90 | C10: vol | D10: Sous-ensemble des tacles : tacles remportés où le joueur récupère proprement la possession après le tacle (pas seulement dégagé). Indicateur de qualité défensive au sol. | E10: Kanté tacklé Pogba et repart avec le ballon = 1 tackle won. Kanté dévie le ballon en touche = tacle mais pas won | F10: DM|CB|CM|FB | G10: FALSE | H10: feat_tackles_won_p90 | I10: z_tackles_won_p90 | J10: tacklesWon | L10: =IFERROR(_xlfn.XLOOKUP(A10,feature_catalog!A:A,feature_catalog!A:A),"") -> tacklesWon
A11: interceptions | B11: interceptions_p90 | C11: vol | D11: Le joueur lit la passe adverse et se déplace dans la trajectoire du ballon pour l'intercepter. Geste ANTICIPATIF — le joueur doit se déplacer vers la ligne de passe avant que le ballon arrive. Différent du tacle (réactif sur porteur) et de la récupération (ballon libre). | E11: Fabinho lit une passe horizontale, se décale et intercepte le ballon dans sa course = 1 interception. Fabinho récupère un rebond qui traîne = ball recovery, pas interception | F11: DM|CB|CM|FB | G11: FALSE | H11: feat_interceptions_p90 | I11: z_interceptions_p90 | J11: interceptions | K11: 2 | L11: =IFERROR(_xlfn.XLOOKUP(A11,feature_catalog!A:A,feature_catalog!A:A),"") -> interceptions
A12: clearances | B12: clearances_p90 | C12: vol | D12: Dégagement = action d'un joueur qui éloigne le ballon d'une zone dangereuse SANS cible précise — il n'essaie pas de passer à un coéquipier, juste de dégager le danger. Si une cible est identifiée, c'est une passe. | E12: Stones dégage un centre tendu de la tête dans les tribunes = 1 clearance. Stones contrôle le même centre et passe à Ederson = passe, pas clearance | F12: CB|FB|DM | G12: FALSE | H12: feat_clearances_p90 | I12: z_clearances_p90 | J12: clearances | L12: =IFERROR(_xlfn.XLOOKUP(A12,feature_catalog!A:A,feature_catalog!A:A),"") -> clearances
A13: headedClearances | B13: headed_clear_p90 | C13: vol | D13: Sous-ensemble des clearances : dégagements effectués de la tête uniquement. Indicateur de domination aérienne défensive dans la surface propre. | E13: Dias dégage un corner adverse de la tête = 1 headed clearance | F13: CB|GK | G13: FALSE | H13: feat_headed_clear_p90 | I13: z_headed_clear_p90 | J13: headedClearances | L13: =IFERROR(_xlfn.XLOOKUP(A13,feature_catalog!A:A,feature_catalog!A:A),"")
A14: blockedShots | B14: blocked_shots_p90 | C14: vol | D14: Joueur de champ qui bloque une tentative de but adverse. Condition stricte Opta : le tir doit être dirigé vers le but (aurait été cadré ou but sans le bloc). Si le tir allait de toute façon à côté, aucun bloc n'est comptabilisé. | E14: Van Dijk se jette devant la frappe de Salah adverse qui allait en haut du poteau = 1 blocked shot. Van Dijk dévie un tir qui allait largement à côté = 0 blocked shot | F14: CB|DM|CM | G14: FALSE | H14: feat_blocked_shots_p90 | I14: z_blocked_shots_p90 | J14: blockedShots | L14: =IFERROR(_xlfn.XLOOKUP(A14,feature_catalog!A:A,feature_catalog!A:A),"") -> blockedShots
A15: outfielderBlocks | B15: outfielder_blocks_p90 | C15: vol | D15: Bloc ou dégagement d'urgence d'un joueur de champ — intervention défensive où le joueur se sacrifie pour couper un tir ou une passe dangereuse dans la surface. Différent de blockedShots (moins strict sur la direction). | E15: Saliba plonge devant une frappe dans la surface et la dévie en corner = 1 outfielder block | F15: CD|DM | G15: FALSE | H15: feat_outfielder_blocks_p90 | I15: z_outfielder_blocks_p90 | J15: outfielderBlocks | L15: =IFERROR(_xlfn.XLOOKUP(A15,feature_catalog!A:A,feature_catalog!A:A),"") -> outfielderBlocks
A16: ballRecovery | B16: ball_recovery_p90 | C16: vol | D16: Récupération de balle — action où le joueur obtient la possession sur un ballon libre ou dévié, sans que ce soit un tacle direct sur porteur ni une interception anticipée. Inclut les segundas pelotas. | E16: Kanté se retrouve sur un rebond d'un tir adverse et récupère le ballon = 1 ball recovery | F16: DM|CM|CD|FB | G16: FALSE | H16: feat_ball_recovery_p90 | I16: z_ball_recovery_p90 | J16: ballRecovery | L16: =IFERROR(_xlfn.XLOOKUP(A16,feature_catalog!A:A,feature_catalog!A:A),"") -> ballRecovery
A17: dribbledPast | B17: dribbled_past_p90 | C17: vol | D17: Nombre de fois où un adversaire réussit un dribble sur ce joueur. Feature défensive à inverser : moins le joueur se fait dribbler, mieux c'est. Indicateur de solidité défensive individuelle au sol. | E17: Salah élimine le latéral adverse qui ne peut que le faucher = 1 dribbled past pour le défenseur | F17: CD|FB | G17: TRUE | H17: feat_dribbled_past_p90 | I17: z_dribbled_past_p90 | J17: dribbledPast | K17: 2 | L17: =IFERROR(_xlfn.XLOOKUP(A17,feature_catalog!A:A,feature_catalog!A:A),"") -> dribbledPast
A18: errorLeadToGoal | B18: errors_goal_p90 | C18: vol | D18: Erreur individuelle d'un joueur menant DIRECTEMENT à un but encaissé. L'erreur doit être la cause directe sans phase de jeu intermédiaire. Très rare — 0 à 2 occurrences par saison pour la plupart des joueurs. | E18: Maguire perd le ballon dans sa propre surface, l'adversaire marque immédiatement = 1 errorLeadToGoal. Feature à inverser | F18: CD|GK|FB | G18: TRUE | H18: feat_errors_goal_p90 | I18: z_errors_goal_p90 | J18: errorLeadToGoal | L18: =IFERROR(_xlfn.XLOOKUP(A18,feature_catalog!A:A,feature_catalog!A:A),"") -> errorLeadToGoal
A19: errorLeadToShot | B19: errors_shot_p90 | C19: vol | D19: Erreur menant DIRECTEMENT à un tir adverse, but ou non. Sur-ensemble de errorLeadToGoal — chaque errorLeadToGoal est aussi un errorLeadToShot mais pas l'inverse. Légèrement plus fréquent (2-6/saison). | E19: Stones glisse et offre le ballon à Salah qui tire (gardien arrête) = 1 errorLeadToShot mais pas errorLeadToGoal | F19: CD|GK|FB | G19: TRUE | H19: feat_errors_shot_p90 | I19: z_errors_shot_p90 | J19: errorLeadToShot | K19: 2 | L19: =IFERROR(_xlfn.XLOOKUP(A19,feature_catalog!A:A,feature_catalog!A:A),"") -> errorLeadToShot
A20: fouls | B20: fouls_p90 | C20: vol | D20: Fautes commises — infractions sifflées suite à un contact irrégulier du joueur sur un adversaire. Comptée indépendamment du carton éventuel. Feature à inverser : moins = mieux. | E20: Tchouaméni tacklé irrégulièrement un adversaire, arbitre siffle = 1 foul. Valeur typique DM ≈ 2-3/match | F20: DM|CB|CM | G20: TRUE | H20: feat_fouls_p90 | I20: z_fouls_p90 | J20: fouls | K20: 1 | L20: =IFERROR(_xlfn.XLOOKUP(A20,feature_catalog!A:A,feature_catalog!A:A),"") -> fouls
A21: penaltyConceded | B21: penalty_conc_p90 | C21: vol | D21: Pénalty concédé — faute commise par ce joueur dans sa propre surface de réparation, entraînant un pénalty pour l'adversaire. Feature à inverser : moins = mieux. | E21: Pavard fauche Mbappé dans la surface = 1 penalty conceded pour Pavard | F21: CD|FB | G21: TRUE | H21: feat_penalty_conc_p90 | I21: z_penalty_conc_p90 | J21: penaltyConceded | K21: 1 | L21: =IFERROR(_xlfn.XLOOKUP(A21,feature_catalog!A:A,feature_catalog!A:A),"") -> penaltyConceded
A22: accuratePassesPercentage | B22: pass_acc_pct | C22: pct | D22: Passes réussies divisées par passes tentées. Une passe est réussie si un coéquipier la contrôle. Exclut les corners, remises en jeu, dégagements du gardien et centres (comptés séparément). | E22: Kroos : 85 passes réussies / 90 tentées = 94.4%. Moyenne DM Premier League ≈ 82% | F22: CM|DM|CB|FB|AM|GK | G22: FALSE | H22: feat_pass_acc_pct | I22: z_pass_acc_pct | J22: accuratePassesPercentage | K22: 2.5 | L22: =IFERROR(_xlfn.XLOOKUP(A22,feature_catalog!A:A,feature_catalog!A:A),"") -> accuratePassesPercentage
A23: accuratePasses | B23: acc_passes_p90 | C23: vol | D23: Nombre absolu de passes réussies sur la saison — passe qu'un coéquipier contrôle. Converti en per-90 pour la comparaison inter-joueurs. Exclut les corners, remises en jeu et dégagements gardien. | E23: Kroos : 85 passes réussies en 90min = 85 acc_passes pour ce match. Moyenne DM = 60-80 per-90 | F23: CM|DM|CB|AM | G23: FALSE | H23: feat_acc_passes_p90 | I23: z_acc_passes_p90 | J23: accuratePasses | L23: =IFERROR(_xlfn.XLOOKUP(A23,feature_catalog!A:A,feature_catalog!A:A),"") -> accuratePasses
A24: accurateLongBallsPercentage | B24: long_balls_pct | C24: pct | D24: Passes longues réussies sur passes longues tentées. Une passe longue est définie par Opta comme un ballon joué en hauteur sur une distance significative (généralement >32m). Indicateur clé des CBs relanceurs et gardiens modernes. | E24: Rúben Dias joue 8 longues passes, 6 arrivent à un coéquipier = 75% long balls | F24: CB|DM|GK|CM | G24: FALSE | H24: feat_long_balls_pct | I24: z_long_balls_pct | J24: accurateLongBallsPercentage | K24: 2 | L24: =IFERROR(_xlfn.XLOOKUP(A24,feature_catalog!A:A,feature_catalog!A:A),"") -> accurateLongBallsPercentage
A25: accurateLongBalls | B25: long_balls_p90 | C25: vol | D25: Passes longues réussies — ballon joué en hauteur sur une distance significative (généralement >32m) récupéré par un coéquipier. Comptées en absolu per-90. | E25: Rúben Dias joue 8 longues passes dont 6 arrivent à un coéquipier = 6 long balls réussies | F25: CB|DM|GK|CM | G25: FALSE | H25: feat_long_balls_p90 | I25: z_long_balls_p90 | J25: accurateLongBalls | L25: =IFERROR(_xlfn.XLOOKUP(A25,feature_catalog!A:A,feature_catalog!A:A),"") -> accurateLongBalls
A26: accurateFinalThirdPasses | B26: passes_f3_p90 | C26: vol | D26: Passes dont le point d'arrivée se situe dans le dernier tiers du terrain (33m finaux). Mesure la capacité à faire progresser le jeu vers l'avant. Ne requiert pas que la passe soit une passe clé. | E26: Busquets joue une passe depuis son propre camp vers Pedri dans le dernier tiers = 1 passToFinalThird | F26: CM|DM|CB|AM | G26: FALSE | H26: feat_passes_f3_p90 | I26: z_passes_f3_p90 | J26: accurateFinalThirdPasses | L26: =IFERROR(_xlfn.XLOOKUP(A26,feature_catalog!A:A,feature_catalog!A:A),"") -> accurateFinalThirdPasses
A27: xGChain_us | B27: xgchain_p90 | C27: vol | D27: Somme des xG de toutes les occasions auxquelles le joueur a participé dans la séquence de jeu, qu'il ait tiré, passé, ou simplement touché le ballon à n'importe quel moment de l'action. Très inclusif. | E27: Modric touche le ballon 3 passes avant le tir de Benzema (xG=0.25) → Modric reçoit 0.25 dans son xGChain | F27: CF|W|AM|CM|DM|FB | G27: False | H27: feat_xgchain_p90 | I27: z_xgchain_p90 | J27: xGChain_us | K27: 2 | L27: =IFERROR(_xlfn.XLOOKUP(A27,feature_catalog!A:A,feature_catalog!A:A),"") -> xGChain_us
A28: throughBalls | B28: through_balls_p90 | C28: vol | D28: Passes en profondeur tentées — ballon joué dans l'espace derrière la ligne défensive adverse pour un coéquipier en mouvement. Comptées réussies ou non. | E28: De Bruyne joue un ballon millimétré dans le dos de la défense pour Haaland = 1 through ball (réussie si Haaland contrôle) | F28: AM|CM|DM | G28: FALSE | H28: feat_through_balls_p90 | I28: z_through_balls_p90 | J28: throughBalls | L28: =IFERROR(_xlfn.XLOOKUP(A28,feature_catalog!A:A,feature_catalog!A:A),"")
A29: progressiveCarries | B29: prog_carries_p90 | C29: vol | D29: Conduite de balle d'au moins 5m vers l'avant (en direction du but adverse). Mesure la capacité à faire progresser l'équipe par la course avec le ballon. | E29: Vinícius reçoit à 40m, conduit jusqu'à 30m en ligne droite = 1 progressive carry (10m vers l'avant) | F29: W|CM|FB|CF | G29: FALSE | H29: feat_prog_carries_p90 | I29: z_prog_carries_p90 | J29: progressiveCarries | L29: =IFERROR(_xlfn.XLOOKUP(A29,feature_catalog!A:A,feature_catalog!A:A),"") -> progressiveCarries
A30: keyPasses | B30: key_passes_p90 | C30: vol | D30: Passe menant directement à une tentative de but de l'équipe, sans être une passe décisive officielle (le tir ne se transforme pas en but). Critère : la passe doit être la dernière avant le tir. | E30: Ødegaard joue une passe à Saka qui tire, gardien arrête = 1 key pass pour Ødegaard. Si Saka marque = assist, pas key pass | F30: AM|CM|W|CF|FB | G30: FALSE | H30: feat_key_passes_p90 | I30: z_key_passes_p90 | J30: keyPasses | L30: =IFERROR(_xlfn.XLOOKUP(A30,feature_catalog!A:A,feature_catalog!A:A),"") -> keyPasses
A31: expectedAssists | B31: xa_p90 | C31: vol | D31: xG de l'occasion créée par la passe, calculé au moment où le receveur tire. Mesure la qualité des passes menant à un tir, quel que soit le résultat du tir. Une passe vers un xG=0.5 vaut xA=0.5 même si le tir est raté. | E31: Passe dans la surface pour tir à bout portant (xG=0.45) = xA=0.45 pour le passeur. Passe vers une frappe lointaine (xG=0.03) = xA=0.03 | F31: W|AM|CM|CF|FB | G31: FALSE | H31: feat_xa_p90 | I31: z_xa_p90 | J31: expectedAssists | L31: =IFERROR(_xlfn.XLOOKUP(A31,feature_catalog!A:A,feature_catalog!A:A),"") -> expectedAssists
A32: possessionLost | B32: poss_lost_p90 | C32: vol | D32: Nombre de fois où le joueur perd la possession — tacle adverse réussi sur lui, mauvais contrôle, passe ratée dans les pieds adverses, interception subie. Comptabilisé uniquement quand la possession change d'équipe suite à l'action du joueur. | E32: Griezmann reçoit, adverse le tacklé et récupère le ballon = 1 possession lost pour Griezmann | F32: CF|W|CM|DM|CB | G32: TRUE | H32: feat_poss_lost_p90 | I32: z_poss_lost_p90 | J32: possessionLost | K32: 1 | L32: =IFERROR(_xlfn.XLOOKUP(A32,feature_catalog!A:A,feature_catalog!A:A),"") -> possessionLost
A33: dispossessed | B33: dispossessed_p90 | C33: vol | D33: Sous-ensemble de possessionLost : uniquement les pertes de balle causées par un tacle adverse réussi sur le joueur en possession. Exclut les mauvaises passes et mauvais contrôles. | E33: Vinicius conduit, un défenseur le tacklé proprement et récupère le ballon = 1 dispossessed. Mauvaise passe de Vinicius = possessionLost mais pas dispossessed | F33: W|CF|AM|CM | G33: TRUE | H33: feat_dispossessed_p90 | I33: z_dispossessed_p90 | J33: dispossessed | L33: =IFERROR(_xlfn.XLOOKUP(A33,feature_catalog!A:A,feature_catalog!A:A),"") -> dispossessed
A34: rating | B34: ss_rating | C34: raw | D34: Note SofaScore calculée algorithmiquement à partir de l'ensemble des actions de jeu pondérées par poste. Échelle 1-10, mise à jour après chaque match. Utilisée comme benchmark de validation des scores du modèle. | E34: De Bruyne : moyenne 7.3 sur la saison = excellent. Moyenne joueur ≈ 6.8. Gardien bonne saison ≈ 7.0-7.2 | F34: ALL | G34: FALSE | H34: feat_ss_rating | I34: z_ss_rating | J34: rating | L34: =IFERROR(_xlfn.XLOOKUP(A34,feature_catalog!A:A,feature_catalog!A:A),"") -> rating
A35: height | B35: height_cm | C35: raw | D35: Taille en cm déclarée sur le profil officiel Transfermarkt du joueur. Donnée statique, issue des fiches officielles clubs / fédérations. | E35: Virgil van Dijk : 193cm. Thibaut Courtois : 199cm. Seuil 'tour de contrôle' CB : ≥188cm | F35: CB|CF|GK | G35: FALSE | H35: feat_height_cm | I35: z_height_cm | J35: height | L35: =IFERROR(_xlfn.XLOOKUP(A35,feature_catalog!A:A,feature_catalog!A:A),"") -> height
A36: averageX | B36: avg_x | C36: raw | D36: Position X moyenne du joueur sur le terrain au moment de ses touches de balle, agrégée sur la saison via l'endpoint heatmap/overall SofaScore. X=0 = ligne de but propre, X=100 = ligne de but adverse. Calculé comme moyenne des coordonnées X de toutes les touches de la heatmap saison. | E36: Benzema saison faux-9 : avgX≈62 (milieu-haut). Haaland : avgX≈80 (très haut). Casemiro sentinelle : avgX≈35 (bas) | F36: ALL | G36: FALSE | H36: feat_avg_x | I36: z_avg_x | J36: averageX | L36: =IFERROR(_xlfn.XLOOKUP(A36,feature_catalog!A:A,feature_catalog!A:A),"") -> averageX
A37: averageY | B37: avg_y | C37: raw | D37: Position Y moyenne du joueur (axe latéral), agrégée sur la saison. Y=0 = ligne de touche gauche, Y=100 = ligne de touche droite, Y=50 = axe central. Utilisé pour distinguer ailier excentré (Y≈10 ou 90) d'un intérieur (Y≈30 ou 70). | E37: Trent Alexander-Arnold : avgY≈80 (côté droit collé). Modric : avgY≈50 (axe central). Salah ailier droit rentrant : avgY≈65 | F37: ALL | G37: FALSE | H37: feat_avg_y | I37: z_avg_y | J37: averageY | L37: =IFERROR(_xlfn.XLOOKUP(A37,feature_catalog!A:A,feature_catalog!A:A),"") -> averageY

Sheet stoppeur
A1: source_column | B1: feature_name | C1: type | D1: description | E1: exemple | F1: relevant_roles | G1: inverted | H1: feat_col | I1: z_col | J1: source_column | K1: pondération
A2: aerialDuelsWonPercentage | B2: aerial_duels_pct | C2: pct | D2: Duels aériens gagnés sur duels aériens disputés. Un duel aérien nécessite 2+ joueurs qui challengent pour le même ballon en l'air. Gagné = le joueur obtient le premier contact contrôlé. Si fauté pendant le duel aérien, le joueur fauté gagne le duel. | E2: Giroud vs un défenseur sur corner : tous deux sautent, Giroud capte le ballon de la tête = Giroud gagne le duel aérien. Si le défenseur le fauche en sautant = Giroud gagne le duel (fauté) | F2: CB|CF|DM|FB | G2: FALSE | H2: feat_aerial_duels_pct | I2: z_aerial_duels_pct | J2: aerialDuelsWonPercentage | K2: 3 | L2: =IFERROR(_xlfn.XLOOKUP(A2,feature_catalog!A:A,feature_catalog!A:A),"") -> aerialDuelsWonPercentage
A3: aerialDuelsWon | B3: aerial_duels_p90 | C3: vol | D3: Duels aériens gagnés — challenges en l'air pour des centres, dégagements ou balles longues. Indicateur de domination physique aérienne. Comptés séparément des duels au sol. | E3: Giroud saute plus haut que le défenseur et capte un corner de la tête = 1 aerial duel won | F3: CB|CF|DM | G3: FALSE | H3: feat_aerial_duels_p90 | I3: z_aerial_duels_p90 | J3: aerialDuelsWon | L3: =IFERROR(_xlfn.XLOOKUP(A3,feature_catalog!A:A,feature_catalog!A:A),"") -> aerialDuelsWon
A4: groundDuelsWonPercentage | B4: ground_duels_pct | C4: pct | D4: % duels au sol gagnés sur duels au sol disputés. Un duel est défini comme un contest 50/50 entre deux joueurs adverses. Indicateur de solidité au sol dans les duels 1v1. | E4: Tchouaméni : 6 duels sol gagnés / 9 disputés = 67%. Moyenne milieu défensif PL ≈ 55-60% | F4: DM|CM|CB|CF | G4: FALSE | H4: feat_ground_duels_pct | I4: z_ground_duels_pct | J4: groundDuelsWonPercentage | K4: 2.5 | L4: =IFERROR(_xlfn.XLOOKUP(A4,feature_catalog!A:A,feature_catalog!A:A),"") -> groundDuelsWonPercentage
A5: groundDuelsWon | B5: ground_duels_p90 | C5: vol | D5: Duels au sol gagnés — contests 50/50 sur le sol où le joueur récupère la possession. Comptés séparément des duels aériens. Indicateur de solidité physique au sol. | E5: Tchouaméni glisse dans un tacle et récupère le ballon face à De Bruyne = 1 ground duel won | F5: DM|CM|CB|CF | G5: FALSE | H5: feat_ground_duels_p90 | I5: z_ground_duels_p90 | J5: groundDuelsWon | L5: =IFERROR(_xlfn.XLOOKUP(A5,feature_catalog!A:A,feature_catalog!A:A),"") -> groundDuelsWon
A6: _duels_won_pct | B6: duels_won_pct | C6: pct | D6: % duels gagnés (tous types) — proxy calculé comme (groundDuelsWonPercentage + aerialDuelsWonPercentage) / 2. Indicateur global d'efficacité dans les duels 1v1. | E6: Tchouaméni : 67% duels sol + 58% duels aériens = 62.5% duels_won_pct | F6: CB|DM|CM|CF|FB | G6: FALSE | H6: feat_duels_won_pct | I6: z_duels_won_pct | J6: _duels_won_pct | L6: =IFERROR(_xlfn.XLOOKUP(A6,feature_catalog!A:A,feature_catalog!A:A),"") -> _duels_won_pct
A7: _duels_won_p90 | B7: duels_won_p90 | C7: vol | D7: Duels gagnés par 90min — somme des duels au sol et aériens gagnés (groundDuelsWon + aerialDuelsWon), converti en per-90. Indicateur global de présence physique dans les duels. | E7: Tchouaméni : 4 duels sol gagnés + 2 duels aériens gagnés = 6 duels_won pour ce match | F7: CB|DM|CM|CF | G7: FALSE | H7: feat_duels_won_p90 | I7: z_duels_won_p90 | J7: _duels_won_p90 | L7: =IFERROR(_xlfn.XLOOKUP(A7,feature_catalog!A:A,feature_catalog!A:A),"") -> _duels_won_p90
A8: _tackle_success_pct | B8: tackle_success_pct | C8: pct | D8: % tacles réussis = tacklesWon / tackles × 100. Mesure l'efficacité défensive au sol. Distingue le défenseur engagé précis (haut %) du défenseur brouillon qui tacle beaucoup mais perd souvent. | E8: Fabinho : 8 tacles, 6 remportés = 75% tackle success. Valeur top DM PL ≈ 65-75% | F8: DM|CB|CM|FB | G8: FALSE | H8: feat_tackle_success_pct | I8: z_tackle_success_pct | J8: _tackle_success_pct | L8: =IFERROR(_xlfn.XLOOKUP(A8,feature_catalog!A:A,feature_catalog!A:A),"") -> _tackle_success_pct
A9: tackles | B9: tackles_p90 | C9: vol | D9: Tacle réussi = le joueur entre en contact avec le ballon dans un duel au sol et récupère la possession ou dégage le ballon. Le joueur taclé doit clairement être en possession. Couper une passe n'est PAS un tacle (c'est une interception). | E9: Kanté glisse et rafle le ballon sous le pied de Pogba qui avait le contrôle = 1 tackle. Kanté intercepte une passe = interception, pas tackle | F9: DM|CB|CM|FB | G9: FALSE | H9: feat_tackles_p90 | I9: z_tackles_p90 | J9: tackles | L9: =IFERROR(_xlfn.XLOOKUP(A9,feature_catalog!A:A,feature_catalog!A:A),"") -> tackles
A10: tacklesWon | B10: tackles_won_p90 | C10: vol | D10: Sous-ensemble des tacles : tacles remportés où le joueur récupère proprement la possession après le tacle (pas seulement dégagé). Indicateur de qualité défensive au sol. | E10: Kanté tacklé Pogba et repart avec le ballon = 1 tackle won. Kanté dévie le ballon en touche = tacle mais pas won | F10: DM|CB|CM|FB | G10: FALSE | H10: feat_tackles_won_p90 | I10: z_tackles_won_p90 | J10: tacklesWon | L10: =IFERROR(_xlfn.XLOOKUP(A10,feature_catalog!A:A,feature_catalog!A:A),"") -> tacklesWon
A11: interceptions | B11: interceptions_p90 | C11: vol | D11: Le joueur lit la passe adverse et se déplace dans la trajectoire du ballon pour l'intercepter. Geste ANTICIPATIF — le joueur doit se déplacer vers la ligne de passe avant que le ballon arrive. Différent du tacle (réactif sur porteur) et de la récupération (ballon libre). | E11: Fabinho lit une passe horizontale, se décale et intercepte le ballon dans sa course = 1 interception. Fabinho récupère un rebond qui traîne = ball recovery, pas interception | F11: DM|CB|CM|FB | G11: FALSE | H11: feat_interceptions_p90 | I11: z_interceptions_p90 | J11: interceptions | K11: 1 | L11: =IFERROR(_xlfn.XLOOKUP(A11,feature_catalog!A:A,feature_catalog!A:A),"") -> interceptions
A12: clearances | B12: clearances_p90 | C12: vol | D12: Dégagement = action d'un joueur qui éloigne le ballon d'une zone dangereuse SANS cible précise — il n'essaie pas de passer à un coéquipier, juste de dégager le danger. Si une cible est identifiée, c'est une passe. | E12: Stones dégage un centre tendu de la tête dans les tribunes = 1 clearance. Stones contrôle le même centre et passe à Ederson = passe, pas clearance | F12: CB|FB|DM | G12: FALSE | H12: feat_clearances_p90 | I12: z_clearances_p90 | J12: clearances | L12: =IFERROR(_xlfn.XLOOKUP(A12,feature_catalog!A:A,feature_catalog!A:A),"") -> clearances
A13: headedClearances | B13: headed_clear_p90 | C13: vol | D13: Sous-ensemble des clearances : dégagements effectués de la tête uniquement. Indicateur de domination aérienne défensive dans la surface propre. | E13: Dias dégage un corner adverse de la tête = 1 headed clearance | F13: CB|GK | G13: FALSE | H13: feat_headed_clear_p90 | I13: z_headed_clear_p90 | J13: headedClearances | L13: =IFERROR(_xlfn.XLOOKUP(A13,feature_catalog!A:A,feature_catalog!A:A),"")
A14: blockedShots | B14: blocked_shots_p90 | C14: vol | D14: Joueur de champ qui bloque une tentative de but adverse. Condition stricte Opta : le tir doit être dirigé vers le but (aurait été cadré ou but sans le bloc). Si le tir allait de toute façon à côté, aucun bloc n'est comptabilisé. | E14: Van Dijk se jette devant la frappe de Salah adverse qui allait en haut du poteau = 1 blocked shot. Van Dijk dévie un tir qui allait largement à côté = 0 blocked shot | F14: CB|DM|CM | G14: FALSE | H14: feat_blocked_shots_p90 | I14: z_blocked_shots_p90 | J14: blockedShots | L14: =IFERROR(_xlfn.XLOOKUP(A14,feature_catalog!A:A,feature_catalog!A:A),"") -> blockedShots
A15: outfielderBlocks | B15: outfielder_blocks_p90 | C15: vol | D15: Bloc ou dégagement d'urgence d'un joueur de champ — intervention défensive où le joueur se sacrifie pour couper un tir ou une passe dangereuse dans la surface. Différent de blockedShots (moins strict sur la direction). | E15: Saliba plonge devant une frappe dans la surface et la dévie en corner = 1 outfielder block | F15: CD|DM | G15: FALSE | H15: feat_outfielder_blocks_p90 | I15: z_outfielder_blocks_p90 | J15: outfielderBlocks | L15: =IFERROR(_xlfn.XLOOKUP(A15,feature_catalog!A:A,feature_catalog!A:A),"") -> outfielderBlocks
A16: ballRecovery | B16: ball_recovery_p90 | C16: vol | D16: Récupération de balle — action où le joueur obtient la possession sur un ballon libre ou dévié, sans que ce soit un tacle direct sur porteur ni une interception anticipée. Inclut les segundas pelotas. | E16: Kanté se retrouve sur un rebond d'un tir adverse et récupère le ballon = 1 ball recovery | F16: DM|CM|CD|FB | G16: FALSE | H16: feat_ball_recovery_p90 | I16: z_ball_recovery_p90 | J16: ballRecovery | L16: =IFERROR(_xlfn.XLOOKUP(A16,feature_catalog!A:A,feature_catalog!A:A),"") -> ballRecovery
A17: dribbledPast | B17: dribbled_past_p90 | C17: vol | D17: Nombre de fois où un adversaire réussit un dribble sur ce joueur. Feature défensive à inverser : moins le joueur se fait dribbler, mieux c'est. Indicateur de solidité défensive individuelle au sol. | E17: Salah élimine le latéral adverse qui ne peut que le faucher = 1 dribbled past pour le défenseur | F17: CD|FB | G17: TRUE | H17: feat_dribbled_past_p90 | I17: z_dribbled_past_p90 | J17: dribbledPast | K17: 1.5 | L17: =IFERROR(_xlfn.XLOOKUP(A17,feature_catalog!A:A,feature_catalog!A:A),"") -> dribbledPast
A18: possessionWonAttThird | B18: poss_won_att3_p90 | C18: vol | D18: Ballons récupérés dans le tiers offensif adverse — résultat d'un pressing haut réussi ou d'une interception dans la zone ennemie. Indicateur d'intensité et d'efficacité du pressing offensif. | E18: Firmino presse le défenseur adverse dans son couloir défensif, provoque une mauvaise passe et récupère = 1 possession won att third | F18: CF|W|AM|CM | G18: FALSE | H18: feat_poss_won_att3_p90 | I18: z_poss_won_att3_p90 | J18: possessionWonAttThird | L18: =IFERROR(_xlfn.XLOOKUP(A18,feature_catalog!A:A,feature_catalog!A:A),"") -> possessionWonAttThird
A19: errorLeadToGoal | B19: errors_goal_p90 | C19: vol | D19: Erreur individuelle d'un joueur menant DIRECTEMENT à un but encaissé. L'erreur doit être la cause directe sans phase de jeu intermédiaire. Très rare — 0 à 2 occurrences par saison pour la plupart des joueurs. | E19: Maguire perd le ballon dans sa propre surface, l'adversaire marque immédiatement = 1 errorLeadToGoal. Feature à inverser | F19: CD|GK|FB | G19: TRUE | H19: feat_errors_goal_p90 | I19: z_errors_goal_p90 | J19: errorLeadToGoal | L19: =IFERROR(_xlfn.XLOOKUP(A19,feature_catalog!A:A,feature_catalog!A:A),"") -> errorLeadToGoal
A20: errorLeadToShot | B20: errors_shot_p90 | C20: vol | D20: Erreur menant DIRECTEMENT à un tir adverse, but ou non. Sur-ensemble de errorLeadToGoal — chaque errorLeadToGoal est aussi un errorLeadToShot mais pas l'inverse. Légèrement plus fréquent (2-6/saison). | E20: Stones glisse et offre le ballon à Salah qui tire (gardien arrête) = 1 errorLeadToShot mais pas errorLeadToGoal | F20: CD|GK|FB | G20: TRUE | H20: feat_errors_shot_p90 | I20: z_errors_shot_p90 | J20: errorLeadToShot | K20: 1.5 | L20: =IFERROR(_xlfn.XLOOKUP(A20,feature_catalog!A:A,feature_catalog!A:A),"") -> errorLeadToShot
A21: fouls | B21: fouls_p90 | C21: vol | D21: Fautes commises — infractions sifflées suite à un contact irrégulier du joueur sur un adversaire. Comptée indépendamment du carton éventuel. Feature à inverser : moins = mieux. | E21: Tchouaméni tacklé irrégulièrement un adversaire, arbitre siffle = 1 foul. Valeur typique DM ≈ 2-3/match | F21: DM|CB|CM | G21: TRUE | H21: feat_fouls_p90 | I21: z_fouls_p90 | J21: fouls | L21: =IFERROR(_xlfn.XLOOKUP(A21,feature_catalog!A:A,feature_catalog!A:A),"") -> fouls
A22: penaltyConceded | B22: penalty_conc_p90 | C22: vol | D22: Pénalty concédé — faute commise par ce joueur dans sa propre surface de réparation, entraînant un pénalty pour l'adversaire. Feature à inverser : moins = mieux. | E22: Pavard fauche Mbappé dans la surface = 1 penalty conceded pour Pavard | F22: CD|FB | G22: TRUE | H22: feat_penalty_conc_p90 | I22: z_penalty_conc_p90 | J22: penaltyConceded | K22: =_xlfn.XLOOKUP(J22,defenseur_central!J:J,defenseur_central!K:K) -> 0 | L22: =IFERROR(_xlfn.XLOOKUP(A22,feature_catalog!A:A,feature_catalog!A:A),"") -> penaltyConceded
A23: accuratePassesPercentage | B23: pass_acc_pct | C23: pct | D23: Passes réussies divisées par passes tentées. Une passe est réussie si un coéquipier la contrôle. Exclut les corners, remises en jeu, dégagements du gardien et centres (comptés séparément). | E23: Kroos : 85 passes réussies / 90 tentées = 94.4%. Moyenne DM Premier League ≈ 82% | F23: CM|DM|CB|FB|AM|GK | G23: FALSE | H23: feat_pass_acc_pct | I23: z_pass_acc_pct | J23: accuratePassesPercentage | K23: 1 | L23: =IFERROR(_xlfn.XLOOKUP(A23,feature_catalog!A:A,feature_catalog!A:A),"") -> accuratePassesPercentage
A24: accurateLongBallsPercentage | B24: long_balls_pct | C24: pct | D24: Passes longues réussies sur passes longues tentées. Une passe longue est définie par Opta comme un ballon joué en hauteur sur une distance significative (généralement >32m). Indicateur clé des CBs relanceurs et gardiens modernes. | E24: Rúben Dias joue 8 longues passes, 6 arrivent à un coéquipier = 75% long balls | F24: CB|DM|GK|CM | G24: FALSE | H24: feat_long_balls_pct | I24: z_long_balls_pct | J24: accurateLongBallsPercentage | L24: =IFERROR(_xlfn.XLOOKUP(A24,feature_catalog!A:A,feature_catalog!A:A),"") -> accurateLongBallsPercentage
A25: accurateLongBalls | B25: long_balls_p90 | C25: vol | D25: Passes longues réussies — ballon joué en hauteur sur une distance significative (généralement >32m) récupéré par un coéquipier. Comptées en absolu per-90. | E25: Rúben Dias joue 8 longues passes dont 6 arrivent à un coéquipier = 6 long balls réussies | F25: CB|DM|GK|CM | G25: FALSE | H25: feat_long_balls_p90 | I25: z_long_balls_p90 | J25: accurateLongBalls | L25: =IFERROR(_xlfn.XLOOKUP(A25,feature_catalog!A:A,feature_catalog!A:A),"") -> accurateLongBalls
A26: possessionLost | B26: poss_lost_p90 | C26: vol | D26: Nombre de fois où le joueur perd la possession — tacle adverse réussi sur lui, mauvais contrôle, passe ratée dans les pieds adverses, interception subie. Comptabilisé uniquement quand la possession change d'équipe suite à l'action du joueur. | E26: Griezmann reçoit, adverse le tacklé et récupère le ballon = 1 possession lost pour Griezmann | F26: CF|W|CM|DM|CB | G26: TRUE | H26: feat_poss_lost_p90 | I26: z_poss_lost_p90 | J26: possessionLost | L26: =IFERROR(_xlfn.XLOOKUP(A26,feature_catalog!A:A,feature_catalog!A:A),"") -> possessionLost
A27: headedGoals | B27: headed_goals_p90 | C27: vol | D27: Buts marqués de la tête — sous-ensemble de goals attribués à une touche de tête intentionnelle. Indicateur de domination aérienne offensive. | E27: Giroud détourne un corner de la tête en haut du filet = 1 headed goal | F27: CF|CD | G27: FALSE | H27: feat_headed_goals_p90 | I27: z_headed_goals_p90 | J27: headedGoals | L27: =IFERROR(_xlfn.XLOOKUP(A27,feature_catalog!A:A,feature_catalog!A:A),"") -> headedGoals
A28: rating | B28: ss_rating | C28: raw | D28: Note SofaScore calculée algorithmiquement à partir de l'ensemble des actions de jeu pondérées par poste. Échelle 1-10, mise à jour après chaque match. Utilisée comme benchmark de validation des scores du modèle. | E28: De Bruyne : moyenne 7.3 sur la saison = excellent. Moyenne joueur ≈ 6.8. Gardien bonne saison ≈ 7.0-7.2 | F28: ALL | G28: FALSE | H28: feat_ss_rating | I28: z_ss_rating | J28: rating | L28: =IFERROR(_xlfn.XLOOKUP(A28,feature_catalog!A:A,feature_catalog!A:A),"") -> rating
A29: height | B29: height_cm | C29: raw | D29: Taille en cm déclarée sur le profil officiel Transfermarkt du joueur. Donnée statique, issue des fiches officielles clubs / fédérations. | E29: Virgil van Dijk : 193cm. Thibaut Courtois : 199cm. Seuil 'tour de contrôle' CB : ≥188cm | F29: CB|CF|GK | G29: FALSE | H29: feat_height_cm | I29: z_height_cm | J29: height | L29: =IFERROR(_xlfn.XLOOKUP(A29,feature_catalog!A:A,feature_catalog!A:A),"") -> height
A30: averageX | B30: avg_x | C30: raw | D30: Position X moyenne du joueur sur le terrain au moment de ses touches de balle, agrégée sur la saison via l'endpoint heatmap/overall SofaScore. X=0 = ligne de but propre, X=100 = ligne de but adverse. Calculé comme moyenne des coordonnées X de toutes les touches de la heatmap saison. | E30: Benzema saison faux-9 : avgX≈62 (milieu-haut). Haaland : avgX≈80 (très haut). Casemiro sentinelle : avgX≈35 (bas) | F30: ALL | G30: FALSE | H30: feat_avg_x | I30: z_avg_x | J30: averageX | L30: =IFERROR(_xlfn.XLOOKUP(A30,feature_catalog!A:A,feature_catalog!A:A),"") -> averageX
A31: averageY | B31: avg_y | C31: raw | D31: Position Y moyenne du joueur (axe latéral), agrégée sur la saison. Y=0 = ligne de touche gauche, Y=100 = ligne de touche droite, Y=50 = axe central. Utilisé pour distinguer ailier excentré (Y≈10 ou 90) d'un intérieur (Y≈30 ou 70). | E31: Trent Alexander-Arnold : avgY≈80 (côté droit collé). Modric : avgY≈50 (axe central). Salah ailier droit rentrant : avgY≈65 | F31: ALL | G31: FALSE | H31: feat_avg_y | I31: z_avg_y | J31: averageY | L31: =IFERROR(_xlfn.XLOOKUP(A31,feature_catalog!A:A,feature_catalog!A:A),"") -> averageY
L32: =IFERROR(_xlfn.XLOOKUP(A32,feature_catalog!A:A,feature_catalog!A:A),"") -> 0
L33: =IFERROR(_xlfn.XLOOKUP(A33,feature_catalog!A:A,feature_catalog!A:A),"") -> 0
L34: =IFERROR(_xlfn.XLOOKUP(A34,feature_catalog!A:A,feature_catalog!A:A),"") -> 0
L35: =IFERROR(_xlfn.XLOOKUP(A35,feature_catalog!A:A,feature_catalog!A:A),"") -> 0
L36: =IFERROR(_xlfn.XLOOKUP(A36,feature_catalog!A:A,feature_catalog!A:A),"") -> 0
L37: =IFERROR(_xlfn.XLOOKUP(A37,feature_catalog!A:A,feature_catalog!A:A),"") -> 0

Sheet libero_defensif
A1: source_column | B1: feature_name | C1: type | D1: description | E1: exemple | F1: relevant_roles | G1: inverted | H1: feat_col | I1: z_col | J1: source_column | K1: pondération
A2: interceptions | B2: interceptions_p90 | C2: vol | D2: Le joueur lit la passe adverse et se déplace dans la trajectoire du ballon pour l'intercepter. Geste ANTICIPATIF — le joueur doit se déplacer vers la ligne de passe avant que le ballon arrive. Différent du tacle (réactif sur porteur) et de la récupération (ballon libre). | E2: Fabinho lit une passe horizontale, se décale et intercepte le ballon dans sa course = 1 interception. Fabinho récupère un rebond qui traîne = ball recovery, pas interception | F2: DM|CB|CM|FB | G2: FALSE | H2: feat_interceptions_p90 | I2: z_interceptions_p90 | J2: interceptions | K2: 3 | L2: =IFERROR(_xlfn.XLOOKUP(A2,feature_catalog!A:A,feature_catalog!A:A),"") -> interceptions
A3: ballRecovery | B3: ball_recovery_p90 | C3: vol | D3: Récupération de balle — action où le joueur obtient la possession sur un ballon libre ou dévié, sans que ce soit un tacle direct sur porteur ni une interception anticipée. Inclut les segundas pelotas. | E3: Kanté se retrouve sur un rebond d'un tir adverse et récupère le ballon = 1 ball recovery | F3: DM|CM|CD|FB | G3: FALSE | H3: feat_ball_recovery_p90 | I3: z_ball_recovery_p90 | J3: ballRecovery | K3: 2 | L3: =IFERROR(_xlfn.XLOOKUP(A3,feature_catalog!A:A,feature_catalog!A:A),"") -> ballRecovery
A4: clearances | B4: clearances_p90 | C4: vol | D4: Dégagement = action d'un joueur qui éloigne le ballon d'une zone dangereuse SANS cible précise — il n'essaie pas de passer à un coéquipier, juste de dégager le danger. Si une cible est identifiée, c'est une passe. | E4: Stones dégage un centre tendu de la tête dans les tribunes = 1 clearance. Stones contrôle le même centre et passe à Ederson = passe, pas clearance | F4: CB|FB|DM | G4: FALSE | H4: feat_clearances_p90 | I4: z_clearances_p90 | J4: clearances | L4: =IFERROR(_xlfn.XLOOKUP(A4,feature_catalog!A:A,feature_catalog!A:A),"") -> clearances
A5: headedClearances | B5: headed_clear_p90 | C5: vol | D5: Sous-ensemble des clearances : dégagements effectués de la tête uniquement. Indicateur de domination aérienne défensive dans la surface propre. | E5: Dias dégage un corner adverse de la tête = 1 headed clearance | F5: CB|GK | G5: FALSE | H5: feat_headed_clear_p90 | I5: z_headed_clear_p90 | J5: headedClearances | L5: =IFERROR(_xlfn.XLOOKUP(A5,feature_catalog!A:A,feature_catalog!A:A),"")
A6: blockedShots | B6: blocked_shots_p90 | C6: vol | D6: Joueur de champ qui bloque une tentative de but adverse. Condition stricte Opta : le tir doit être dirigé vers le but (aurait été cadré ou but sans le bloc). Si le tir allait de toute façon à côté, aucun bloc n'est comptabilisé. | E6: Van Dijk se jette devant la frappe de Salah adverse qui allait en haut du poteau = 1 blocked shot. Van Dijk dévie un tir qui allait largement à côté = 0 blocked shot | F6: CB|DM|CM | G6: FALSE | H6: feat_blocked_shots_p90 | I6: z_blocked_shots_p90 | J6: blockedShots | L6: =IFERROR(_xlfn.XLOOKUP(A6,feature_catalog!A:A,feature_catalog!A:A),"") -> blockedShots
A7: outfielderBlocks | B7: outfielder_blocks_p90 | C7: vol | D7: Bloc ou dégagement d'urgence d'un joueur de champ — intervention défensive où le joueur se sacrifie pour couper un tir ou une passe dangereuse dans la surface. Différent de blockedShots (moins strict sur la direction). | E7: Saliba plonge devant une frappe dans la surface et la dévie en corner = 1 outfielder block | F7: CD|DM | G7: FALSE | H7: feat_outfielder_blocks_p90 | I7: z_outfielder_blocks_p90 | J7: outfielderBlocks | L7: =IFERROR(_xlfn.XLOOKUP(A7,feature_catalog!A:A,feature_catalog!A:A),"") -> outfielderBlocks
A8: aerialDuelsWonPercentage | B8: aerial_duels_pct | C8: pct | D8: Duels aériens gagnés sur duels aériens disputés. Un duel aérien nécessite 2+ joueurs qui challengent pour le même ballon en l'air. Gagné = le joueur obtient le premier contact contrôlé. Si fauté pendant le duel aérien, le joueur fauté gagne le duel. | E8: Giroud vs un défenseur sur corner : tous deux sautent, Giroud capte le ballon de la tête = Giroud gagne le duel aérien. Si le défenseur le fauche en sautant = Giroud gagne le duel (fauté) | F8: CB|CF|DM|FB | G8: FALSE | H8: feat_aerial_duels_pct | I8: z_aerial_duels_pct | J8: aerialDuelsWonPercentage | K8: 1 | L8: =IFERROR(_xlfn.XLOOKUP(A8,feature_catalog!A:A,feature_catalog!A:A),"") -> aerialDuelsWonPercentage
A9: aerialDuelsWon | B9: aerial_duels_p90 | C9: vol | D9: Duels aériens gagnés — challenges en l'air pour des centres, dégagements ou balles longues. Indicateur de domination physique aérienne. Comptés séparément des duels au sol. | E9: Giroud saute plus haut que le défenseur et capte un corner de la tête = 1 aerial duel won | F9: CB|CF|DM | G9: FALSE | H9: feat_aerial_duels_p90 | I9: z_aerial_duels_p90 | J9: aerialDuelsWon | L9: =IFERROR(_xlfn.XLOOKUP(A9,feature_catalog!A:A,feature_catalog!A:A),"") -> aerialDuelsWon
A10: groundDuelsWonPercentage | B10: ground_duels_pct | C10: pct | D10: % duels au sol gagnés sur duels au sol disputés. Un duel est défini comme un contest 50/50 entre deux joueurs adverses. Indicateur de solidité au sol dans les duels 1v1. | E10: Tchouaméni : 6 duels sol gagnés / 9 disputés = 67%. Moyenne milieu défensif PL ≈ 55-60% | F10: DM|CM|CB|CF | G10: FALSE | H10: feat_ground_duels_pct | I10: z_ground_duels_pct | J10: groundDuelsWonPercentage | K10: 2 | L10: =IFERROR(_xlfn.XLOOKUP(A10,feature_catalog!A:A,feature_catalog!A:A),"") -> groundDuelsWonPercentage
A11: groundDuelsWon | B11: ground_duels_p90 | C11: vol | D11: Duels au sol gagnés — contests 50/50 sur le sol où le joueur récupère la possession. Comptés séparément des duels aériens. Indicateur de solidité physique au sol. | E11: Tchouaméni glisse dans un tacle et récupère le ballon face à De Bruyne = 1 ground duel won | F11: DM|CM|CB|CF | G11: FALSE | H11: feat_ground_duels_p90 | I11: z_ground_duels_p90 | J11: groundDuelsWon | L11: =IFERROR(_xlfn.XLOOKUP(A11,feature_catalog!A:A,feature_catalog!A:A),"") -> groundDuelsWon
A12: _duels_won_pct | B12: duels_won_pct | C12: pct | D12: % duels gagnés (tous types) — proxy calculé comme (groundDuelsWonPercentage + aerialDuelsWonPercentage) / 2. Indicateur global d'efficacité dans les duels 1v1. | E12: Tchouaméni : 67% duels sol + 58% duels aériens = 62.5% duels_won_pct | F12: CB|DM|CM|CF|FB | G12: FALSE | H12: feat_duels_won_pct | I12: z_duels_won_pct | J12: _duels_won_pct | L12: =IFERROR(_xlfn.XLOOKUP(A12,feature_catalog!A:A,feature_catalog!A:A),"") -> _duels_won_pct
A13: _tackle_success_pct | B13: tackle_success_pct | C13: pct | D13: % tacles réussis = tacklesWon / tackles × 100. Mesure l'efficacité défensive au sol. Distingue le défenseur engagé précis (haut %) du défenseur brouillon qui tacle beaucoup mais perd souvent. | E13: Fabinho : 8 tacles, 6 remportés = 75% tackle success. Valeur top DM PL ≈ 65-75% | F13: DM|CB|CM|FB | G13: FALSE | H13: feat_tackle_success_pct | I13: z_tackle_success_pct | J13: _tackle_success_pct | L13: =IFERROR(_xlfn.XLOOKUP(A13,feature_catalog!A:A,feature_catalog!A:A),"") -> _tackle_success_pct
A14: tackles | B14: tackles_p90 | C14: vol | D14: Tacle réussi = le joueur entre en contact avec le ballon dans un duel au sol et récupère la possession ou dégage le ballon. Le joueur taclé doit clairement être en possession. Couper une passe n'est PAS un tacle (c'est une interception). | E14: Kanté glisse et rafle le ballon sous le pied de Pogba qui avait le contrôle = 1 tackle. Kanté intercepte une passe = interception, pas tackle | F14: DM|CB|CM|FB | G14: FALSE | H14: feat_tackles_p90 | I14: z_tackles_p90 | J14: tackles | L14: =IFERROR(_xlfn.XLOOKUP(A14,feature_catalog!A:A,feature_catalog!A:A),"") -> tackles
A15: tacklesWon | B15: tackles_won_p90 | C15: vol | D15: Sous-ensemble des tacles : tacles remportés où le joueur récupère proprement la possession après le tacle (pas seulement dégagé). Indicateur de qualité défensive au sol. | E15: Kanté tacklé Pogba et repart avec le ballon = 1 tackle won. Kanté dévie le ballon en touche = tacle mais pas won | F15: DM|CB|CM|FB | G15: FALSE | H15: feat_tackles_won_p90 | I15: z_tackles_won_p90 | J15: tacklesWon | L15: =IFERROR(_xlfn.XLOOKUP(A15,feature_catalog!A:A,feature_catalog!A:A),"") -> tacklesWon
A16: dribbledPast | B16: dribbled_past_p90 | C16: vol | D16: Nombre de fois où un adversaire réussit un dribble sur ce joueur. Feature défensive à inverser : moins le joueur se fait dribbler, mieux c'est. Indicateur de solidité défensive individuelle au sol. | E16: Salah élimine le latéral adverse qui ne peut que le faucher = 1 dribbled past pour le défenseur | F16: CD|FB | G16: TRUE | H16: feat_dribbled_past_p90 | I16: z_dribbled_past_p90 | J16: dribbledPast | K16: 2 | L16: =IFERROR(_xlfn.XLOOKUP(A16,feature_catalog!A:A,feature_catalog!A:A),"") -> dribbledPast
A17: averageX | B17: avg_x | C17: raw | D17: Position X moyenne du joueur sur le terrain au moment de ses touches de balle, agrégée sur la saison via l'endpoint heatmap/overall SofaScore. X=0 = ligne de but propre, X=100 = ligne de but adverse. Calculé comme moyenne des coordonnées X de toutes les touches de la heatmap saison. | E17: Benzema saison faux-9 : avgX≈62 (milieu-haut). Haaland : avgX≈80 (très haut). Casemiro sentinelle : avgX≈35 (bas) | F17: ALL | G17: FALSE | H17: feat_avg_x | I17: z_avg_x | J17: averageX | L17: =IFERROR(_xlfn.XLOOKUP(A17,feature_catalog!A:A,feature_catalog!A:A),"") -> averageX
A18: errorLeadToGoal | B18: errors_goal_p90 | C18: vol | D18: Erreur individuelle d'un joueur menant DIRECTEMENT à un but encaissé. L'erreur doit être la cause directe sans phase de jeu intermédiaire. Très rare — 0 à 2 occurrences par saison pour la plupart des joueurs. | E18: Maguire perd le ballon dans sa propre surface, l'adversaire marque immédiatement = 1 errorLeadToGoal. Feature à inverser | F18: CD|GK|FB | G18: TRUE | H18: feat_errors_goal_p90 | I18: z_errors_goal_p90 | J18: errorLeadToGoal | L18: =IFERROR(_xlfn.XLOOKUP(A18,feature_catalog!A:A,feature_catalog!A:A),"") -> errorLeadToGoal
A19: errorLeadToShot | B19: errors_shot_p90 | C19: vol | D19: Erreur menant DIRECTEMENT à un tir adverse, but ou non. Sur-ensemble de errorLeadToGoal — chaque errorLeadToGoal est aussi un errorLeadToShot mais pas l'inverse. Légèrement plus fréquent (2-6/saison). | E19: Stones glisse et offre le ballon à Salah qui tire (gardien arrête) = 1 errorLeadToShot mais pas errorLeadToGoal | F19: CD|GK|FB | G19: TRUE | H19: feat_errors_shot_p90 | I19: z_errors_shot_p90 | J19: errorLeadToShot | K19: 2 | L19: =IFERROR(_xlfn.XLOOKUP(A19,feature_catalog!A:A,feature_catalog!A:A),"") -> errorLeadToShot
A20: penaltyConceded | B20: penalty_conc_p90 | C20: vol | D20: Pénalty concédé — faute commise par ce joueur dans sa propre surface de réparation, entraînant un pénalty pour l'adversaire. Feature à inverser : moins = mieux. | E20: Pavard fauche Mbappé dans la surface = 1 penalty conceded pour Pavard | F20: CD|FB | G20: TRUE | H20: feat_penalty_conc_p90 | I20: z_penalty_conc_p90 | J20: penaltyConceded | L20: =IFERROR(_xlfn.XLOOKUP(A20,feature_catalog!A:A,feature_catalog!A:A),"") -> penaltyConceded
A21: fouls | B21: fouls_p90 | C21: vol | D21: Fautes commises — infractions sifflées suite à un contact irrégulier du joueur sur un adversaire. Comptée indépendamment du carton éventuel. Feature à inverser : moins = mieux. | E21: Tchouaméni tacklé irrégulièrement un adversaire, arbitre siffle = 1 foul. Valeur typique DM ≈ 2-3/match | F21: DM|CB|CM | G21: TRUE | H21: feat_fouls_p90 | I21: z_fouls_p90 | J21: fouls | K21: 1 | L21: =IFERROR(_xlfn.XLOOKUP(A21,feature_catalog!A:A,feature_catalog!A:A),"") -> fouls
A22: possessionLost | B22: poss_lost_p90 | C22: vol | D22: Nombre de fois où le joueur perd la possession — tacle adverse réussi sur lui, mauvais contrôle, passe ratée dans les pieds adverses, interception subie. Comptabilisé uniquement quand la possession change d'équipe suite à l'action du joueur. | E22: Griezmann reçoit, adverse le tacklé et récupère le ballon = 1 possession lost pour Griezmann | F22: CF|W|CM|DM|CB | G22: TRUE | H22: feat_poss_lost_p90 | I22: z_poss_lost_p90 | J22: possessionLost | K22: 1 | L22: =IFERROR(_xlfn.XLOOKUP(A22,feature_catalog!A:A,feature_catalog!A:A),"") -> possessionLost
A23: accuratePassesPercentage | B23: pass_acc_pct | C23: pct | D23: Passes réussies divisées par passes tentées. Une passe est réussie si un coéquipier la contrôle. Exclut les corners, remises en jeu, dégagements du gardien et centres (comptés séparément). | E23: Kroos : 85 passes réussies / 90 tentées = 94.4%. Moyenne DM Premier League ≈ 82% | F23: CM|DM|CB|FB|AM|GK | G23: FALSE | H23: feat_pass_acc_pct | I23: z_pass_acc_pct | J23: accuratePassesPercentage | K23: 1.5 | L23: =IFERROR(_xlfn.XLOOKUP(A23,feature_catalog!A:A,feature_catalog!A:A),"") -> accuratePassesPercentage
A24: accurateLongBallsPercentage | B24: long_balls_pct | C24: pct | D24: Passes longues réussies sur passes longues tentées. Une passe longue est définie par Opta comme un ballon joué en hauteur sur une distance significative (généralement >32m). Indicateur clé des CBs relanceurs et gardiens modernes. | E24: Rúben Dias joue 8 longues passes, 6 arrivent à un coéquipier = 75% long balls | F24: CB|DM|GK|CM | G24: FALSE | H24: feat_long_balls_pct | I24: z_long_balls_pct | J24: accurateLongBallsPercentage | L24: =IFERROR(_xlfn.XLOOKUP(A24,feature_catalog!A:A,feature_catalog!A:A),"") -> accurateLongBallsPercentage
A25: accurateLongBalls | B25: long_balls_p90 | C25: vol | D25: Passes longues réussies — ballon joué en hauteur sur une distance significative (généralement >32m) récupéré par un coéquipier. Comptées en absolu per-90. | E25: Rúben Dias joue 8 longues passes dont 6 arrivent à un coéquipier = 6 long balls réussies | F25: CB|DM|GK|CM | G25: FALSE | H25: feat_long_balls_p90 | I25: z_long_balls_p90 | J25: accurateLongBalls | L25: =IFERROR(_xlfn.XLOOKUP(A25,feature_catalog!A:A,feature_catalog!A:A),"") -> accurateLongBalls
A26: rating | B26: ss_rating | C26: raw | D26: Note SofaScore calculée algorithmiquement à partir de l'ensemble des actions de jeu pondérées par poste. Échelle 1-10, mise à jour après chaque match. Utilisée comme benchmark de validation des scores du modèle. | E26: De Bruyne : moyenne 7.3 sur la saison = excellent. Moyenne joueur ≈ 6.8. Gardien bonne saison ≈ 7.0-7.2 | F26: ALL | G26: FALSE | H26: feat_ss_rating | I26: z_ss_rating | J26: rating | L26: =IFERROR(_xlfn.XLOOKUP(A26,feature_catalog!A:A,feature_catalog!A:A),"") -> rating
A27: height | B27: height_cm | C27: raw | D27: Taille en cm déclarée sur le profil officiel Transfermarkt du joueur. Donnée statique, issue des fiches officielles clubs / fédérations. | E27: Virgil van Dijk : 193cm. Thibaut Courtois : 199cm. Seuil 'tour de contrôle' CB : ≥188cm | F27: CB|CF|GK | G27: FALSE | H27: feat_height_cm | I27: z_height_cm | J27: height | L27: =IFERROR(_xlfn.XLOOKUP(A27,feature_catalog!A:A,feature_catalog!A:A),"") -> height
A28: averageY | B28: avg_y | C28: raw | D28: Position Y moyenne du joueur (axe latéral), agrégée sur la saison. Y=0 = ligne de touche gauche, Y=100 = ligne de touche droite, Y=50 = axe central. Utilisé pour distinguer ailier excentré (Y≈10 ou 90) d'un intérieur (Y≈30 ou 70). | E28: Trent Alexander-Arnold : avgY≈80 (côté droit collé). Modric : avgY≈50 (axe central). Salah ailier droit rentrant : avgY≈65 | F28: ALL | G28: FALSE | H28: feat_avg_y | I28: z_avg_y | J28: averageY | L28: =IFERROR(_xlfn.XLOOKUP(A28,feature_catalog!A:A,feature_catalog!A:A),"") -> averageY
L29: =IFERROR(_xlfn.XLOOKUP(A29,feature_catalog!A:A,feature_catalog!A:A),"") -> 0
L30: =IFERROR(_xlfn.XLOOKUP(A30,feature_catalog!A:A,feature_catalog!A:A),"") -> 0
L31: =IFERROR(_xlfn.XLOOKUP(A31,feature_catalog!A:A,feature_catalog!A:A),"") -> 0
L32: =IFERROR(_xlfn.XLOOKUP(A32,feature_catalog!A:A,feature_catalog!A:A),"") -> 0
L33: =IFERROR(_xlfn.XLOOKUP(A33,feature_catalog!A:A,feature_catalog!A:A),"") -> 0
L34: =IFERROR(_xlfn.XLOOKUP(A34,feature_catalog!A:A,feature_catalog!A:A),"") -> 0
L35: =IFERROR(_xlfn.XLOOKUP(A35,feature_catalog!A:A,feature_catalog!A:A),"") -> 0
L36: =IFERROR(_xlfn.XLOOKUP(A36,feature_catalog!A:A,feature_catalog!A:A),"")
L37: =IFERROR(_xlfn.XLOOKUP(A37,feature_catalog!A:A,feature_catalog!A:A),"") -> 0

Sheet tour_de_controle
A1: source_column | B1: feature_name | C1: type | D1: description | E1: exemple | F1: relevant_roles | G1: inverted | H1: feat_col | I1: z_col | J1: source_column | K1: pondération
A2: aerialDuelsWonPercentage | B2: aerial_duels_pct | C2: pct | D2: Duels aériens gagnés sur duels aériens disputés. Un duel aérien nécessite 2+ joueurs qui challengent pour le même ballon en l'air. Gagné = le joueur obtient le premier contact contrôlé. Si fauté pendant le duel aérien, le joueur fauté gagne le duel. | E2: Giroud vs un défenseur sur corner : tous deux sautent, Giroud capte le ballon de la tête = Giroud gagne le duel aérien. Si le défenseur le fauche en sautant = Giroud gagne le duel (fauté) | F2: CB|CF|DM|FB | G2: FALSE | H2: feat_aerial_duels_pct | I2: z_aerial_duels_pct | J2: aerialDuelsWonPercentage | K2: 2.5 | L2: =IFERROR(_xlfn.XLOOKUP(A2,feature_catalog!A:A,feature_catalog!A:A),"") -> aerialDuelsWonPercentage
A3: aerialDuelsWon | B3: aerial_duels_p90 | C3: vol | D3: Duels aériens gagnés — challenges en l'air pour des centres, dégagements ou balles longues. Indicateur de domination physique aérienne. Comptés séparément des duels au sol. | E3: Giroud saute plus haut que le défenseur et capte un corner de la tête = 1 aerial duel won | F3: CB|CF|DM | G3: FALSE | H3: feat_aerial_duels_p90 | I3: z_aerial_duels_p90 | J3: aerialDuelsWon | K3: 1 | L3: =IFERROR(_xlfn.XLOOKUP(A3,feature_catalog!A:A,feature_catalog!A:A),"") -> aerialDuelsWon
A4: headedGoals | B4: headed_goals_p90 | C4: vol | D4: Buts marqués de la tête — sous-ensemble de goals attribués à une touche de tête intentionnelle. Indicateur de domination aérienne offensive. | E4: Giroud détourne un corner de la tête en haut du filet = 1 headed goal | F4: CF|CD | G4: FALSE | H4: feat_headed_goals_p90 | I4: z_headed_goals_p90 | J4: headedGoals | K4: 1.5 | L4: =IFERROR(_xlfn.XLOOKUP(A4,feature_catalog!A:A,feature_catalog!A:A),"") -> headedGoals
A5: highClaims | B5: high_claims_p90 | C5: vol | D5: Captages hauts réussis — le gardien sort aériennement pour attraper ou dégager un centre ou corner en hauteur, en challengeant avec des attaquants adverses. Réussi = le gardien capture ou dégage proprement sans laisser la balle traîner. | E5: Alisson sort sur un corner, capte le ballon devant Lukaku qui challengeait = 1 high claim réussi. Alisson sort, perd le duel et le ballon traîne = 0 high claim réussi | F5: GK | G5: FALSE | H5: feat_high_claims_p90 | I5: z_high_claims_p90 | J5: highClaims | L5: =IFERROR(_xlfn.XLOOKUP(A5,feature_catalog!A:A,feature_catalog!A:A),"") -> highClaims
A6: groundDuelsWonPercentage | B6: ground_duels_pct | C6: pct | D6: % duels au sol gagnés sur duels au sol disputés. Un duel est défini comme un contest 50/50 entre deux joueurs adverses. Indicateur de solidité au sol dans les duels 1v1. | E6: Tchouaméni : 6 duels sol gagnés / 9 disputés = 67%. Moyenne milieu défensif PL ≈ 55-60% | F6: DM|CM|CB|CF | G6: FALSE | H6: feat_ground_duels_pct | I6: z_ground_duels_pct | J6: groundDuelsWonPercentage | K6: 2 | L6: =IFERROR(_xlfn.XLOOKUP(A6,feature_catalog!A:A,feature_catalog!A:A),"") -> groundDuelsWonPercentage
A7: groundDuelsWon | B7: ground_duels_p90 | C7: vol | D7: Duels au sol gagnés — contests 50/50 sur le sol où le joueur récupère la possession. Comptés séparément des duels aériens. Indicateur de solidité physique au sol. | E7: Tchouaméni glisse dans un tacle et récupère le ballon face à De Bruyne = 1 ground duel won | F7: DM|CM|CB|CF | G7: FALSE | H7: feat_ground_duels_p90 | I7: z_ground_duels_p90 | J7: groundDuelsWon | L7: =IFERROR(_xlfn.XLOOKUP(A7,feature_catalog!A:A,feature_catalog!A:A),"") -> groundDuelsWon
A8: _duels_won_pct | B8: duels_won_pct | C8: pct | D8: % duels gagnés (tous types) — proxy calculé comme (groundDuelsWonPercentage + aerialDuelsWonPercentage) / 2. Indicateur global d'efficacité dans les duels 1v1. | E8: Tchouaméni : 67% duels sol + 58% duels aériens = 62.5% duels_won_pct | F8: CB|DM|CM|CF|FB | G8: FALSE | H8: feat_duels_won_pct | I8: z_duels_won_pct | J8: _duels_won_pct | L8: =IFERROR(_xlfn.XLOOKUP(A8,feature_catalog!A:A,feature_catalog!A:A),"") -> _duels_won_pct
A9: _duels_won_p90 | B9: duels_won_p90 | C9: vol | D9: Duels gagnés par 90min — somme des duels au sol et aériens gagnés (groundDuelsWon + aerialDuelsWon), converti en per-90. Indicateur global de présence physique dans les duels. | E9: Tchouaméni : 4 duels sol gagnés + 2 duels aériens gagnés = 6 duels_won pour ce match | F9: CB|DM|CM|CF | G9: FALSE | H9: feat_duels_won_p90 | I9: z_duels_won_p90 | J9: _duels_won_p90 | L9: =IFERROR(_xlfn.XLOOKUP(A9,feature_catalog!A:A,feature_catalog!A:A),"") -> _duels_won_p90
A10: _tackle_success_pct | B10: tackle_success_pct | C10: pct | D10: % tacles réussis = tacklesWon / tackles × 100. Mesure l'efficacité défensive au sol. Distingue le défenseur engagé précis (haut %) du défenseur brouillon qui tacle beaucoup mais perd souvent. | E10: Fabinho : 8 tacles, 6 remportés = 75% tackle success. Valeur top DM PL ≈ 65-75% | F10: DM|CB|CM|FB | G10: FALSE | H10: feat_tackle_success_pct | I10: z_tackle_success_pct | J10: _tackle_success_pct | L10: =IFERROR(_xlfn.XLOOKUP(A10,feature_catalog!A:A,feature_catalog!A:A),"") -> _tackle_success_pct
A11: tackles | B11: tackles_p90 | C11: vol | D11: Tacle réussi = le joueur entre en contact avec le ballon dans un duel au sol et récupère la possession ou dégage le ballon. Le joueur taclé doit clairement être en possession. Couper une passe n'est PAS un tacle (c'est une interception). | E11: Kanté glisse et rafle le ballon sous le pied de Pogba qui avait le contrôle = 1 tackle. Kanté intercepte une passe = interception, pas tackle | F11: DM|CB|CM|FB | G11: FALSE | H11: feat_tackles_p90 | I11: z_tackles_p90 | J11: tackles | L11: =IFERROR(_xlfn.XLOOKUP(A11,feature_catalog!A:A,feature_catalog!A:A),"") -> tackles
A12: clearances | B12: clearances_p90 | C12: vol | D12: Dégagement = action d'un joueur qui éloigne le ballon d'une zone dangereuse SANS cible précise — il n'essaie pas de passer à un coéquipier, juste de dégager le danger. Si une cible est identifiée, c'est une passe. | E12: Stones dégage un centre tendu de la tête dans les tribunes = 1 clearance. Stones contrôle le même centre et passe à Ederson = passe, pas clearance | F12: CB|FB|DM | G12: FALSE | H12: feat_clearances_p90 | I12: z_clearances_p90 | J12: clearances | L12: =IFERROR(_xlfn.XLOOKUP(A12,feature_catalog!A:A,feature_catalog!A:A),"") -> clearances
A13: blockedShots | B13: blocked_shots_p90 | C13: vol | D13: Joueur de champ qui bloque une tentative de but adverse. Condition stricte Opta : le tir doit être dirigé vers le but (aurait été cadré ou but sans le bloc). Si le tir allait de toute façon à côté, aucun bloc n'est comptabilisé. | E13: Van Dijk se jette devant la frappe de Salah adverse qui allait en haut du poteau = 1 blocked shot. Van Dijk dévie un tir qui allait largement à côté = 0 blocked shot | F13: CB|DM|CM | G13: FALSE | H13: feat_blocked_shots_p90 | I13: z_blocked_shots_p90 | J13: blockedShots | L13: =IFERROR(_xlfn.XLOOKUP(A13,feature_catalog!A:A,feature_catalog!A:A),"") -> blockedShots
A14: outfielderBlocks | B14: outfielder_blocks_p90 | C14: vol | D14: Bloc ou dégagement d'urgence d'un joueur de champ — intervention défensive où le joueur se sacrifie pour couper un tir ou une passe dangereuse dans la surface. Différent de blockedShots (moins strict sur la direction). | E14: Saliba plonge devant une frappe dans la surface et la dévie en corner = 1 outfielder block | F14: CD|DM | G14: FALSE | H14: feat_outfielder_blocks_p90 | I14: z_outfielder_blocks_p90 | J14: outfielderBlocks | L14: =IFERROR(_xlfn.XLOOKUP(A14,feature_catalog!A:A,feature_catalog!A:A),"") -> outfielderBlocks
A15: ballRecovery | B15: ball_recovery_p90 | C15: vol | D15: Récupération de balle — action où le joueur obtient la possession sur un ballon libre ou dévié, sans que ce soit un tacle direct sur porteur ni une interception anticipée. Inclut les segundas pelotas. | E15: Kanté se retrouve sur un rebond d'un tir adverse et récupère le ballon = 1 ball recovery | F15: DM|CM|CD|FB | G15: FALSE | H15: feat_ball_recovery_p90 | I15: z_ball_recovery_p90 | J15: ballRecovery | L15: =IFERROR(_xlfn.XLOOKUP(A15,feature_catalog!A:A,feature_catalog!A:A),"") -> ballRecovery
A16: dribbledPast | B16: dribbled_past_p90 | C16: vol | D16: Nombre de fois où un adversaire réussit un dribble sur ce joueur. Feature défensive à inverser : moins le joueur se fait dribbler, mieux c'est. Indicateur de solidité défensive individuelle au sol. | E16: Salah élimine le latéral adverse qui ne peut que le faucher = 1 dribbled past pour le défenseur | F16: CD|FB | G16: TRUE | H16: feat_dribbled_past_p90 | I16: z_dribbled_past_p90 | J16: dribbledPast | K16: 1.5 | L16: =IFERROR(_xlfn.XLOOKUP(A16,feature_catalog!A:A,feature_catalog!A:A),"") -> dribbledPast
A17: errorLeadToGoal | B17: errors_goal_p90 | C17: vol | D17: Erreur individuelle d'un joueur menant DIRECTEMENT à un but encaissé. L'erreur doit être la cause directe sans phase de jeu intermédiaire. Très rare — 0 à 2 occurrences par saison pour la plupart des joueurs. | E17: Maguire perd le ballon dans sa propre surface, l'adversaire marque immédiatement = 1 errorLeadToGoal. Feature à inverser | F17: CD|GK|FB | G17: TRUE | H17: feat_errors_goal_p90 | I17: z_errors_goal_p90 | J17: errorLeadToGoal | L17: =IFERROR(_xlfn.XLOOKUP(A17,feature_catalog!A:A,feature_catalog!A:A),"") -> errorLeadToGoal
A18: errorLeadToShot | B18: errors_shot_p90 | C18: vol | D18: Erreur menant DIRECTEMENT à un tir adverse, but ou non. Sur-ensemble de errorLeadToGoal — chaque errorLeadToGoal est aussi un errorLeadToShot mais pas l'inverse. Légèrement plus fréquent (2-6/saison). | E18: Stones glisse et offre le ballon à Salah qui tire (gardien arrête) = 1 errorLeadToShot mais pas errorLeadToGoal | F18: CD|GK|FB | G18: TRUE | H18: feat_errors_shot_p90 | I18: z_errors_shot_p90 | J18: errorLeadToShot | K18: =_xlfn.XLOOKUP(J18,defenseur_central!J:J,defenseur_central!K:K) -> 2 | L18: =IFERROR(_xlfn.XLOOKUP(A18,feature_catalog!A:A,feature_catalog!A:A),"") -> errorLeadToShot
A19: fouls | B19: fouls_p90 | C19: vol | D19: Fautes commises — infractions sifflées suite à un contact irrégulier du joueur sur un adversaire. Comptée indépendamment du carton éventuel. Feature à inverser : moins = mieux. | E19: Tchouaméni tacklé irrégulièrement un adversaire, arbitre siffle = 1 foul. Valeur typique DM ≈ 2-3/match | F19: DM|CB|CM | G19: TRUE | H19: feat_fouls_p90 | I19: z_fouls_p90 | J19: fouls | K19: =_xlfn.XLOOKUP(J19,defenseur_central!J:J,defenseur_central!K:K) -> 1 | L19: =IFERROR(_xlfn.XLOOKUP(A19,feature_catalog!A:A,feature_catalog!A:A),"") -> fouls
A20: penaltyConceded | B20: penalty_conc_p90 | C20: vol | D20: Pénalty concédé — faute commise par ce joueur dans sa propre surface de réparation, entraînant un pénalty pour l'adversaire. Feature à inverser : moins = mieux. | E20: Pavard fauche Mbappé dans la surface = 1 penalty conceded pour Pavard | F20: CD|FB | G20: TRUE | H20: feat_penalty_conc_p90 | I20: z_penalty_conc_p90 | J20: penaltyConceded | L20: =IFERROR(_xlfn.XLOOKUP(A20,feature_catalog!A:A,feature_catalog!A:A),"") -> penaltyConceded
A21: accuratePassesPercentage | B21: pass_acc_pct | C21: pct | D21: Passes réussies divisées par passes tentées. Une passe est réussie si un coéquipier la contrôle. Exclut les corners, remises en jeu, dégagements du gardien et centres (comptés séparément). | E21: Kroos : 85 passes réussies / 90 tentées = 94.4%. Moyenne DM Premier League ≈ 82% | F21: CM|DM|CB|FB|AM|GK | G21: FALSE | H21: feat_pass_acc_pct | I21: z_pass_acc_pct | J21: accuratePassesPercentage | K21: 1.5 | L21: =IFERROR(_xlfn.XLOOKUP(A21,feature_catalog!A:A,feature_catalog!A:A),"") -> accuratePassesPercentage
A22: accurateLongBallsPercentage | B22: long_balls_pct | C22: pct | D22: Passes longues réussies sur passes longues tentées. Une passe longue est définie par Opta comme un ballon joué en hauteur sur une distance significative (généralement >32m). Indicateur clé des CBs relanceurs et gardiens modernes. | E22: Rúben Dias joue 8 longues passes, 6 arrivent à un coéquipier = 75% long balls | F22: CB|DM|GK|CM | G22: FALSE | H22: feat_long_balls_pct | I22: z_long_balls_pct | J22: accurateLongBallsPercentage | L22: =IFERROR(_xlfn.XLOOKUP(A22,feature_catalog!A:A,feature_catalog!A:A),"") -> accurateLongBallsPercentage
A23: accurateLongBalls | B23: long_balls_p90 | C23: vol | D23: Passes longues réussies — ballon joué en hauteur sur une distance significative (généralement >32m) récupéré par un coéquipier. Comptées en absolu per-90. | E23: Rúben Dias joue 8 longues passes dont 6 arrivent à un coéquipier = 6 long balls réussies | F23: CB|DM|GK|CM | G23: FALSE | H23: feat_long_balls_p90 | I23: z_long_balls_p90 | J23: accurateLongBalls | L23: =IFERROR(_xlfn.XLOOKUP(A23,feature_catalog!A:A,feature_catalog!A:A),"") -> accurateLongBalls
A24: possessionLost | B24: poss_lost_p90 | C24: vol | D24: Nombre de fois où le joueur perd la possession — tacle adverse réussi sur lui, mauvais contrôle, passe ratée dans les pieds adverses, interception subie. Comptabilisé uniquement quand la possession change d'équipe suite à l'action du joueur. | E24: Griezmann reçoit, adverse le tacklé et récupère le ballon = 1 possession lost pour Griezmann | F24: CF|W|CM|DM|CB | G24: TRUE | H24: feat_poss_lost_p90 | I24: z_poss_lost_p90 | J24: possessionLost | K24: 1 | L24: =IFERROR(_xlfn.XLOOKUP(A24,feature_catalog!A:A,feature_catalog!A:A),"") -> possessionLost
A25: height | B25: height_cm | C25: raw | D25: Taille en cm déclarée sur le profil officiel Transfermarkt du joueur. Donnée statique, issue des fiches officielles clubs / fédérations. | E25: Virgil van Dijk : 193cm. Thibaut Courtois : 199cm. Seuil 'tour de contrôle' CB : ≥188cm | F25: CB|CF|GK | G25: FALSE | H25: feat_height_cm | I25: z_height_cm | J25: height | L25: =IFERROR(_xlfn.XLOOKUP(A25,feature_catalog!A:A,feature_catalog!A:A),"") -> height
A26: rating | B26: ss_rating | C26: raw | D26: Note SofaScore calculée algorithmiquement à partir de l'ensemble des actions de jeu pondérées par poste. Échelle 1-10, mise à jour après chaque match. Utilisée comme benchmark de validation des scores du modèle. | E26: De Bruyne : moyenne 7.3 sur la saison = excellent. Moyenne joueur ≈ 6.8. Gardien bonne saison ≈ 7.0-7.2 | F26: ALL | G26: FALSE | H26: feat_ss_rating | I26: z_ss_rating | J26: rating | L26: =IFERROR(_xlfn.XLOOKUP(A26,feature_catalog!A:A,feature_catalog!A:A),"") -> rating
A27: averageX | B27: avg_x | C27: raw | D27: Position X moyenne du joueur sur le terrain au moment de ses touches de balle, agrégée sur la saison via l'endpoint heatmap/overall SofaScore. X=0 = ligne de but propre, X=100 = ligne de but adverse. Calculé comme moyenne des coordonnées X de toutes les touches de la heatmap saison. | E27: Benzema saison faux-9 : avgX≈62 (milieu-haut). Haaland : avgX≈80 (très haut). Casemiro sentinelle : avgX≈35 (bas) | F27: ALL | G27: FALSE | H27: feat_avg_x | I27: z_avg_x | J27: averageX | L27: =IFERROR(_xlfn.XLOOKUP(A27,feature_catalog!A:A,feature_catalog!A:A),"") -> averageX
A28: averageY | B28: avg_y | C28: raw | D28: Position Y moyenne du joueur (axe latéral), agrégée sur la saison. Y=0 = ligne de touche gauche, Y=100 = ligne de touche droite, Y=50 = axe central. Utilisé pour distinguer ailier excentré (Y≈10 ou 90) d'un intérieur (Y≈30 ou 70). | E28: Trent Alexander-Arnold : avgY≈80 (côté droit collé). Modric : avgY≈50 (axe central). Salah ailier droit rentrant : avgY≈65 | F28: ALL | G28: FALSE | H28: feat_avg_y | I28: z_avg_y | J28: averageY | L28: =IFERROR(_xlfn.XLOOKUP(A28,feature_catalog!A:A,feature_catalog!A:A),"") -> averageY
L29: =IFERROR(_xlfn.XLOOKUP(A29,feature_catalog!A:A,feature_catalog!A:A),"") -> 0
L30: =IFERROR(_xlfn.XLOOKUP(A30,feature_catalog!A:A,feature_catalog!A:A),"") -> 0
L31: =IFERROR(_xlfn.XLOOKUP(A31,feature_catalog!A:A,feature_catalog!A:A),"") -> 0
L32: =IFERROR(_xlfn.XLOOKUP(A32,feature_catalog!A:A,feature_catalog!A:A),"")
L33: =IFERROR(_xlfn.XLOOKUP(A33,feature_catalog!A:A,feature_catalog!A:A),"") -> 0
L34: =IFERROR(_xlfn.XLOOKUP(A34,feature_catalog!A:A,feature_catalog!A:A),"")
L35: =IFERROR(_xlfn.XLOOKUP(A35,feature_catalog!A:A,feature_catalog!A:A),"")
L36: =IFERROR(_xlfn.XLOOKUP(A36,feature_catalog!A:A,feature_catalog!A:A),"") -> 0

Sheet aventureux
A1: source_column | B1: feature_name | C1: type | D1: description | E1: exemple | F1: relevant_roles | G1: inverted | H1: feat_col | I1: z_col | J1: source_column | K1: pondération | L1: pondération
A2: aerialDuelsWonPercentage | B2: aerial_duels_pct | C2: pct | D2: Duels aériens gagnés sur duels aériens disputés. Un duel aérien nécessite 2+ joueurs qui challengent pour le même ballon en l'air. Gagné = le joueur obtient le premier contact contrôlé. Si fauté pendant le duel aérien, le joueur fauté gagne le duel. | E2: Giroud vs un défenseur sur corner : tous deux sautent, Giroud capte le ballon de la tête = Giroud gagne le duel aérien. Si le défenseur le fauche en sautant = Giroud gagne le duel (fauté) | F2: CB|CF|DM|FB | G2: FALSE | H2: feat_aerial_duels_pct | I2: z_aerial_duels_pct | J2: aerialDuelsWonPercentage | K2: 1.5 | L2: important | M2: =IFERROR(_xlfn.XLOOKUP(B2,feature_catalog!B:B,feature_catalog!B:B),"") -> aerial_duels_pct
A3: groundDuelsWonPercentage | B3: ground_duels_pct | C3: pct | D3: % duels au sol gagnés sur duels au sol disputés. Un duel est défini comme un contest 50/50 entre deux joueurs adverses. Indicateur de solidité au sol dans les duels 1v1. | E3: Tchouaméni : 6 duels sol gagnés / 9 disputés = 67%. Moyenne milieu défensif PL ≈ 55-60% | F3: DM|CM|CB|CF | G3: FALSE | H3: feat_ground_duels_pct | I3: z_ground_duels_pct | J3: groundDuelsWonPercentage | K3: 2.5 | L3: important | M3: =IFERROR(_xlfn.XLOOKUP(B3,feature_catalog!B:B,feature_catalog!B:B),"") -> ground_duels_pct
A4: _duels_won_pct | B4: duels_won_pct | C4: pct | D4: % duels gagnés (tous types) — proxy calculé comme (groundDuelsWonPercentage + aerialDuelsWonPercentage) / 2. Indicateur global d'efficacité dans les duels 1v1. | E4: Tchouaméni : 67% duels sol + 58% duels aériens = 62.5% duels_won_pct | F4: CB|DM|CM|CF|FB | G4: FALSE | H4: feat_duels_won_pct | I4: z_duels_won_pct | J4: _duels_won_pct | L4: passable | M4: =IFERROR(_xlfn.XLOOKUP(B4,feature_catalog!B:B,feature_catalog!B:B),"") -> duels_won_pct
A5: _tackle_success_pct | B5: tackle_success_pct | C5: pct | D5: % tacles réussis = tacklesWon / tackles × 100. Mesure l'efficacité défensive au sol. Distingue le défenseur engagé précis (haut %) du défenseur brouillon qui tacle beaucoup mais perd souvent. | E5: Fabinho : 8 tacles, 6 remportés = 75% tackle success. Valeur top DM PL ≈ 65-75% | F5: DM|CB|CM|FB | G5: FALSE | H5: feat_tackle_success_pct | I5: z_tackle_success_pct | J5: _tackle_success_pct | L5: important | M5: =IFERROR(_xlfn.XLOOKUP(B5,feature_catalog!B:B,feature_catalog!B:B),"") -> tackle_success_pct
A6: tackles | B6: tackles_p90 | C6: vol | D6: Tacle réussi = le joueur entre en contact avec le ballon dans un duel au sol et récupère la possession ou dégage le ballon. Le joueur taclé doit clairement être en possession. Couper une passe n'est PAS un tacle (c'est une interception). | E6: Kanté glisse et rafle le ballon sous le pied de Pogba qui avait le contrôle = 1 tackle. Kanté intercepte une passe = interception, pas tackle | F6: DM|CB|CM|FB | G6: FALSE | H6: feat_tackles_p90 | I6: z_tackles_p90 | J6: tackles | L6: passable | M6: =IFERROR(_xlfn.XLOOKUP(B6,feature_catalog!B:B,feature_catalog!B:B),"") -> tackles_p90
A7: interceptions | B7: interceptions_p90 | C7: vol | D7: Le joueur lit la passe adverse et se déplace dans la trajectoire du ballon pour l'intercepter. Geste ANTICIPATIF — le joueur doit se déplacer vers la ligne de passe avant que le ballon arrive. Différent du tacle (réactif sur porteur) et de la récupération (ballon libre). | E7: Fabinho lit une passe horizontale, se décale et intercepte le ballon dans sa course = 1 interception. Fabinho récupère un rebond qui traîne = ball recovery, pas interception | F7: DM|CB|CM|FB | G7: FALSE | H7: feat_interceptions_p90 | I7: z_interceptions_p90 | J7: interceptions | K7: 2 | L7: passable | M7: =IFERROR(_xlfn.XLOOKUP(B7,feature_catalog!B:B,feature_catalog!B:B),"") -> interceptions_p90
A8: clearances | B8: clearances_p90 | C8: vol | D8: Dégagement = action d'un joueur qui éloigne le ballon d'une zone dangereuse SANS cible précise — il n'essaie pas de passer à un coéquipier, juste de dégager le danger. Si une cible est identifiée, c'est une passe. | E8: Stones dégage un centre tendu de la tête dans les tribunes = 1 clearance. Stones contrôle le même centre et passe à Ederson = passe, pas clearance | F8: CB|FB|DM | G8: FALSE | H8: feat_clearances_p90 | I8: z_clearances_p90 | J8: clearances | L8: passable | M8: =IFERROR(_xlfn.XLOOKUP(B8,feature_catalog!B:B,feature_catalog!B:B),"") -> clearances_p90
A9: dribbledPast | B9: dribbled_past_p90 | C9: vol | D9: Nombre de fois où un adversaire réussit un dribble sur ce joueur. Feature défensive à inverser : moins le joueur se fait dribbler, mieux c'est. Indicateur de solidité défensive individuelle au sol. | E9: Salah élimine le latéral adverse qui ne peut que le faucher = 1 dribbled past pour le défenseur | F9: CD|FB | G9: TRUE | H9: feat_dribbled_past_p90 | I9: z_dribbled_past_p90 | J9: dribbledPast | K9: 2 | L9: important | M9: =IFERROR(_xlfn.XLOOKUP(B9,feature_catalog!B:B,feature_catalog!B:B),"") -> dribbled_past_p90
A10: errorLeadToGoal | B10: errors_goal_p90 | C10: vol | D10: Erreur individuelle d'un joueur menant DIRECTEMENT à un but encaissé. L'erreur doit être la cause directe sans phase de jeu intermédiaire. Très rare — 0 à 2 occurrences par saison pour la plupart des joueurs. | E10: Maguire perd le ballon dans sa propre surface, l'adversaire marque immédiatement = 1 errorLeadToGoal. Feature à inverser | F10: CD|GK|FB | G10: TRUE | H10: feat_errors_goal_p90 | I10: z_errors_goal_p90 | J10: errorLeadToGoal | L10: critique | M10: =IFERROR(_xlfn.XLOOKUP(B10,feature_catalog!B:B,feature_catalog!B:B),"") -> errors_goal_p90
A11: errorLeadToShot | B11: errors_shot_p90 | C11: vol | D11: Erreur menant DIRECTEMENT à un tir adverse, but ou non. Sur-ensemble de errorLeadToGoal — chaque errorLeadToGoal est aussi un errorLeadToShot mais pas l'inverse. Légèrement plus fréquent (2-6/saison). | E11: Stones glisse et offre le ballon à Salah qui tire (gardien arrête) = 1 errorLeadToShot mais pas errorLeadToGoal | F11: CD|GK|FB | G11: TRUE | H11: feat_errors_shot_p90 | I11: z_errors_shot_p90 | J11: errorLeadToShot | K11: =_xlfn.XLOOKUP(J11,defenseur_central!J:J,defenseur_central!K:K) -> 2 | L11: critique | M11: =IFERROR(_xlfn.XLOOKUP(B11,feature_catalog!B:B,feature_catalog!B:B),"") -> errors_shot_p90
A12: fouls | B12: fouls_p90 | C12: vol | D12: Fautes commises — infractions sifflées suite à un contact irrégulier du joueur sur un adversaire. Comptée indépendamment du carton éventuel. Feature à inverser : moins = mieux. | E12: Tchouaméni tacklé irrégulièrement un adversaire, arbitre siffle = 1 foul. Valeur typique DM ≈ 2-3/match | F12: DM|CB|CM | G12: TRUE | H12: feat_fouls_p90 | I12: z_fouls_p90 | J12: fouls | L12: passable | M12: =IFERROR(_xlfn.XLOOKUP(B12,feature_catalog!B:B,feature_catalog!B:B),"") -> fouls_p90
A13: penaltyConceded | B13: penalty_conc_p90 | C13: vol | D13: Pénalty concédé — faute commise par ce joueur dans sa propre surface de réparation, entraînant un pénalty pour l'adversaire. Feature à inverser : moins = mieux. | E13: Pavard fauche Mbappé dans la surface = 1 penalty conceded pour Pavard | F13: CD|FB | G13: TRUE | H13: feat_penalty_conc_p90 | I13: z_penalty_conc_p90 | J13: penaltyConceded | L13: important | M13: =IFERROR(_xlfn.XLOOKUP(B13,feature_catalog!B:B,feature_catalog!B:B),"") -> penalty_conc_p90
A14: successfulDribbles | B14: dribbles_p90 | C14: vol | D14: Dribbles réussis — tentatives où le joueur bat l'adversaire en conservant la possession. Échoué si le dribbleur est taclé ou si le ballon s'éloigne trop (overrun). | E14: Neymar tente 8 dribbles, en réussit 6 = 6 successfulDribbles | F14: W|CF|AM|CM | G14: FALSE | H14: feat_dribbles_p90 | I14: z_dribbles_p90 | J14: successfulDribbles | L14: important | M14: =IFERROR(_xlfn.XLOOKUP(B14,feature_catalog!B:B,feature_catalog!B:B),"") -> dribbles_p90
A15: successfulDribblesPercentage | B15: dribble_pct | C15: pct | D15: Dribbles réussis sur dribbles tentés. Un dribble est réussi si le joueur bat l'adversaire en conservant la possession. Échoué si le dribbleur est taclé ou si le ballon s'éloigne trop (overrun). | E15: Neymar tente 8 dribbles, en réussit 6 = 75%. Valeur top ailier PL ≈ 55-65% | F15: W|CF|AM | G15: FALSE | H15: feat_dribble_pct | I15: z_dribble_pct | J15: successfulDribblesPercentage | L15: important | M15: =IFERROR(_xlfn.XLOOKUP(B15,feature_catalog!B:B,feature_catalog!B:B),"") -> dribble_pct
A16: possessionLost | B16: poss_lost_p90 | C16: vol | D16: Nombre de fois où le joueur perd la possession — tacle adverse réussi sur lui, mauvais contrôle, passe ratée dans les pieds adverses, interception subie. Comptabilisé uniquement quand la possession change d'équipe suite à l'action du joueur. | E16: Griezmann reçoit, adverse le tacklé et récupère le ballon = 1 possession lost pour Griezmann | F16: CF|W|CM|DM|CB | G16: TRUE | H16: feat_poss_lost_p90 | I16: z_poss_lost_p90 | J16: possessionLost | K16: 1 | L16: critique | M16: =IFERROR(_xlfn.XLOOKUP(B16,feature_catalog!B:B,feature_catalog!B:B),"") -> poss_lost_p90
A17: dispossessed | B17: dispossessed_p90 | C17: vol | D17: Sous-ensemble de possessionLost : uniquement les pertes de balle causées par un tacle adverse réussi sur le joueur en possession. Exclut les mauvaises passes et mauvais contrôles. | E17: Vinicius conduit, un défenseur le tacklé proprement et récupère le ballon = 1 dispossessed. Mauvaise passe de Vinicius = possessionLost mais pas dispossessed | F17: W|CF|AM|CM | G17: TRUE | H17: feat_dispossessed_p90 | I17: z_dispossessed_p90 | J17: dispossessed | K17: 1 | L17: important | M17: =IFERROR(_xlfn.XLOOKUP(B17,feature_catalog!B:B,feature_catalog!B:B),"") -> dispossessed_p90
A18: xGBuildup_us | B18: xgbuildup_p90 | C18: vol | D18: xGChain moins la contribution directe du tireur (xG) et du passeur décisif (xA). Mesure exclusivement les touches 'invisibles' en amont de la phase finale — la contribution à la construction profonde. | E18: Cancelo → De Bruyne → Haaland (but, xG=0.45). Cancelo : xGBuildup=0.45. De Bruyne : xGBuildup=0 (passeur déc. exclu). Haaland : xGBuildup=0 (tireur exclu) | F18: CM|DM|CB|FB|AM | G18: FALSE | H18: feat_xgbuildup_p90 | I18: z_xgbuildup_p90 | J18: xGBuildup_us | K18: 2 | L18: critique | M18: =IFERROR(_xlfn.XLOOKUP(B18,feature_catalog!B:B,feature_catalog!B:B),"") -> xgbuildup_p90
A19: accurateFinalThirdPasses | B19: passes_f3_p90 | C19: vol | D19: Passes dont le point d'arrivée se situe dans le dernier tiers du terrain (33m finaux). Mesure la capacité à faire progresser le jeu vers l'avant. Ne requiert pas que la passe soit une passe clé. | E19: Busquets joue une passe depuis son propre camp vers Pedri dans le dernier tiers = 1 passToFinalThird | F19: CM|DM|CB|AM | G19: FALSE | H19: feat_passes_f3_p90 | I19: z_passes_f3_p90 | J19: accurateFinalThirdPasses | L19: important | M19: =IFERROR(_xlfn.XLOOKUP(B19,feature_catalog!B:B,feature_catalog!B:B),"") -> passes_f3_p90
A20: keyPasses | B20: key_passes_p90 | C20: vol | D20: Passe menant directement à une tentative de but de l'équipe, sans être une passe décisive officielle (le tir ne se transforme pas en but). Critère : la passe doit être la dernière avant le tir. | E20: Ødegaard joue une passe à Saka qui tire, gardien arrête = 1 key pass pour Ødegaard. Si Saka marque = assist, pas key pass | F20: AM|CM|W|CF|FB | G20: FALSE | H20: feat_key_passes_p90 | I20: z_key_passes_p90 | J20: keyPasses | L20: passable | M20: =IFERROR(_xlfn.XLOOKUP(B20,feature_catalog!B:B,feature_catalog!B:B),"") -> key_passes_p90
A21: expectedAssists | B21: xa_p90 | C21: vol | D21: xG de l'occasion créée par la passe, calculé au moment où le receveur tire. Mesure la qualité des passes menant à un tir, quel que soit le résultat du tir. Une passe vers un xG=0.5 vaut xA=0.5 même si le tir est raté. | E21: Passe dans la surface pour tir à bout portant (xG=0.45) = xA=0.45 pour le passeur. Passe vers une frappe lointaine (xG=0.03) = xA=0.03 | F21: W|AM|CM|CF|FB | G21: FALSE | H21: feat_xa_p90 | I21: z_xa_p90 | J21: expectedAssists | L21: passable | M21: =IFERROR(_xlfn.XLOOKUP(B21,feature_catalog!B:B,feature_catalog!B:B),"") -> xa_p90
A22: throughBalls | B22: through_balls_p90 | C22: vol | D22: Passes en profondeur tentées — ballon joué dans l'espace derrière la ligne défensive adverse pour un coéquipier en mouvement. Comptées réussies ou non. | E22: De Bruyne joue un ballon millimétré dans le dos de la défense pour Haaland = 1 through ball (réussie si Haaland contrôle) | F22: AM|CM|DM | G22: FALSE | H22: feat_through_balls_p90 | I22: z_through_balls_p90 | J22: throughBalls | L22: passable | M22: =IFERROR(_xlfn.XLOOKUP(B22,feature_catalog!B:B,feature_catalog!B:B),"")
A23: accuratePassesPercentage | B23: pass_acc_pct | C23: pct | D23: Passes réussies divisées par passes tentées. Une passe est réussie si un coéquipier la contrôle. Exclut les corners, remises en jeu, dégagements du gardien et centres (comptés séparément). | E23: Kroos : 85 passes réussies / 90 tentées = 94.4%. Moyenne DM Premier League ≈ 82% | F23: CM|DM|CB|FB|AM|GK | G23: FALSE | H23: feat_pass_acc_pct | I23: z_pass_acc_pct | J23: accuratePassesPercentage | K23: 1.5 | L23: critique | M23: =IFERROR(_xlfn.XLOOKUP(B23,feature_catalog!B:B,feature_catalog!B:B),"") -> pass_acc_pct
A24: accurateLongBallsPercentage | B24: long_balls_pct | C24: pct | D24: Passes longues réussies sur passes longues tentées. Une passe longue est définie par Opta comme un ballon joué en hauteur sur une distance significative (généralement >32m). Indicateur clé des CBs relanceurs et gardiens modernes. | E24: Rúben Dias joue 8 longues passes, 6 arrivent à un coéquipier = 75% long balls | F24: CB|DM|GK|CM | G24: FALSE | H24: feat_long_balls_pct | I24: z_long_balls_pct | J24: accurateLongBallsPercentage | L24: important | M24: =IFERROR(_xlfn.XLOOKUP(B24,feature_catalog!B:B,feature_catalog!B:B),"") -> long_balls_pct
A25: accurateLongBalls | B25: long_balls_p90 | C25: vol | D25: Passes longues réussies — ballon joué en hauteur sur une distance significative (généralement >32m) récupéré par un coéquipier. Comptées en absolu per-90. | E25: Rúben Dias joue 8 longues passes dont 6 arrivent à un coéquipier = 6 long balls réussies | F25: CB|DM|GK|CM | G25: FALSE | H25: feat_long_balls_p90 | I25: z_long_balls_p90 | J25: accurateLongBalls | L25: passable | M25: =IFERROR(_xlfn.XLOOKUP(B25,feature_catalog!B:B,feature_catalog!B:B),"") -> long_balls_p90
A26: averageX | B26: avg_x | C26: raw | D26: Position X moyenne du joueur sur le terrain au moment de ses touches de balle, agrégée sur la saison via l'endpoint heatmap/overall SofaScore. X=0 = ligne de but propre, X=100 = ligne de but adverse. Calculé comme moyenne des coordonnées X de toutes les touches de la heatmap saison. | E26: Benzema saison faux-9 : avgX≈62 (milieu-haut). Haaland : avgX≈80 (très haut). Casemiro sentinelle : avgX≈35 (bas) | F26: ALL | G26: FALSE | H26: feat_avg_x | I26: z_avg_x | J26: averageX | L26: important | M26: =IFERROR(_xlfn.XLOOKUP(B26,feature_catalog!B:B,feature_catalog!B:B),"") -> avg_x
A27: rating | B27: ss_rating | C27: raw | D27: Note SofaScore calculée algorithmiquement à partir de l'ensemble des actions de jeu pondérées par poste. Échelle 1-10, mise à jour après chaque match. Utilisée comme benchmark de validation des scores du modèle. | E27: De Bruyne : moyenne 7.3 sur la saison = excellent. Moyenne joueur ≈ 6.8. Gardien bonne saison ≈ 7.0-7.2 | F27: ALL | G27: FALSE | H27: feat_ss_rating | I27: z_ss_rating | J27: rating | L27: passable | M27: =IFERROR(_xlfn.XLOOKUP(B27,feature_catalog!B:B,feature_catalog!B:B),"") -> ss_rating
A28: height | B28: height_cm | C28: raw | D28: Taille en cm déclarée sur le profil officiel Transfermarkt du joueur. Donnée statique, issue des fiches officielles clubs / fédérations. | E28: Virgil van Dijk : 193cm. Thibaut Courtois : 199cm. Seuil 'tour de contrôle' CB : ≥188cm | F28: CB|CF|GK | G28: FALSE | H28: feat_height_cm | I28: z_height_cm | J28: height | L28: passable
A29: averageY | B29: avg_y | C29: raw | D29: Position Y moyenne du joueur (axe latéral), agrégée sur la saison. Y=0 = ligne de touche gauche, Y=100 = ligne de touche droite, Y=50 = axe central. Utilisé pour distinguer ailier excentré (Y≈10 ou 90) d'un intérieur (Y≈30 ou 70). | E29: Trent Alexander-Arnold : avgY≈80 (côté droit collé). Modric : avgY≈50 (axe central). Salah ailier droit rentrant : avgY≈65 | F29: ALL | G29: FALSE | H29: feat_avg_y | I29: z_avg_y | J29: averageY | L29: passable

Sheet lateral_classique
A1: source_column | B1: feature_name | C1: type | D1: description | E1: exemple | F1: relevant_roles | G1: inverted | H1: feat_col | I1: z_col | J1: source_column | K1: pondération
A2: groundDuelsWonPercentage | B2: ground_duels_pct | C2: pct | D2: % duels au sol gagnés sur duels au sol disputés. Un duel est défini comme un contest 50/50 entre deux joueurs adverses. Indicateur de solidité au sol dans les duels 1v1. | E2: Tchouaméni : 6 duels sol gagnés / 9 disputés = 67%. Moyenne milieu défensif PL ≈ 55-60% | F2: DM|CM|CB|CF | G2: FALSE | H2: feat_ground_duels_pct | I2: z_ground_duels_pct | J2: groundDuelsWonPercentage | K2: 2 | L2: =IFERROR(_xlfn.XLOOKUP(A2,feature_catalog!A:A,feature_catalog!A:A),"") -> groundDuelsWonPercentage
A3: aerialDuelsWonPercentage | B3: aerial_duels_pct | C3: pct | D3: Duels aériens gagnés sur duels aériens disputés. Un duel aérien nécessite 2+ joueurs qui challengent pour le même ballon en l'air. Gagné = le joueur obtient le premier contact contrôlé. Si fauté pendant le duel aérien, le joueur fauté gagne le duel. | E3: Giroud vs un défenseur sur corner : tous deux sautent, Giroud capte le ballon de la tête = Giroud gagne le duel aérien. Si le défenseur le fauche en sautant = Giroud gagne le duel (fauté) | F3: CB|CF|DM|FB | G3: FALSE | H3: feat_aerial_duels_pct | I3: z_aerial_duels_pct | J3: aerialDuelsWonPercentage | K3: 1 | L3: =IFERROR(_xlfn.XLOOKUP(A3,feature_catalog!A:A,feature_catalog!A:A),"") -> aerialDuelsWonPercentage
A4: _tackle_success_pct | B4: tackle_success_pct | C4: pct | D4: % tacles réussis = tacklesWon / tackles × 100. Mesure l'efficacité défensive au sol. Distingue le défenseur engagé précis (haut %) du défenseur brouillon qui tacle beaucoup mais perd souvent. | E4: Fabinho : 8 tacles, 6 remportés = 75% tackle success. Valeur top DM PL ≈ 65-75% | F4: DM|CB|CM|FB | G4: FALSE | H4: feat_tackle_success_pct | I4: z_tackle_success_pct | J4: _tackle_success_pct | L4: =IFERROR(_xlfn.XLOOKUP(A4,feature_catalog!A:A,feature_catalog!A:A),"") -> _tackle_success_pct
A5: tackles | B5: tackles_p90 | C5: vol | D5: Tacle réussi = le joueur entre en contact avec le ballon dans un duel au sol et récupère la possession ou dégage le ballon. Le joueur taclé doit clairement être en possession. Couper une passe n'est PAS un tacle (c'est une interception). | E5: Kanté glisse et rafle le ballon sous le pied de Pogba qui avait le contrôle = 1 tackle. Kanté intercepte une passe = interception, pas tackle | F5: DM|CB|CM|FB | G5: FALSE | H5: feat_tackles_p90 | I5: z_tackles_p90 | J5: tackles | L5: =IFERROR(_xlfn.XLOOKUP(A5,feature_catalog!A:A,feature_catalog!A:A),"") -> tackles
A6: tacklesWon | B6: tackles_won_p90 | C6: vol | D6: Sous-ensemble des tacles : tacles remportés où le joueur récupère proprement la possession après le tacle (pas seulement dégagé). Indicateur de qualité défensive au sol. | E6: Kanté tacklé Pogba et repart avec le ballon = 1 tackle won. Kanté dévie le ballon en touche = tacle mais pas won | F6: DM|CB|CM|FB | G6: FALSE | H6: feat_tackles_won_p90 | I6: z_tackles_won_p90 | J6: tacklesWon | L6: =IFERROR(_xlfn.XLOOKUP(A6,feature_catalog!A:A,feature_catalog!A:A),"") -> tacklesWon
A7: interceptions | B7: interceptions_p90 | C7: vol | D7: Le joueur lit la passe adverse et se déplace dans la trajectoire du ballon pour l'intercepter. Geste ANTICIPATIF — le joueur doit se déplacer vers la ligne de passe avant que le ballon arrive. Différent du tacle (réactif sur porteur) et de la récupération (ballon libre). | E7: Fabinho lit une passe horizontale, se décale et intercepte le ballon dans sa course = 1 interception. Fabinho récupère un rebond qui traîne = ball recovery, pas interception | F7: DM|CB|CM|FB | G7: FALSE | H7: feat_interceptions_p90 | I7: z_interceptions_p90 | J7: interceptions | K7: 1.5 | L7: =IFERROR(_xlfn.XLOOKUP(A7,feature_catalog!A:A,feature_catalog!A:A),"") -> interceptions
A8: dribbledPast | B8: dribbled_past_p90 | C8: vol | D8: Nombre de fois où un adversaire réussit un dribble sur ce joueur. Feature défensive à inverser : moins le joueur se fait dribbler, mieux c'est. Indicateur de solidité défensive individuelle au sol. | E8: Salah élimine le latéral adverse qui ne peut que le faucher = 1 dribbled past pour le défenseur | F8: CD|FB | G8: TRUE | H8: feat_dribbled_past_p90 | I8: z_dribbled_past_p90 | J8: dribbledPast | K8: 2 | L8: =IFERROR(_xlfn.XLOOKUP(A8,feature_catalog!A:A,feature_catalog!A:A),"") -> dribbledPast
A9: clearances | B9: clearances_p90 | C9: vol | D9: Dégagement = action d'un joueur qui éloigne le ballon d'une zone dangereuse SANS cible précise — il n'essaie pas de passer à un coéquipier, juste de dégager le danger. Si une cible est identifiée, c'est une passe. | E9: Stones dégage un centre tendu de la tête dans les tribunes = 1 clearance. Stones contrôle le même centre et passe à Ederson = passe, pas clearance | F9: CB|FB|DM | G9: FALSE | H9: feat_clearances_p90 | I9: z_clearances_p90 | J9: clearances | L9: =IFERROR(_xlfn.XLOOKUP(A9,feature_catalog!A:A,feature_catalog!A:A),"") -> clearances
A10: headedClearances | B10: headed_clear_p90 | C10: vol | D10: Sous-ensemble des clearances : dégagements effectués de la tête uniquement. Indicateur de domination aérienne défensive dans la surface propre. | E10: Dias dégage un corner adverse de la tête = 1 headed clearance | F10: CB|GK | G10: FALSE | H10: feat_headed_clear_p90 | I10: z_headed_clear_p90 | J10: headedClearances | L10: =IFERROR(_xlfn.XLOOKUP(A10,feature_catalog!A:A,feature_catalog!A:A),"")
A11: ballRecovery | B11: ball_recovery_p90 | C11: vol | D11: Récupération de balle — action où le joueur obtient la possession sur un ballon libre ou dévié, sans que ce soit un tacle direct sur porteur ni une interception anticipée. Inclut les segundas pelotas. | E11: Kanté se retrouve sur un rebond d'un tir adverse et récupère le ballon = 1 ball recovery | F11: DM|CM|CD|FB | G11: FALSE | H11: feat_ball_recovery_p90 | I11: z_ball_recovery_p90 | J11: ballRecovery | K11: 1 | L11: =IFERROR(_xlfn.XLOOKUP(A11,feature_catalog!A:A,feature_catalog!A:A),"") -> ballRecovery
A12: blockedShots | B12: blocked_shots_p90 | C12: vol | D12: Joueur de champ qui bloque une tentative de but adverse. Condition stricte Opta : le tir doit être dirigé vers le but (aurait été cadré ou but sans le bloc). Si le tir allait de toute façon à côté, aucun bloc n'est comptabilisé. | E12: Van Dijk se jette devant la frappe de Salah adverse qui allait en haut du poteau = 1 blocked shot. Van Dijk dévie un tir qui allait largement à côté = 0 blocked shot | F12: CB|DM|CM | G12: FALSE | H12: feat_blocked_shots_p90 | I12: z_blocked_shots_p90 | J12: blockedShots | L12: =IFERROR(_xlfn.XLOOKUP(A12,feature_catalog!A:A,feature_catalog!A:A),"") -> blockedShots
A13: errorLeadToGoal | B13: errors_goal_p90 | C13: vol | D13: Erreur individuelle d'un joueur menant DIRECTEMENT à un but encaissé. L'erreur doit être la cause directe sans phase de jeu intermédiaire. Très rare — 0 à 2 occurrences par saison pour la plupart des joueurs. | E13: Maguire perd le ballon dans sa propre surface, l'adversaire marque immédiatement = 1 errorLeadToGoal. Feature à inverser | F13: CD|GK|FB | G13: TRUE | H13: feat_errors_goal_p90 | I13: z_errors_goal_p90 | J13: errorLeadToGoal | L13: =IFERROR(_xlfn.XLOOKUP(A13,feature_catalog!A:A,feature_catalog!A:A),"") -> errorLeadToGoal
A14: errorLeadToShot | B14: errors_shot_p90 | C14: vol | D14: Erreur menant DIRECTEMENT à un tir adverse, but ou non. Sur-ensemble de errorLeadToGoal — chaque errorLeadToGoal est aussi un errorLeadToShot mais pas l'inverse. Légèrement plus fréquent (2-6/saison). | E14: Stones glisse et offre le ballon à Salah qui tire (gardien arrête) = 1 errorLeadToShot mais pas errorLeadToGoal | F14: CD|GK|FB | G14: TRUE | H14: feat_errors_shot_p90 | I14: z_errors_shot_p90 | J14: errorLeadToShot | K14: 1 | L14: =IFERROR(_xlfn.XLOOKUP(A14,feature_catalog!A:A,feature_catalog!A:A),"") -> errorLeadToShot
A15: fouls | B15: fouls_p90 | C15: vol | D15: Fautes commises — infractions sifflées suite à un contact irrégulier du joueur sur un adversaire. Comptée indépendamment du carton éventuel. Feature à inverser : moins = mieux. | E15: Tchouaméni tacklé irrégulièrement un adversaire, arbitre siffle = 1 foul. Valeur typique DM ≈ 2-3/match | F15: DM|CB|CM | G15: TRUE | H15: feat_fouls_p90 | I15: z_fouls_p90 | J15: fouls | K15: 1 | L15: =IFERROR(_xlfn.XLOOKUP(A15,feature_catalog!A:A,feature_catalog!A:A),"") -> fouls
A16: penaltyConceded | B16: penalty_conc_p90 | C16: vol | D16: Pénalty concédé — faute commise par ce joueur dans sa propre surface de réparation, entraînant un pénalty pour l'adversaire. Feature à inverser : moins = mieux. | E16: Pavard fauche Mbappé dans la surface = 1 penalty conceded pour Pavard | F16: CD|FB | G16: TRUE | H16: feat_penalty_conc_p90 | I16: z_penalty_conc_p90 | J16: penaltyConceded | L16: =IFERROR(_xlfn.XLOOKUP(A16,feature_catalog!A:A,feature_catalog!A:A),"") -> penaltyConceded
A17: accuratePassesPercentage | B17: pass_acc_pct | C17: pct | D17: Passes réussies divisées par passes tentées. Une passe est réussie si un coéquipier la contrôle. Exclut les corners, remises en jeu, dégagements du gardien et centres (comptés séparément). | E17: Kroos : 85 passes réussies / 90 tentées = 94.4%. Moyenne DM Premier League ≈ 82% | F17: CM|DM|CB|FB|AM|GK | G17: FALSE | H17: feat_pass_acc_pct | I17: z_pass_acc_pct | J17: accuratePassesPercentage | K17: 2 | L17: =IFERROR(_xlfn.XLOOKUP(A17,feature_catalog!A:A,feature_catalog!A:A),"") -> accuratePassesPercentage
A18: possessionLost | B18: poss_lost_p90 | C18: vol | D18: Nombre de fois où le joueur perd la possession — tacle adverse réussi sur lui, mauvais contrôle, passe ratée dans les pieds adverses, interception subie. Comptabilisé uniquement quand la possession change d'équipe suite à l'action du joueur. | E18: Griezmann reçoit, adverse le tacklé et récupère le ballon = 1 possession lost pour Griezmann | F18: CF|W|CM|DM|CB | G18: TRUE | H18: feat_poss_lost_p90 | I18: z_poss_lost_p90 | J18: possessionLost | K18: 1 | L18: =IFERROR(_xlfn.XLOOKUP(A18,feature_catalog!A:A,feature_catalog!A:A),"") -> possessionLost
A19: dispossessed | B19: dispossessed_p90 | C19: vol | D19: Sous-ensemble de possessionLost : uniquement les pertes de balle causées par un tacle adverse réussi sur le joueur en possession. Exclut les mauvaises passes et mauvais contrôles. | E19: Vinicius conduit, un défenseur le tacklé proprement et récupère le ballon = 1 dispossessed. Mauvaise passe de Vinicius = possessionLost mais pas dispossessed | F19: W|CF|AM|CM | G19: TRUE | H19: feat_dispossessed_p90 | I19: z_dispossessed_p90 | J19: dispossessed | L19: =IFERROR(_xlfn.XLOOKUP(A19,feature_catalog!A:A,feature_catalog!A:A),"") -> dispossessed
A20: accurateCrosses | B20: crosses_p90 | C20: vol | D20: Centres réussis — ballons intentionnels joués depuis une position latérale vers la zone devant le but, récupérés par un coéquipier. Comptés en absolu per-90. | E20: Trent croise 10 fois, 3 trouvent un coéquipier = 3 crosses réussies | F20: FB|W|CM | G20: FALSE | H20: feat_crosses_p90 | I20: z_crosses_p90 | J20: accurateCrosses | L20: =IFERROR(_xlfn.XLOOKUP(A20,feature_catalog!A:A,feature_catalog!A:A),"") -> accurateCrosses
A21: accurateCrossesPercentage | B21: crosses_pct | C21: pct | D21: Centres réussis sur centres tentés. Un centre est défini comme tout ballon intentionnel joué depuis une position latérale vers la zone devant le but. Réussi = contrôlé par un coéquipier. | E21: Trent croise 10 fois, 3 trouvent un coéquipier = 30%. Valeur moyenne latéral PL ≈ 20-25% | F21: FB|W|CM | G21: FALSE | H21: feat_crosses_pct | I21: z_crosses_pct | J21: accurateCrossesPercentage | K21: 1 | L21: =IFERROR(_xlfn.XLOOKUP(A21,feature_catalog!A:A,feature_catalog!A:A),"") -> accurateCrossesPercentage
A22: totalCrosses | B22: total_crosses_p90 | C22: vol | D22: Centres totaux tentés, réussis ou non. Mesure le volume de débordements et de jeu dans la largeur, indépendamment de la précision. | E22: Sané effectue 8 centres dans le match dont 2 réussis = 8 totalCrosses | F22: FB|W | G22: FALSE | H22: feat_total_crosses_p90 | I22: z_total_crosses_p90 | J22: totalCrosses | L22: =IFERROR(_xlfn.XLOOKUP(A22,feature_catalog!A:A,feature_catalog!A:A),"") -> totalCrosses
A23: xGBuildup_us | B23: xgbuildup_p90 | C23: vol | D23: xGChain moins la contribution directe du tireur (xG) et du passeur décisif (xA). Mesure exclusivement les touches 'invisibles' en amont de la phase finale — la contribution à la construction profonde. | E23: Cancelo → De Bruyne → Haaland (but, xG=0.45). Cancelo : xGBuildup=0.45. De Bruyne : xGBuildup=0 (passeur déc. exclu). Haaland : xGBuildup=0 (tireur exclu) | F23: CM|DM|CB|FB|AM | G23: FALSE | H23: feat_xgbuildup_p90 | I23: z_xgbuildup_p90 | J23: xGBuildup_us | L23: =IFERROR(_xlfn.XLOOKUP(A23,feature_catalog!A:A,feature_catalog!A:A),"") -> xGBuildup_us
A24: accurateFinalThirdPasses | B24: passes_f3_p90 | C24: vol | D24: Passes dont le point d'arrivée se situe dans le dernier tiers du terrain (33m finaux). Mesure la capacité à faire progresser le jeu vers l'avant. Ne requiert pas que la passe soit une passe clé. | E24: Busquets joue une passe depuis son propre camp vers Pedri dans le dernier tiers = 1 passToFinalThird | F24: CM|DM|CB|AM | G24: FALSE | H24: feat_passes_f3_p90 | I24: z_passes_f3_p90 | J24: accurateFinalThirdPasses | L24: =IFERROR(_xlfn.XLOOKUP(A24,feature_catalog!A:A,feature_catalog!A:A),"") -> accurateFinalThirdPasses
A25: expectedAssists | B25: xa_p90 | C25: vol | D25: xG de l'occasion créée par la passe, calculé au moment où le receveur tire. Mesure la qualité des passes menant à un tir, quel que soit le résultat du tir. Une passe vers un xG=0.5 vaut xA=0.5 même si le tir est raté. | E25: Passe dans la surface pour tir à bout portant (xG=0.45) = xA=0.45 pour le passeur. Passe vers une frappe lointaine (xG=0.03) = xA=0.03 | F25: W|AM|CM|CF|FB | G25: FALSE | H25: feat_xa_p90 | I25: z_xa_p90 | J25: expectedAssists | L25: =IFERROR(_xlfn.XLOOKUP(A25,feature_catalog!A:A,feature_catalog!A:A),"") -> expectedAssists
A26: keyPasses | B26: key_passes_p90 | C26: vol | D26: Passe menant directement à une tentative de but de l'équipe, sans être une passe décisive officielle (le tir ne se transforme pas en but). Critère : la passe doit être la dernière avant le tir. | E26: Ødegaard joue une passe à Saka qui tire, gardien arrête = 1 key pass pour Ødegaard. Si Saka marque = assist, pas key pass | F26: AM|CM|W|CF|FB | G26: FALSE | H26: feat_key_passes_p90 | I26: z_key_passes_p90 | J26: keyPasses | L26: =IFERROR(_xlfn.XLOOKUP(A26,feature_catalog!A:A,feature_catalog!A:A),"") -> keyPasses
A27: assists | B27: ast_p90 | C27: vol | D27: Dernière action (passe, déviation, ou toute autre touche) menant directement au but du receveur. Si la passe décisive est déviée par un adversaire, une 'fantasy assist' est comptée pour le rating mais pas dans les stats officielles. | E27: De Bruyne centre, Haaland marque de la tête = assist De Bruyne. Si un défenseur dévie le centre et Haaland marque = pas d'assist officiel | F27: W|AM|CM|CF|FB | G27: FALSE | H27: feat_ast_p90 | I27: z_ast_p90 | J27: assists | L27: =IFERROR(_xlfn.XLOOKUP(A27,feature_catalog!A:A,feature_catalog!A:A),"") -> assists
A28: averageX | B28: avg_x | C28: raw | D28: Position X moyenne du joueur sur le terrain au moment de ses touches de balle, agrégée sur la saison via l'endpoint heatmap/overall SofaScore. X=0 = ligne de but propre, X=100 = ligne de but adverse. Calculé comme moyenne des coordonnées X de toutes les touches de la heatmap saison. | E28: Benzema saison faux-9 : avgX≈62 (milieu-haut). Haaland : avgX≈80 (très haut). Casemiro sentinelle : avgX≈35 (bas) | F28: ALL | G28: FALSE | H28: feat_avg_x | I28: z_avg_x | J28: averageX | L28: =IFERROR(_xlfn.XLOOKUP(A28,feature_catalog!A:A,feature_catalog!A:A),"") -> averageX
A29: averageY | B29: avg_y | C29: raw | D29: Position Y moyenne du joueur (axe latéral), agrégée sur la saison. Y=0 = ligne de touche gauche, Y=100 = ligne de touche droite, Y=50 = axe central. Utilisé pour distinguer ailier excentré (Y≈10 ou 90) d'un intérieur (Y≈30 ou 70). | E29: Trent Alexander-Arnold : avgY≈80 (côté droit collé). Modric : avgY≈50 (axe central). Salah ailier droit rentrant : avgY≈65 | F29: ALL | G29: FALSE | H29: feat_avg_y | I29: z_avg_y | J29: averageY | L29: =IFERROR(_xlfn.XLOOKUP(A29,feature_catalog!A:A,feature_catalog!A:A),"") -> averageY
A30: rating | B30: ss_rating | C30: raw | D30: Note SofaScore calculée algorithmiquement à partir de l'ensemble des actions de jeu pondérées par poste. Échelle 1-10, mise à jour après chaque match. Utilisée comme benchmark de validation des scores du modèle. | E30: De Bruyne : moyenne 7.3 sur la saison = excellent. Moyenne joueur ≈ 6.8. Gardien bonne saison ≈ 7.0-7.2 | F30: ALL | G30: FALSE | H30: feat_ss_rating | I30: z_ss_rating | J30: rating

Sheet piston
A1: source_column | B1: feature_name | C1: type | D1: description | E1: exemple | F1: relevant_roles | G1: inverted | H1: feat_col | I1: z_col | J1: source_column | K1: pondération (RECHERCHEV lc) | L1: pondération
A2: groundDuelsWonPercentage | B2: ground_duels_pct | C2: pct | D2: % duels au sol gagnés sur duels au sol disputés. Un duel est défini comme un contest 50/50 entre deux joueurs adverses. Indicateur de solidité au sol dans les duels 1v1. | E2: Tchouaméni : 6 duels sol gagnés / 9 disputés = 67%. Moyenne milieu défensif PL ≈ 55-60% | F2: DM|CM|CB|CF | G2: FALSE | H2: feat_ground_duels_pct | I2: z_ground_duels_pct | J2: groundDuelsWonPercentage | K2: 1.5 | L2: critique | M2: =IFERROR(_xlfn.XLOOKUP(B2,feature_catalog!B:B,feature_catalog!B:B),"") -> ground_duels_pct
A3: aerialDuelsWonPercentage | B3: aerial_duels_pct | C3: pct | D3: Duels aériens gagnés sur duels aériens disputés. Un duel aérien nécessite 2+ joueurs qui challengent pour le même ballon en l'air. Gagné = le joueur obtient le premier contact contrôlé. Si fauté pendant le duel aérien, le joueur fauté gagne le duel. | E3: Giroud vs un défenseur sur corner : tous deux sautent, Giroud capte le ballon de la tête = Giroud gagne le duel aérien. Si le défenseur le fauche en sautant = Giroud gagne le duel (fauté) | F3: CB|CF|DM|FB | G3: FALSE | H3: feat_aerial_duels_pct | I3: z_aerial_duels_pct | J3: aerialDuelsWonPercentage | K3: =IFERROR(VLOOKUP(J3,lateral_classique!$A:$K,11,0),"") -> 1 | L3: passable | M3: =IFERROR(_xlfn.XLOOKUP(B3,feature_catalog!B:B,feature_catalog!B:B),"") -> aerial_duels_pct
A4: _tackle_success_pct | B4: tackle_success_pct | C4: pct | D4: % tacles réussis = tacklesWon / tackles × 100. Mesure l'efficacité défensive au sol. Distingue le défenseur engagé précis (haut %) du défenseur brouillon qui tacle beaucoup mais perd souvent. | E4: Fabinho : 8 tacles, 6 remportés = 75% tackle success. Valeur top DM PL ≈ 65-75% | F4: DM|CB|CM|FB | G4: FALSE | H4: feat_tackle_success_pct | I4: z_tackle_success_pct | J4: _tackle_success_pct | L4: critique | M4: =IFERROR(_xlfn.XLOOKUP(B4,feature_catalog!B:B,feature_catalog!B:B),"") -> tackle_success_pct
A5: tackles | B5: tackles_p90 | C5: vol | D5: Tacle réussi = le joueur entre en contact avec le ballon dans un duel au sol et récupère la possession ou dégage le ballon. Le joueur taclé doit clairement être en possession. Couper une passe n'est PAS un tacle (c'est une interception). | E5: Kanté glisse et rafle le ballon sous le pied de Pogba qui avait le contrôle = 1 tackle. Kanté intercepte une passe = interception, pas tackle | F5: DM|CB|CM|FB | G5: FALSE | H5: feat_tackles_p90 | I5: z_tackles_p90 | J5: tackles | L5: important | M5: =IFERROR(_xlfn.XLOOKUP(B5,feature_catalog!B:B,feature_catalog!B:B),"") -> tackles_p90
A6: interceptions | B6: interceptions_p90 | C6: vol | D6: Le joueur lit la passe adverse et se déplace dans la trajectoire du ballon pour l'intercepter. Geste ANTICIPATIF — le joueur doit se déplacer vers la ligne de passe avant que le ballon arrive. Différent du tacle (réactif sur porteur) et de la récupération (ballon libre). | E6: Fabinho lit une passe horizontale, se décale et intercepte le ballon dans sa course = 1 interception. Fabinho récupère un rebond qui traîne = ball recovery, pas interception | F6: DM|CB|CM|FB | G6: FALSE | H6: feat_interceptions_p90 | I6: z_interceptions_p90 | J6: interceptions | K6: =IFERROR(VLOOKUP(J6,lateral_classique!$A:$K,11,0),"") -> 1.5 | L6: important | M6: =IFERROR(_xlfn.XLOOKUP(B6,feature_catalog!B:B,feature_catalog!B:B),"") -> interceptions_p90
A7: dribbledPast | B7: dribbled_past_p90 | C7: vol | D7: Nombre de fois où un adversaire réussit un dribble sur ce joueur. Feature défensive à inverser : moins le joueur se fait dribbler, mieux c'est. Indicateur de solidité défensive individuelle au sol. | E7: Salah élimine le latéral adverse qui ne peut que le faucher = 1 dribbled past pour le défenseur | F7: CD|FB | G7: TRUE | H7: feat_dribbled_past_p90 | I7: z_dribbled_past_p90 | J7: dribbledPast | K7: 1 | L7: critique | M7: =IFERROR(_xlfn.XLOOKUP(B7,feature_catalog!B:B,feature_catalog!B:B),"") -> dribbled_past_p90
A8: clearances | B8: clearances_p90 | C8: vol | D8: Dégagement = action d'un joueur qui éloigne le ballon d'une zone dangereuse SANS cible précise — il n'essaie pas de passer à un coéquipier, juste de dégager le danger. Si une cible est identifiée, c'est une passe. | E8: Stones dégage un centre tendu de la tête dans les tribunes = 1 clearance. Stones contrôle le même centre et passe à Ederson = passe, pas clearance | F8: CB|FB|DM | G8: FALSE | H8: feat_clearances_p90 | I8: z_clearances_p90 | J8: clearances | L8: passable | M8: =IFERROR(_xlfn.XLOOKUP(B8,feature_catalog!B:B,feature_catalog!B:B),"") -> clearances_p90
A9: errorLeadToGoal | B9: errors_goal_p90 | C9: vol | D9: Erreur individuelle d'un joueur menant DIRECTEMENT à un but encaissé. L'erreur doit être la cause directe sans phase de jeu intermédiaire. Très rare — 0 à 2 occurrences par saison pour la plupart des joueurs. | E9: Maguire perd le ballon dans sa propre surface, l'adversaire marque immédiatement = 1 errorLeadToGoal. Feature à inverser | F9: CD|GK|FB | G9: TRUE | H9: feat_errors_goal_p90 | I9: z_errors_goal_p90 | J9: errorLeadToGoal | L9: critique | M9: =IFERROR(_xlfn.XLOOKUP(B9,feature_catalog!B:B,feature_catalog!B:B),"") -> errors_goal_p90
A10: errorLeadToShot | B10: errors_shot_p90 | C10: vol | D10: Erreur menant DIRECTEMENT à un tir adverse, but ou non. Sur-ensemble de errorLeadToGoal — chaque errorLeadToGoal est aussi un errorLeadToShot mais pas l'inverse. Légèrement plus fréquent (2-6/saison). | E10: Stones glisse et offre le ballon à Salah qui tire (gardien arrête) = 1 errorLeadToShot mais pas errorLeadToGoal | F10: CD|GK|FB | G10: TRUE | H10: feat_errors_shot_p90 | I10: z_errors_shot_p90 | J10: errorLeadToShot | K10: =IFERROR(VLOOKUP(J10,lateral_classique!$A:$K,11,0),"") -> 1 | L10: critique | M10: =IFERROR(_xlfn.XLOOKUP(B10,feature_catalog!B:B,feature_catalog!B:B),"") -> errors_shot_p90
A11: fouls | B11: fouls_p90 | C11: vol | D11: Fautes commises — infractions sifflées suite à un contact irrégulier du joueur sur un adversaire. Comptée indépendamment du carton éventuel. Feature à inverser : moins = mieux. | E11: Tchouaméni tacklé irrégulièrement un adversaire, arbitre siffle = 1 foul. Valeur typique DM ≈ 2-3/match | F11: DM|CB|CM | G11: TRUE | H11: feat_fouls_p90 | I11: z_fouls_p90 | J11: fouls | L11: passable | M11: =IFERROR(_xlfn.XLOOKUP(B11,feature_catalog!B:B,feature_catalog!B:B),"") -> fouls_p90
A12: penaltyConceded | B12: penalty_conc_p90 | C12: vol | D12: Pénalty concédé — faute commise par ce joueur dans sa propre surface de réparation, entraînant un pénalty pour l'adversaire. Feature à inverser : moins = mieux. | E12: Pavard fauche Mbappé dans la surface = 1 penalty conceded pour Pavard | F12: CD|FB | G12: TRUE | H12: feat_penalty_conc_p90 | I12: z_penalty_conc_p90 | J12: penaltyConceded | L12: important | M12: =IFERROR(_xlfn.XLOOKUP(B12,feature_catalog!B:B,feature_catalog!B:B),"") -> penalty_conc_p90
A13: accuratePassesPercentage | B13: pass_acc_pct | C13: pct | D13: Passes réussies divisées par passes tentées. Une passe est réussie si un coéquipier la contrôle. Exclut les corners, remises en jeu, dégagements du gardien et centres (comptés séparément). | E13: Kroos : 85 passes réussies / 90 tentées = 94.4%. Moyenne DM Premier League ≈ 82% | F13: CM|DM|CB|FB|AM|GK | G13: FALSE | H13: feat_pass_acc_pct | I13: z_pass_acc_pct | J13: accuratePassesPercentage | K13: =IFERROR(VLOOKUP(J13,lateral_classique!$A:$K,11,0),"") -> 2 | L13: important | M13: =IFERROR(_xlfn.XLOOKUP(B13,feature_catalog!B:B,feature_catalog!B:B),"") -> pass_acc_pct
A14: possessionLost | B14: poss_lost_p90 | C14: vol | D14: Nombre de fois où le joueur perd la possession — tacle adverse réussi sur lui, mauvais contrôle, passe ratée dans les pieds adverses, interception subie. Comptabilisé uniquement quand la possession change d'équipe suite à l'action du joueur. | E14: Griezmann reçoit, adverse le tacklé et récupère le ballon = 1 possession lost pour Griezmann | F14: CF|W|CM|DM|CB | G14: TRUE | H14: feat_poss_lost_p90 | I14: z_poss_lost_p90 | J14: possessionLost | K14: 1 | L14: critique | M14: =IFERROR(_xlfn.XLOOKUP(B14,feature_catalog!B:B,feature_catalog!B:B),"") -> poss_lost_p90
A15: dispossessed | B15: dispossessed_p90 | C15: vol | D15: Sous-ensemble de possessionLost : uniquement les pertes de balle causées par un tacle adverse réussi sur le joueur en possession. Exclut les mauvaises passes et mauvais contrôles. | E15: Vinicius conduit, un défenseur le tacklé proprement et récupère le ballon = 1 dispossessed. Mauvaise passe de Vinicius = possessionLost mais pas dispossessed | F15: W|CF|AM|CM | G15: TRUE | H15: feat_dispossessed_p90 | I15: z_dispossessed_p90 | J15: dispossessed | L15: important | M15: =IFERROR(_xlfn.XLOOKUP(B15,feature_catalog!B:B,feature_catalog!B:B),"") -> dispossessed_p90
A16: accurateCrosses | B16: crosses_p90 | C16: vol | D16: Centres réussis — ballons intentionnels joués depuis une position latérale vers la zone devant le but, récupérés par un coéquipier. Comptés en absolu per-90. | E16: Trent croise 10 fois, 3 trouvent un coéquipier = 3 crosses réussies | F16: FB|W|CM | G16: FALSE | H16: feat_crosses_p90 | I16: z_crosses_p90 | J16: accurateCrosses | K16: 1 | L16: critique | M16: =IFERROR(_xlfn.XLOOKUP(B16,feature_catalog!B:B,feature_catalog!B:B),"") -> crosses_p90
A17: accurateCrossesPercentage | B17: crosses_pct | C17: pct | D17: Centres réussis sur centres tentés. Un centre est défini comme tout ballon intentionnel joué depuis une position latérale vers la zone devant le but. Réussi = contrôlé par un coéquipier. | E17: Trent croise 10 fois, 3 trouvent un coéquipier = 30%. Valeur moyenne latéral PL ≈ 20-25% | F17: FB|W|CM | G17: FALSE | H17: feat_crosses_pct | I17: z_crosses_pct | J17: accurateCrossesPercentage | K17: =IFERROR(VLOOKUP(J17,lateral_classique!$A:$K,11,0),"") -> 1 | L17: important | M17: =IFERROR(_xlfn.XLOOKUP(B17,feature_catalog!B:B,feature_catalog!B:B),"") -> crosses_pct
A18: totalCrosses | B18: total_crosses_p90 | C18: vol | D18: Centres totaux tentés, réussis ou non. Mesure le volume de débordements et de jeu dans la largeur, indépendamment de la précision. | E18: Sané effectue 8 centres dans le match dont 2 réussis = 8 totalCrosses | F18: FB|W | G18: FALSE | H18: feat_total_crosses_p90 | I18: z_total_crosses_p90 | J18: totalCrosses | L18: important | M18: =IFERROR(_xlfn.XLOOKUP(B18,feature_catalog!B:B,feature_catalog!B:B),"") -> total_crosses_p90
A19: xGChain_us | B19: xgchain_p90 | C19: vol | D19: Somme des xG de toutes les occasions auxquelles le joueur a participé dans la séquence de jeu, qu'il ait tiré, passé, ou simplement touché le ballon à n'importe quel moment de l'action. Très inclusif. | E19: Modric touche le ballon 3 passes avant le tir de Benzema (xG=0.25) → Modric reçoit 0.25 dans son xGChain | F19: CF|W|AM|CM|DM|FB | G19: False | H19: feat_xgchain_p90 | I19: z_xgchain_p90 | J19: xGChain_us | K19: 2 | L19: critique | M19: =IFERROR(_xlfn.XLOOKUP(B19,feature_catalog!B:B,feature_catalog!B:B),"") -> xgchain_p90
A20: expectedAssists | B20: xa_p90 | C20: vol | D20: xG de l'occasion créée par la passe, calculé au moment où le receveur tire. Mesure la qualité des passes menant à un tir, quel que soit le résultat du tir. Une passe vers un xG=0.5 vaut xA=0.5 même si le tir est raté. | E20: Passe dans la surface pour tir à bout portant (xG=0.45) = xA=0.45 pour le passeur. Passe vers une frappe lointaine (xG=0.03) = xA=0.03 | F20: W|AM|CM|CF|FB | G20: FALSE | H20: feat_xa_p90 | I20: z_xa_p90 | J20: expectedAssists | L20: critique | M20: =IFERROR(_xlfn.XLOOKUP(B20,feature_catalog!B:B,feature_catalog!B:B),"") -> xa_p90
A21: xA_us | B21: xa_us_p90 | C21: vol | D21: xA calculé par Understat — probabilité de but générée par les passes du joueur, sur la base des tirs qui ont suivi. Méthodologie légèrement différente de l'xA Opta : Understat exclut les assistances sur pénaltys. | E21: De Bruyne joue 3 passes menant à des tirs (xG=0.35, 0.12, 0.08) → xA_us = 0.55 pour ce match | F21: W|AM|CM|CF|FB | G21: FALSE | H21: feat_xa_us_p90 | I21: z_xa_us_p90 | J21: xA_us | L21: passable | M21: =IFERROR(_xlfn.XLOOKUP(B21,feature_catalog!B:B,feature_catalog!B:B),"") -> xa_us_p90
A22: assists | B22: ast_p90 | C22: vol | D22: Dernière action (passe, déviation, ou toute autre touche) menant directement au but du receveur. Si la passe décisive est déviée par un adversaire, une 'fantasy assist' est comptée pour le rating mais pas dans les stats officielles. | E22: De Bruyne centre, Haaland marque de la tête = assist De Bruyne. Si un défenseur dévie le centre et Haaland marque = pas d'assist officiel | F22: W|AM|CM|CF|FB | G22: FALSE | H22: feat_ast_p90 | I22: z_ast_p90 | J22: assists | L22: important | M22: =IFERROR(_xlfn.XLOOKUP(B22,feature_catalog!B:B,feature_catalog!B:B),"") -> ast_p90
A23: keyPasses | B23: key_passes_p90 | C23: vol | D23: Passe menant directement à une tentative de but de l'équipe, sans être une passe décisive officielle (le tir ne se transforme pas en but). Critère : la passe doit être la dernière avant le tir. | E23: Ødegaard joue une passe à Saka qui tire, gardien arrête = 1 key pass pour Ødegaard. Si Saka marque = assist, pas key pass | F23: AM|CM|W|CF|FB | G23: FALSE | H23: feat_key_passes_p90 | I23: z_key_passes_p90 | J23: keyPasses | L23: important | M23: =IFERROR(_xlfn.XLOOKUP(B23,feature_catalog!B:B,feature_catalog!B:B),"") -> key_passes_p90
A24: accurateFinalThirdPasses | B24: passes_f3_p90 | C24: vol | D24: Passes dont le point d'arrivée se situe dans le dernier tiers du terrain (33m finaux). Mesure la capacité à faire progresser le jeu vers l'avant. Ne requiert pas que la passe soit une passe clé. | E24: Busquets joue une passe depuis son propre camp vers Pedri dans le dernier tiers = 1 passToFinalThird | F24: CM|DM|CB|AM | G24: FALSE | H24: feat_passes_f3_p90 | I24: z_passes_f3_p90 | J24: accurateFinalThirdPasses | K24: 2 | L24: important | M24: =IFERROR(_xlfn.XLOOKUP(B24,feature_catalog!B:B,feature_catalog!B:B),"") -> passes_f3_p90
A25: successfulDribbles | B25: dribbles_p90 | C25: vol | D25: Dribbles réussis — tentatives où le joueur bat l'adversaire en conservant la possession. Échoué si le dribbleur est taclé ou si le ballon s'éloigne trop (overrun). | E25: Neymar tente 8 dribbles, en réussit 6 = 6 successfulDribbles | F25: W|CF|AM|CM | G25: FALSE | H25: feat_dribbles_p90 | I25: z_dribbles_p90 | J25: successfulDribbles | K25: =IFERROR(VLOOKUP(J25,lateral_classique!$A:$K,11,0),"") | L25: important | M25: =IFERROR(_xlfn.XLOOKUP(B25,feature_catalog!B:B,feature_catalog!B:B),"") -> dribbles_p90
A26: successfulDribblesPercentage | B26: dribble_pct | C26: pct | D26: Dribbles réussis sur dribbles tentés. Un dribble est réussi si le joueur bat l'adversaire en conservant la possession. Échoué si le dribbleur est taclé ou si le ballon s'éloigne trop (overrun). | E26: Neymar tente 8 dribbles, en réussit 6 = 75%. Valeur top ailier PL ≈ 55-65% | F26: W|CF|AM | G26: FALSE | H26: feat_dribble_pct | I26: z_dribble_pct | J26: successfulDribblesPercentage | K26: =IFERROR(VLOOKUP(J26,lateral_classique!$A:$K,11,0),"") | L26: passable | M26: =IFERROR(_xlfn.XLOOKUP(B26,feature_catalog!B:B,feature_catalog!B:B),"") -> dribble_pct
A27: touches | B27: touches_p90 | C27: vol | D27: Somme de tous les événements où le joueur touche le ballon — passe, tir, contrôle, dégagement, etc. Si un joueur contrôle puis passe, c'est 1 touche (l'action complète), pas 2. | E27: Iniesta reçoit, contrôle et passe en une action fluide = 1 touch. Un défenseur qui dévie involontairement un tir = 1 touch | F27: CF|CM|DM|AM|W | G27: FALSE | H27: feat_touches_p90 | I27: z_touches_p90 | J27: touches | K27: =IFERROR(VLOOKUP(J27,lateral_classique!$A:$K,11,0),"") | L27: passable | M27: =IFERROR(_xlfn.XLOOKUP(B27,feature_catalog!B:B,feature_catalog!B:B),"") -> touches_p90
